Workbook

Sheet Composition
A2: =SUM(B3:D12) -> 1.7939574e+08 | B2: Developed | C2: Emerging Markets | D2: Frontier Markets | E2: Developed | F2: Emerging Markets | G2: Frontier Markets | H2: Developed | I2: Emerging Markets | J2: Frontier Markets | P2: =Bonds!BP107 -> Industry | Q2: =Bonds!BQ107 -> Market Value | R2: =Bonds!BR107 -> % | T2: =Bonds!BT107 -> Country | U2: =Bonds!BU107 -> Market Value | V2: =Bonds!BV107 -> % | X2: =Bonds!BX107 -> Country | Y2: =Bonds!BY107 -> Government | Z2: =Bonds!BZ107 -> AT1 | AA2: =Bonds!CA107 -> Oil and Gas Extraction and Refining | AB2: =Bonds!CB107 -> Banks | AC2: =Bonds!CC107 -> Power | AD2: =Bonds!CD107 -> Chemical and petrochemical industry | AE2: =Bonds!CE107 -> Non-ferrous metals | AF2: =Bonds!CF107 -> Other
A3: Bonds | B3: 34561291 | C3: 33032532 | D3: 4161889.2 | E3: =B3/$A$2 -> 0.19265392 | F3: =C3/$A$2 -> 0.18413221 | G3: =D3/$A$2 -> 0.023199488 | H3: =B3/SUM($B3:$D3) -> 0.48165212 | I3: =C3/SUM($B3:$D3) -> 0.46034707 | J3: =D3/SUM($B3:$D3) -> 0.058000807 | P3: =Bonds!BP108 -> Government | Q3: =Bonds!BQ108 -> 16365970 | R3: =Bonds!BR108 -> 0.22814422 | T3: =Bonds!BT108 -> Brazil | U3: =Bonds!BU108 -> 8799972.8 | V3: =Bonds!BV108 -> 0.12267301 | X3: =Bonds!BX108 -> Brazil | Y3: =Bonds!BY108 -> 0.025547867 | Z3: =Bonds!BZ108 -> 0 | AA3: =Bonds!CA108 -> 0.060261318 | AB3: =Bonds!CB108 -> 0 | AC3: =Bonds!CC108 -> 0.0057604761 | AD3: =Bonds!CD108 -> 0 | AE3: =Bonds!CE108 -> 0 | AF3: =Bonds!CF108 -> 0.031103353
A4: Bonds ETFs | B4: 14063941 | C4: 14582344 | D4: 1000000 | E4: =B4/$A$2 -> 0.078396186 | F4: =C4/$A$2 -> 0.081285903 | G4: =D4/$A$2 -> 0.0055742686 | H4: =B4/SUM($B4:$D4) -> 0.47439135 | I4: =C4/SUM($B4:$D4) -> 0.49187761 | J4: =D4/SUM($B4:$D4) -> 0.033731039 | P4: =Bonds!BP109 -> AT1 | Q4: =Bonds!BQ109 -> 10684224 | R4: =Bonds!BR109 -> 0.14893977 | T4: =Bonds!BT109 -> France | U4: =Bonds!BU109 -> 6570155 | V4: =Bonds!BV109 -> 0.091589 | X4: =Bonds!BX109 -> France | Y4: =Bonds!BY109 -> 0 | Z4: =Bonds!BZ109 -> 0.037596984 | AA4: =Bonds!CA109 -> 0 | AB4: =Bonds!CB109 -> 0 | AC4: =Bonds!CC109 -> 0.02395279 | AD4: =Bonds!CD109 -> 0 | AE4: =Bonds!CE109 -> 0 | AF4: =Bonds!CF109 -> 0.030039226
A5: Private Credit | B5: =9770768.704733-1484693 -> 8286075.7 | E5: =B5/$A$2 -> 0.046188811 | F5: =C5/$A$2 -> 0 | G5: =D5/$A$2 -> 0 | H5: =B5/SUM($B5:$D5) -> 1 | I5: =C5/SUM($B5:$D5) -> 0 | J5: =D5/SUM($B5:$D5) -> 0 | P5: =Bonds!BP110 -> Oil and Gas Extraction and Refining | Q5: =Bonds!BQ110 -> 9318956.9 | R5: =Bonds!BR110 -> 0.12990773 | T5: =Bonds!BT110 -> Mexico | U5: =Bonds!BU110 -> 6454864.9 | V5: =Bonds!BV110 -> 0.089981838 | X5: =Bonds!BX110 -> Mexico | Y5: =Bonds!BY110 -> 0.066445955 | Z5: =Bonds!BZ110 -> 0 | AA5: =Bonds!CA110 -> 0.012659013 | AB5: =Bonds!CB110 -> 0 | AC5: =Bonds!CC110 -> 0.01087687 | AD5: =Bonds!CD110 -> 0 | AE5: =Bonds!CE110 -> 0 | AF5: =Bonds!CF110 -> 0
A6: Equity | B6: 9121276.6 | C6: 1411825.5 | E6: =B6/$A$2 -> 0.050844445 | F6: =C6/$A$2 -> 0.0078698944 | G6: =D6/$A$2 -> 0 | H6: =B6/SUM($B6:$D6) -> 0.86596299 | I6: =C6/SUM($B6:$D6) -> 0.13403701 | J6: =D6/SUM($B6:$D6) -> 0 | P6: =Bonds!BP111 -> Banks | Q6: =Bonds!BQ111 -> 8751754.5 | R6: =Bonds!BR111 -> 0.12200084 | T6: =Bonds!BT111 -> USA | U6: =Bonds!BU111 -> 7734546 | V6: =Bonds!BV111 -> 0.10782079 | X6: =Bonds!BX111 -> USA | Y6: =Bonds!BY111 -> 0.02508378 | Z6: =Bonds!BZ111 -> 0 | AA6: =Bonds!CA111 -> 0 | AB6: =Bonds!CB111 -> 0.027313387 | AC6: =Bonds!CC111 -> 0 | AD6: =Bonds!CD111 -> 0.0052281002 | AE6: =Bonds!CE111 -> 0 | AF6: =Bonds!CF111 -> 0.050195527
A7: Equity ETF | B7: 9194626 | C7: 4072892.6 | E7: =B7/$A$2 -> 0.051253314 | F7: =C7/$A$2 -> 0.022703397 | G7: =D7/$A$2 -> 0 | H7: =B7/SUM($B7:$D7) -> 0.69301776 | I7: =C7/SUM($B7:$D7) -> 0.30698224 | J7: =D7/SUM($B7:$D7) -> 0 | P7: =Bonds!BP112 -> Power | Q7: =Bonds!BQ112 -> 3942420.6 | R7: =Bonds!BR112 -> 0.054957967 | T7: =Bonds!BT112 -> United Kingdom | U7: =Bonds!BU112 -> 6054139.9 | V7: =Bonds!BV112 -> 0.084395667 | X7: =Bonds!BX112 -> United Kingdom | Y7: =Bonds!BY112 -> 0 | Z7: =Bonds!BZ112 -> 0.071513246 | AA7: =Bonds!CA112 -> 0 | AB7: =Bonds!CB112 -> 0.012882422 | AC7: =Bonds!CC112 -> 0 | AD7: =Bonds!CD112 -> 0 | AE7: =Bonds!CE112 -> 0 | AF7: =Bonds!CF112 -> 0
A8: Option | B8: 333276 | C8: 0 | E8: =B8/$A$2 -> 0.0018577699 | F8: =C8/$A$2 -> 0 | G8: =D8/$A$2 -> 0 | H8: =B8/SUM($B8:$D8) -> 1 | I8: =C8/SUM($B8:$D8) -> 0 | J8: =D8/SUM($B8:$D8) -> 0 | P8: =Bonds!BP113 -> Chemical and petrochemical industry | Q8: =Bonds!BQ113 -> 4080698.2 | R8: =Bonds!BR113 -> 0.056885579 | T8: =Bonds!BT113 -> Turkey | U8: =Bonds!BU113 -> 4337997.1 | V8: =Bonds!BV113 -> 0.060472366 | X8: =Bonds!BX113 -> Turkey | Y8: =Bonds!BY113 -> 0.039671977 | Z8: =Bonds!BZ113 -> 0 | AA8: =Bonds!CA113 -> 0 | AB8: =Bonds!CB113 -> 0 | AC8: =Bonds!CC113 -> 0 | AD8: =Bonds!CD113 -> 0 | AE8: =Bonds!CE113 -> 0 | AF8: =Bonds!CF113 -> 0.020800389
A9: JPM Modules | B9: ='JPM - DP (3R)'!W5 -> 13293212 | E9: =B9/$A$2 -> 0.074099934 | F9: =C9/$A$2 -> 0 | G9: =D9/$A$2 -> 0 | P9: =Bonds!BP114 -> Non-ferrous metals | Q9: =Bonds!BQ114 -> 3728370.1 | R9: =Bonds!BR114 -> 0.051974069 | T9: =Bonds!BT114 -> Netherlands | U9: =Bonds!BU114 -> 3904314.1 | V9: =Bonds!BV114 -> 0.054426757 | X9: =Bonds!BX114 -> Netherlands | Y9: =Bonds!BY114 -> 0 | Z9: =Bonds!BZ114 -> 0 | AA9: =Bonds!CA114 -> 0 | AB9: =Bonds!CB114 -> 0.054426757 | AC9: =Bonds!CC114 -> 0 | AD9: =Bonds!CD114 -> 0 | AE9: =Bonds!CE114 -> 0 | AF9: =Bonds!CF114 -> 0
A10: Alternative Assets | B10: ='Alternative assets'!J20 -> 0 | C10: ='Alternative assets'!J21 -> 0 | E10: =B10/$A$2 -> 0 | F10: =C10/$A$2 -> 0 | G10: =D10/$A$2 -> 0 | H10: =IFERROR(B10/SUM($B10:$D10),0) -> 0 | I10: =IFERROR(C10/SUM($B10:$D10),0) -> 0 | J10: =IFERROR(D10/SUM($B10:$D10),0) -> 0 | P10: =Bonds!BP115 -> Insurance and Reinsurance | Q10: =Bonds!BQ115 -> 1870799.9 | R10: =Bonds!BR115 -> 0.026079247 | T10: =Bonds!BT115 -> India | U10: =Bonds!BU115 -> 3817299.5 | V10: =Bonds!BV115 -> 0.053213759 | X10: =Bonds!BX115 -> India | Y10: =Bonds!BY115 -> 0 | Z10: =Bonds!BZ115 -> 0 | AA10: =Bonds!CA115 -> 0 | AB10: =Bonds!CB115 -> 0 | AC10: =Bonds!CC115 -> 0 | AD10: =Bonds!CD115 -> 0 | AE10: =Bonds!CE115 -> 0.043237562 | AF10: =Bonds!CF115 -> 0.0099761968
A11: Cash | B11: 10854064 | E11: =B11/$A$2 -> 0.06050347 | F11: =C11/$A$2 -> 0 | G11: =D11/$A$2 -> 0 | H11: =B11/SUM($B11:$D11) -> 1 | I11: =C11/SUM($B11:$D11) -> 0 | J11: =D11/SUM($B11:$D11) -> 0 | P11: =Bonds!BP116 -> Food and Beverage Production | Q11: =Bonds!BQ116 -> 1365730.6 | R11: =Bonds!BR116 -> 0.0190385 | T11: =Bonds!BT116 -> Colombia | U11: =Bonds!BU116 -> 3641957.5 | V11: =Bonds!BV116 -> 0.050769464 | X11: =Bonds!BX116 -> Colombia | Y11: =Bonds!BY116 -> 0.021952752 | Z11: =Bonds!BZ116 -> 0 | AA11: =Bonds!CA116 -> 0.020430057 | AB11: =Bonds!CB116 -> 0 | AC11: =Bonds!CC116 -> 0 | AD11: =Bonds!CD116 -> 0 | AE11: =Bonds!CE116 -> 0 | AF11: =Bonds!CF116 -> 0.0083866548
A12: RE proceeds 2026 | B12: 21426488 | E12: =B12/$A$2 -> 0.119437 | F12: =C12/$A$2 -> 0 | G12: =D12/$A$2 -> 0 | H12: =B12/SUM($B12:$D12) -> 1 | I12: =C12/SUM($B12:$D12) -> 0 | J12: =D12/SUM($B12:$D12) -> 0 | P12: =Bonds!BP117 -> Other Financial Institutions | Q12: =Bonds!BQ117 -> 1310781.8 | R12: =Bonds!BR117 -> 0.018272505 | T12: =Bonds!BT117 -> Israel | U12: =Bonds!BU117 -> 3178434.4 | V12: =Bonds!BV117 -> 0.044307879 | X12: =Bonds!BX117 -> Israel | Y12: =Bonds!BY117 -> 0.0084761738 | Z12: =Bonds!BZ117 -> 0 | AA12: =Bonds!CA117 -> 0.0087005407 | AB12: =Bonds!CB117 -> 0 | AC12: =Bonds!CC117 -> 0 | AD12: =Bonds!CD117 -> 0.014751592 | AE12: =Bonds!CE117 -> 0 | AF12: =Bonds!CF117 -> 0.012379573
P13: =Bonds!BP118 -> Ferrous metals | Q13: =Bonds!BQ118 -> 1289932.1 | R13: =Bonds!BR118 -> 0.017981857 | T13: =Bonds!BT118 -> Japan | U13: =Bonds!BU118 -> 2656651.1 | V13: =Bonds!BV118 -> 0.037034137 | X13: =Bonds!BX118 -> Japan | Y13: =Bonds!BY118 -> 0 | Z13: =Bonds!BZ118 -> 0 | AA13: =Bonds!CA118 -> 0 | AB13: =Bonds!CB118 -> 0.027378277 | AC13: =Bonds!CC118 -> 0 | AD13: =Bonds!CD118 -> 0 | AE13: =Bonds!CE118 -> 0 | AF13: =Bonds!CF118 -> 0.0096558597
A14: Total | B14: =SUM(B3:B12) -> 1.2113425e+08 | C14: =SUM(C3:C12) -> 53099595 | D14: =SUM(D3:D12) -> 5161889.2 | E14: =SUM(E3:E12) -> 0.67523484 | F14: =SUM(F3:F12) -> 0.2959914 | G14: =SUM(G3:G12) -> 0.028773757 | P14: =Bonds!BP119 -> Communication Services | Q14: =Bonds!BQ119 -> 1067662.5 | R14: =Bonds!BR119 -> 0.014883384 | T14: =Bonds!BT119 -> Austria | U14: =Bonds!BU119 -> 1810912.9 | V14: =Bonds!BV119 -> 0.025244413 | X14: =Bonds!BX119 -> Austria | Y14: =Bonds!BY119 -> 0 | Z14: =Bonds!BZ119 -> 0.025244413 | AA14: =Bonds!CA119 -> 0 | AB14: =Bonds!CB119 -> 0 | AC14: =Bonds!CC119 -> 0 | AD14: =Bonds!CD119 -> 0 | AE14: =Bonds!CE119 -> 0 | AF14: =Bonds!CF119 -> 0
P15: =Bonds!BP120 -> Air Transportation | Q15: =Bonds!BQ120 -> 707432.99 | R15: =Bonds!BR120 -> 0.0098617278 | T15: =Bonds!BT120 -> South Africa | U15: =Bonds!BU120 -> 2274733.8 | V15: =Bonds!BV120 -> 0.031710149 | X15: =Bonds!BX120 -> South Africa | Y15: =Bonds!BY120 -> 0.0090548995 | Z15: =Bonds!BZ120 -> 0 | AA15: =Bonds!CA120 -> 0 | AB15: =Bonds!CB120 -> 0 | AC15: =Bonds!CC120 -> 0 | AD15: =Bonds!CD120 -> 0.0098287099 | AE15: =Bonds!CE120 -> 0 | AF15: =Bonds!CF120 -> 0.01282654
P16: =Bonds!BP121 -> Holding Companies | Q16: =Bonds!BQ121 -> 920114.38 | R16: =Bonds!BR121 -> 0.01282654 | T16: =Bonds!BT121 -> Morocco | U16: =Bonds!BU121 -> 1942386.7 | V16: =Bonds!BV121 -> 0.027077177 | X16: =Bonds!BX121 -> Morocco | Y16: =Bonds!BY121 -> 0 | Z16: =Bonds!BZ121 -> 0 | AA16: =Bonds!CA121 -> 0 | AB16: =Bonds!CB121 -> 0 | AC16: =Bonds!CC121 -> 0 | AD16: =Bonds!CD121 -> 0.027077177 | AE16: =Bonds!CE121 -> 0 | AF16: =Bonds!CF121 -> 0
P17: =Bonds!BP122 -> Media | Q17: =Bonds!BQ122 -> 857284.4 | R17: =Bonds!BR122 -> 0.01195068 | T17: =Bonds!BT122 -> Chile | U17: =Bonds!BU122 -> 1334148 | V17: =Bonds!BV122 -> 0.018598234 | X17: =Bonds!BX122 -> Chile | Y17: =Bonds!BY122 -> 0 | Z17: =Bonds!BZ122 -> 0 | AA17: =Bonds!CA122 -> 0 | AB17: =Bonds!CB122 -> 0 | AC17: =Bonds!CC122 -> 0 | AD17: =Bonds!CD122 -> 0 | AE17: =Bonds!CE122 -> 0.0087365063 | AF17: =Bonds!CF122 -> 0.0098617278
P18: =Bonds!BP123 -> Transportation Support Activities | Q18: =Bonds!BQ123 -> 715644.44 | R18: =Bonds!BR123 -> 0.0099761968 | T18: =Bonds!BT123 -> Romania | U18: =Bonds!BU123 -> 1442145.3 | V18: =Bonds!BV123 -> 0.020103733 | X18: =Bonds!BX123 -> Romania | Y18: =Bonds!BY123 -> 0.020103733 | Z18: =Bonds!BZ123 -> 0 | AA18: =Bonds!CA123 -> 0 | AB18: =Bonds!CB123 -> 0 | AC18: =Bonds!CC123 -> 0 | AD18: =Bonds!CD123 -> 0 | AE18: =Bonds!CE123 -> 0 | AF18: =Bonds!CF123 -> 0
P19: =Bonds!BP124 -> Online Retail | Q19: =Bonds!BQ124 -> 692665 | R19: =Bonds!BR124 -> 0.0096558597 | T19: =Bonds!BT124 -> Kazakhstan | U19: =Bonds!BU124 -> 1393365.6 | V19: =Bonds!BV124 -> 0.019423737 | X19: =Bonds!BX124 -> Kazakhstan | Y19: =Bonds!BY124 -> 0 | Z19: =Bonds!BZ124 -> 0 | AA19: =Bonds!CA124 -> 0.019423737 | AB19: =Bonds!CB124 -> 0 | AC19: =Bonds!CC124 -> 0 | AD19: =Bonds!CD124 -> 0 | AE19: =Bonds!CE124 -> 0 | AF19: =Bonds!CF124 -> 0
P20: =Bonds!BP125 -> Motor Vehicle Production | Q20: =Bonds!BQ125 -> 596426.67 | R20: =Bonds!BR125 -> 0.0083142821 | T20: =Bonds!BT125 -> Switzerland | U20: =Bonds!BU125 -> 1046267.2 | V20: =Bonds!BV125 -> 0.014585131 | X20: =Bonds!BX125 -> Switzerland | Y20: =Bonds!BY125 -> 0 | Z20: =Bonds!BZ125 -> 0.014585131 | AA20: =Bonds!CA125 -> 0 | AB20: =Bonds!CB125 -> 0 | AC20: =Bonds!CC125 -> 0 | AD20: =Bonds!CD125 -> 0 | AE20: =Bonds!CE125 -> 0 | AF20: =Bonds!CF125 -> 0
P21: =Bonds!BP126 -> Leasing and Rental | Q21: =Bonds!BQ126 -> 566155.57 | R21: =Bonds!BR126 -> 0.0078922982 | T21: =Bonds!BT126 -> Panama | U21: =Bonds!BU126 -> 846983.09 | V21: =Bonds!BV126 -> 0.011807078 | X21: =Bonds!BX126 -> Panama | Y21: =Bonds!BY126 -> 0.011807078 | Z21: =Bonds!BZ126 -> 0 | AA21: =Bonds!CA126 -> 0 | AB21: =Bonds!CB126 -> 0 | AC21: =Bonds!CC126 -> 0 | AD21: =Bonds!CD126 -> 0 | AE21: =Bonds!CE126 -> 0 | AF21: =Bonds!CF126 -> 0
P22: =Bonds!BP127 -> Energy | Q22: =Bonds!BQ127 -> 601618.33 | R22: =Bonds!BR127 -> 0.0083866548 | T22: =Bonds!BT127 -> Italy | U22: =Bonds!BU127 -> 542380.34 | V22: =Bonds!BV127 -> 0.0075608678 | X22: =Bonds!BX127 -> Italy | Y22: =Bonds!BY127 -> 0 | Z22: =Bonds!BZ127 -> 0 | AA22: =Bonds!CA127 -> 0 | AB22: =Bonds!CB127 -> 0 | AC22: =Bonds!CC127 -> 0.0075608678 | AD22: =Bonds!CD127 -> 0 | AE22: =Bonds!CE127 -> 0 | AF22: =Bonds!CF127 -> 0
P23: =Bonds!BP128 -> Fertilizers | Q23: =Bonds!BQ128 -> 440108.74 | R23: =Bonds!BR128 -> 0.0061351854 | T23: =Bonds!BT128 -> Denmark | U23: =Bonds!BU128 -> 488298.86 | V23: =Bonds!BV128 -> 0.0068069633 | X23: =Bonds!BX128 -> Denmark | Y23: =Bonds!BY128 -> 0 | Z23: =Bonds!BZ128 -> 0 | AA23: =Bonds!CA128 -> 0 | AB23: =Bonds!CB128 -> 0 | AC23: =Bonds!CC128 -> 0.0068069633 | AD23: =Bonds!CD128 -> 0 | AE23: =Bonds!CE128 -> 0 | AF23: =Bonds!CF128 -> 0
P24: =Bonds!BP129 -> Mining: Other | Q24: =Bonds!BQ129 -> 418186.67 | R24: =Bonds!BR129 -> 0.0058295883 | T24: =Bonds!BT129 -> Hungary | U24: =Bonds!BU129 -> 440108.74 | V24: =Bonds!BV129 -> 0.0061351854 | X24: =Bonds!BX129 -> Hungary | Y24: =Bonds!BY129 -> 0 | Z24: =Bonds!BZ129 -> 0 | AA24: =Bonds!CA129 -> 0 | AB24: =Bonds!CB129 -> 0 | AC24: =Bonds!CC129 -> 0 | AD24: =Bonds!CD129 -> 0 | AE24: =Bonds!CE129 -> 0 | AF24: =Bonds!CF129 -> 0.0061351854
P25: =Bonds!BP130 -> Technology | Q25: =Bonds!BQ130 -> 801208.72 | R25: =Bonds!BR130 -> 0.011168976 | T25: =Bonds!BT130 -> Canada | U25: =Bonds!BU130 -> 218691.11 | V25: =Bonds!BV130 -> 0.0030485887 | X25: =Bonds!BX130 -> Canada | Y25: =Bonds!BY130 -> 0 | Z25: =Bonds!BZ130 -> 0 | AA25: =Bonds!CA130 -> 0.0030485887 | AB25: =Bonds!CB130 -> 0 | AC25: =Bonds!CC130 -> 0 | AD25: =Bonds!CD130 -> 0 | AE25: =Bonds!CE130 -> 0 | AF25: =Bonds!CF130 -> 0
P26: =Bonds!BP131 -> Semiconductors | Q26: =Bonds!BQ131 -> 356980 | R26: =Bonds!BR131 -> 0.0049763577 | T26: =Bonds!BT131 -> Indonesia | U26: =Bonds!BU131 -> 418186.67 | V26: =Bonds!BV131 -> 0.0058295883 | X26: =Bonds!BX131 -> Indonesia | Y26: =Bonds!BY131 -> 0 | Z26: =Bonds!BZ131 -> 0 | AA26: =Bonds!CA131 -> 0 | AB26: =Bonds!CB131 -> 0 | AC26: =Bonds!CC131 -> 0 | AD26: =Bonds!CD131 -> 0 | AE26: =Bonds!CE131 -> 0 | AF26: =Bonds!CF131 -> 0.0058295883
P27: =Bonds!BP132 -> Utilities | Q27: =Bonds!BQ132 -> 284069.89 | R27: =Bonds!BR132 -> 0.0039599792 | T27: =Bonds!BT132 -> Australia | U27: =Bonds!BU132 -> 386256.67 | V27: =Bonds!BV132 -> 0.005384479 | X27: =Bonds!BX132 -> Australia | Y27: =Bonds!BY132 -> 0 | Z27: =Bonds!BZ132 -> 0 | AA27: =Bonds!CA132 -> 0.005384479 | AB27: =Bonds!CB132 -> 0 | AC27: =Bonds!CC132 -> 0 | AD27: =Bonds!CD132 -> 0 | AE27: =Bonds!CE132 -> 0 | AF27: =Bonds!CF132 -> 0
T33: =Bonds!BT138 -> Market | U33: =Bonds!BU138 -> Market Value | V33: =Bonds!BV138 -> % | X33: =Bonds!BX138 -> Market | Y33: =Bonds!BY138 -> Government | Z33: =Bonds!BZ138 -> AT1 | AA33: =Bonds!CA138 -> Oil and Gas Extraction and Refining | AB33: =Bonds!CB138 -> Banks | AC33: =Bonds!CC138 -> Power | AD33: =Bonds!CD138 -> Chemical and petrochemical industry | AE33: =Bonds!CE138 -> Non-ferrous metals | AF33: =Bonds!CF138 -> Other
T34: =Bonds!BT139 -> Developed | U34: =Bonds!BU139 -> 34591048 | V34: =Bonds!BV139 -> 0.48220468 | X34: =Bonds!BX139 -> Emerging Markets | Y34: =Bonds!BY139 -> 0.18277718 | Z34: =Bonds!BZ139 -> 0 | AA34: =Bonds!CA139 -> 0.093350388 | AB34: =Bonds!CB139 -> 0 | AC34: =Bonds!CC139 -> 0.016637346 | AD34: =Bonds!CD139 -> 0.0098287099 | AE34: =Bonds!CE139 -> 0.051974069 | AF34: =Bonds!CF139 -> 0.12763698
T35: =Bonds!BT140 -> Emerging Markets | U35: =Bonds!BU140 -> 32961414 | V35: =Bonds!BV140 -> 0.45948733 | X35: =Bonds!BX140 -> Developed | Y35: =Bonds!BY140 -> 0.033559954 | Z35: =Bonds!BZ140 -> 0.14893977 | AA35: =Bonds!CA140 -> 0.017133608 | AB35: =Bonds!CB140 -> 0.12200084 | AC35: =Bonds!CC140 -> 0.038320621 | AD35: =Bonds!CD140 -> 0.019979692 | AE35: =Bonds!CE140 -> 0 | AF35: =Bonds!CF140 -> 0.079552839
T36: =Bonds!BT141 -> Frontier Markets | U36: =Bonds!BU141 -> 4182735.4 | V36: =Bonds!BV141 -> 0.058307993 | X36: =Bonds!BX141 -> Frontier Markets | Y36: =Bonds!BY141 -> 0.011807078 | Z36: =Bonds!BZ141 -> 0 | AA36: =Bonds!CA141 -> 0.019423737 | AB36: =Bonds!CB141 -> 0 | AC36: =Bonds!CC141 -> 0 | AD36: =Bonds!CD141 -> 0.027077177 | AE36: =Bonds!CE141 -> 0 | AF36: =Bonds!CF141 -> 0
T38: =Bonds!BT143 -> Market | U38: =Bonds!BU143 -> Market Value | V38: =Bonds!BV143 -> %
T39: =Bonds!BT144 -> USA | U39: =Bonds!BU144 -> 7734546 | V39: =Bonds!BV144 -> 0.10782079
T40: =Bonds!BT145 -> United Kingdom | U40: =Bonds!BU145 -> 6054139.9 | V40: =Bonds!BV145 -> 0.084395667
T41: =Bonds!BT146 -> Europe | U41: =Bonds!BU146 -> 12732695 | V41: =Bonds!BV146 -> 0.17749578
T42: =Bonds!BT147 -> Japan | U42: =Bonds!BU147 -> 2656651.1 | V42: =Bonds!BV147 -> 0.037034137
T43: =Bonds!BT148 -> Israel | U43: =Bonds!BU148 -> 3178434.4 | V43: =Bonds!BV148 -> 0.044307879
T44: =Bonds!BT149 -> Other DM | U44: =Bonds!BU149 -> 604947.78 | V44: =Bonds!BV149 -> 0.0084330677
T45: =Bonds!BT150 -> Brazil | U45: =Bonds!BU150 -> 8799972.8 | V45: =Bonds!BV150 -> 0.12267301
T46: =Bonds!BT151 -> Mexico | U46: =Bonds!BU151 -> 6454864.9 | V46: =Bonds!BV151 -> 0.089981838
T47: =Bonds!BT152 -> Turkey | U47: =Bonds!BU152 -> 4337997.1 | V47: =Bonds!BV152 -> 0.060472366
T48: =Bonds!BT153 -> India | U48: =Bonds!BU153 -> 3817299.5 | V48: =Bonds!BV153 -> 0.053213759
T49: =Bonds!BT154 -> Colombia | U49: =Bonds!BU154 -> 3641957.5 | V49: =Bonds!BV154 -> 0.050769464
... T51: =Bonds!BT156 -> Frontier Markets | U51: =Bonds!BU156 -> 4182735.4 | V51: =Bonds!BV156 -> 0.058307993

Sheet Results
B2: All-portfolio | S2: Portfolio Loans, 2025
B3: Currency | C3: Weights | D3: AW coupon (CCY) | E3: AW Current yield (CCY) | F3: Total inflows (CCY) | G3: Total inflows (USD) | H3: Total MV of positions, CCY | I3: Total MV of positions (USD) | S3: CCY | T3: Cost of debt, 2025 | U3: Curent debt CCY | V3: Current Debt USD | W3: Annual interest, CCY | X3: Annual interest, USD | Y3: Total coupon, CCY
B4: USD | C4: =I4/$I$11 -> #VALUE! | D4: =IFERROR(( SUMIFS(T_Bonds[Coupon in Loc.Curr],T_Bonds[Risk CCY],Results!$B4)+ SUMIFS(T_bETFs[Coupon in CCY],T_bETFs[Risk CCY],$B4)+ SUMIFS(T_deposits[Coupon in Loc.Curr],T_deposits[Risk CCY],$B4)+ SUMIFS(T_Eq[Dividend in Loc.Curr],T_Eq[Risk CCY],B4))/ (SUMIFS(T_Bonds[Quantity],T_Bonds[Risk CCY],$B4)+ SUMIFS(T_bETFs[Market Value, CCY],T_bETFs[Risk CCY],B4)+ SUMIFS(T_deposits[Quantity],T_deposits[Risk CCY],B4)+ SUMIFS(T_Eq[Market value, CCY],T_Eq[Risk CCY],B4)),"") | E4: =IFERROR((SUMIFS(T_Bonds[Coupon in Loc.Curr],T_Bonds[Risk CCY],Results!$B4)+ SUMIFS(T_bETFs[Coupon in CCY],T_bETFs[Risk CCY],$B4)+ SUMIFS(T_deposits[Coupon in Loc.Curr],T_deposits[Risk CCY],$B4)+ SUMIFS(T_Eq[Dividend in Loc.Curr],T_Eq[Risk CCY],B4))/ (SUMIFS(T_Bonds[Cost value],T_Bonds[Risk CCY],$B4)+ SUMIFS(T_bETFs[Market Value, CCY],T_bETFs[Risk CCY],$B4)+ SUMIFS(T_deposits[Quantity],T_deposits[Risk CCY],$B4)+ SUMIFS(T_Eq[Market value, CCY],T_Eq[Risk CCY],B4)),"") | F4: =IFERROR( SUMIFS(T_Bonds[Coupon in Loc.Curr],T_Bonds[Risk CCY],Results!$B4)+ SUMIFS(T_bETFs[Coupon in CCY],T_bETFs[Risk CCY],$B4)+ SUMIFS(T_deposits[Coupon in Loc.Curr],T_deposits[Risk CCY],$B4)+ SUMIFS(T_Eq[Dividend in Loc.Curr],T_Eq[Risk CCY],B4)+ SUMIFS('Real Estate'!X:X,'Real Estate'!D:D,B4),"") | G4: =IFERROR( SUMIFS(T_Bonds[Coupon in USD],T_Bonds[Risk CCY],Results!$B4)+ SUMIFS(T_bETFs[Coupon in USD],T_bETFs[Risk CCY],$B4)+ SUMIFS(T_deposits[Coupon in USD],T_deposits[Risk CCY],$B4)+ SUMIFS(T_Eq[Dividend in USD],T_Eq[Risk CCY],B4)+ SUMIFS('Real Estate'!Y:Y,'Real Estate'!D:D,B4),"") | H4: =IFERROR((SUMIFS(T_Bonds[Full MV in CCY],T_Bonds[Risk CCY],Results!$B4)+ SUMIFS(T_bETFs[Market value in CCY],T_bETFs[Risk CCY],$B4)+ SUMIFS(T_deposits[Market value in USD],T_deposits[Risk CCY],$B4)+ SUMIFS(T_Eq[Market value, CCY],T_Eq[Risk CCY],$B4)+ SUMIFS(T_AI[Market value in CCY],T_AI[Risk CCY],$B4)+ SUMIFS(Cash!F:F,Cash!E:E,$B4))+ SUMIFS('Real Estate'!$G:$G,'Real Estate'!$D:$D,B4)+ SUMIFS('JPM - DP (3R)'!$F:$F,'JPM - DP (3R)'!$C:$C,B4),"") | I4: =IFERROR((SUMIFS(T_Bonds[Full MV in USD],T_Bonds[Risk CCY],Results!$B4)+ SUMIFS(T_bETFs[Market value in USD],T_bETFs[Risk CCY],$B4)+ SUMIFS(T_deposits[Market value in USD],T_deposits[Risk CCY],$B4)+ SUMIFS(T_Eq[Market value, USD],T_Eq[Risk CCY],$B4)+ SUMIFS(T_AI[Market value in USD],T_AI[Risk CCY],$B4)+ SUMIFS(Cash!H:H,Cash!E:E,$B4)+ SUMIFS('Real Estate'!$F:$F,'Real Estate'!$D:$D,B4)+ SUMIFS('JPM - DP (3R)'!$J:$J,'JPM - DP (3R)'!$C:$C,Results!B4)),"") | S4: USD | T4: {=IFERROR(SUMPRODUCT(Loans!D:D,Loans!F:F,IF(Loans!C:C=LTV!F5,1,0))/SUMIFS(Loans!D:D,Loans!C:C,LTV!F5),0)} -> 0.044834337 | U4: =-SUMIFS(Loans!D:D,Loans!C:C,LTV!F5) -> 210492.39 | V4: =-SUMIFS(Loans!G:G,Loans!C:C,LTV!F5) -> 210492.39 | W4: =U4*T4 -> 9437.2868 | X4: =INDEX('Tech list'!$A$2:$C$8,MATCH(S4,'Tech list'!$A$2:$A$8,0),3)*W4 -> 9437.2868 | Y4: =Results!F4
B5: GBP | C5: =I5/$I$11 -> 0.91907904 | D5: =IFERROR((SUMIFS(T_Bonds[Coupon in Loc.Curr],T_Bonds[Risk CCY],Results!$B5)+SUMIFS(T_bETFs[Coupon in CCY],T_bETFs[Risk CCY],$B5)+SUMIFS(T_deposits[Coupon in Loc.Curr],T_deposits[Risk CCY],$B5)+SUMIFS(T_Eq[Dividend in Loc.Curr],T_Eq[Risk CCY],B5))/(SUMIFS(T_Bonds[Quantity],T_Bonds[Risk CCY],$B5)+SUMIFS(T_bETFs[Market Value, CCY],T_bETFs[Risk CCY],B5)+SUMIFS(T_deposits[Quantity],T_deposits[Risk CCY],B5)+SUMIFS(T_Eq[Market value, CCY],T_Eq[Risk CCY],B5)),"") -> 0.063007408 | E5: =IFERROR((SUMIFS(T_Bonds[Coupon in Loc.Curr],T_Bonds[Risk CCY],Results!$B5)+SUMIFS(T_bETFs[Coupon in CCY],T_bETFs[Risk CCY],$B5)+SUMIFS(T_deposits[Coupon in Loc.Curr],T_deposits[Risk CCY],$B5)+SUMIFS(T_Eq[Dividend in Loc.Curr],T_Eq[Risk CCY],B5))/ (SUMIFS(T_Bonds[Cost value],T_Bonds[Risk CCY],$B5)+SUMIFS(T_bETFs[Market Value, CCY],T_bETFs[Risk CCY],$B5)+SUMIFS(T_deposits[Quantity],T_deposits[Risk CCY],$B5)+SUMIFS(T_Eq[Market value, CCY],T_Eq[Risk CCY],B5)),"") -> 0.069515964 | F5: =IFERROR( SUMIFS(T_Bonds[Coupon in Loc.Curr],T_Bonds[Risk CCY],Results!$B5)+ SUMIFS(T_bETFs[Coupon in CCY],T_bETFs[Risk CCY],$B5)+ SUMIFS(T_deposits[Coupon in Loc.Curr],T_deposits[Risk CCY],$B5)+ SUMIFS(T_Eq[Dividend in Loc.Curr],T_Eq[Risk CCY],B5)+ SUMIFS('Real Estate'!X:X,'Real Estate'!D:D,B5),"") -> 1898227.5 | G5: =IFERROR( SUMIFS(T_Bonds[Coupon in USD],T_Bonds[Risk CCY],Results!$B5)+ SUMIFS(T_bETFs[Coupon in USD],T_bETFs[Risk CCY],$B5)+ SUMIFS(T_deposits[Coupon in USD],T_deposits[Risk CCY],$B5)+ SUMIFS(T_Eq[Dividend in USD],T_Eq[Risk CCY],B5)+ SUMIFS('Real Estate'!Y:Y,'Real Estate'!D:D,B5),"") -> 2538689.5 | H5: =IFERROR((SUMIFS(T_Bonds[Full MV in CCY],T_Bonds[Risk CCY],Results!$B5)+ SUMIFS(T_bETFs[Market value in CCY],T_bETFs[Risk CCY],$B5)+ SUMIFS(T_deposits[Market value in USD],T_deposits[Risk CCY],$B5)+ SUMIFS(T_Eq[Market value, CCY],T_Eq[Risk CCY],$B5)+ SUMIFS(T_AI[Market value in CCY],T_AI[Risk CCY],$B5)+ SUMIFS(Cash!F:F,Cash!E:E,$B5))+ SUMIFS('Real Estate'!$G:$G,'Real Estate'!$D:$D,B5)+ SUMIFS('JPM - DP (3R)'!$F:$F,'JPM - DP (3R)'!$C:$C,B5),"") -> 37611397 | I5: =IFERROR((SUMIFS(T_Bonds[Full MV in USD],T_Bonds[Risk CCY],Results!$B5)+ SUMIFS(T_bETFs[Market value in USD],T_bETFs[Risk CCY],$B5)+ SUMIFS(T_deposits[Market value in USD],T_deposits[Risk CCY],$B5)+ SUMIFS(T_Eq[Market value, USD],T_Eq[Risk CCY],$B5)+ SUMIFS(T_AI[Market value in USD],T_AI[Risk CCY],$B5)+ SUMIFS(Cash!H:H,Cash!E:E,$B5)+ SUMIFS('Real Estate'!$F:$F,'Real Estate'!$D:$D,B5)+ SUMIFS('JPM - DP (3R)'!$J:$J,'JPM - DP (3R)'!$C:$C,Results!B5)),"") -> 50301482 | S5: GBP | T5: {=IFERROR(SUMPRODUCT(Loans!D:D,Loans!F:F,IF(Loans!C:C=LTV!F6,1,0))/SUMIFS(Loans!D:D,Loans!C:C,LTV!F6),0)} -> 0.043572191 | U5: =-SUMIFS(Loans!D:D,Loans!C:C,LTV!F6) -> 1707086.5 | V5: =-SUMIFS(Loans!G:G,Loans!C:C,LTV!F6) -> 2283057.5 | W5: =U5*T5 -> 74381.498 | X5: =INDEX('Tech list'!$A$2:$C$8,MATCH(S5,'Tech list'!$A$2:$A$8,0),3)*W5 -> 99477.815 | Y5: =Results!F5 -> 1898227.5
B6: EUR | C6: =I6/$I$11 -> #VALUE! | D6: =IFERROR((SUMIFS(T_Bonds[Coupon in Loc.Curr],T_Bonds[Risk CCY],Results!$B6)+SUMIFS(T_bETFs[Coupon in CCY],T_bETFs[Risk CCY],$B6)+SUMIFS(T_deposits[Coupon in Loc.Curr],T_deposits[Risk CCY],$B6)+SUMIFS(T_Eq[Dividend in Loc.Curr],T_Eq[Risk CCY],B6))/(SUMIFS(T_Bonds[Quantity],T_Bonds[Risk CCY],$B6)+SUMIFS(T_bETFs[Market Value, CCY],T_bETFs[Risk CCY],B6)+SUMIFS(T_deposits[Quantity],T_deposits[Risk CCY],B6)+SUMIFS(T_Eq[Market value, CCY],T_Eq[Risk CCY],B6)),"") | E6: =IFERROR((SUMIFS(T_Bonds[Coupon in Loc.Curr],T_Bonds[Risk CCY],Results!$B6)+SUMIFS(T_bETFs[Coupon in CCY],T_bETFs[Risk CCY],$B6)+SUMIFS(T_deposits[Coupon in Loc.Curr],T_deposits[Risk CCY],$B6)+SUMIFS(T_Eq[Dividend in Loc.Curr],T_Eq[Risk CCY],B6))/ (SUMIFS(T_Bonds[Cost value],T_Bonds[Risk CCY],$B6)+SUMIFS(T_bETFs[Market Value, CCY],T_bETFs[Risk CCY],$B6)+SUMIFS(T_deposits[Quantity],T_deposits[Risk CCY],$B6)+SUMIFS(T_Eq[Market value, CCY],T_Eq[Risk CCY],B6)),"") | F6: =IFERROR( SUMIFS(T_Bonds[Coupon in Loc.Curr],T_Bonds[Risk CCY],Results!$B6)+ SUMIFS(T_bETFs[Coupon in CCY],T_bETFs[Risk CCY],$B6)+ SUMIFS(T_deposits[Coupon in Loc.Curr],T_deposits[Risk CCY],$B6)+ SUMIFS(T_Eq[Dividend in Loc.Curr],T_Eq[Risk CCY],B6)+ SUMIFS('Real Estate'!X:X,'Real Estate'!D:D,B6),"") | G6: =IFERROR( SUMIFS(T_Bonds[Coupon in USD],T_Bonds[Risk CCY],Results!$B6)+ SUMIFS(T_bETFs[Coupon in USD],T_bETFs[Risk CCY],$B6)+ SUMIFS(T_deposits[Coupon in USD],T_deposits[Risk CCY],$B6)+ SUMIFS(T_Eq[Dividend in USD],T_Eq[Risk CCY],B6)+ SUMIFS('Real Estate'!Y:Y,'Real Estate'!D:D,B6),"") | H6: =IFERROR((SUMIFS(T_Bonds[Full MV in CCY],T_Bonds[Risk CCY],Results!$B6)+ SUMIFS(T_bETFs[Market value in CCY],T_bETFs[Risk CCY],$B6)+ SUMIFS(T_deposits[Market value in USD],T_deposits[Risk CCY],$B6)+ SUMIFS(T_Eq[Market value, CCY],T_Eq[Risk CCY],$B6)+ SUMIFS(T_AI[Market value in CCY],T_AI[Risk CCY],$B6)+ SUMIFS(Cash!F:F,Cash!E:E,$B6))+ SUMIFS('Real Estate'!$G:$G,'Real Estate'!$D:$D,B6)+ SUMIFS('JPM - DP (3R)'!$F:$F,'JPM - DP (3R)'!$C:$C,B6),"") | I6: =IFERROR((SUMIFS(T_Bonds[Full MV in USD],T_Bonds[Risk CCY],Results!$B6)+ SUMIFS(T_bETFs[Market value in USD],T_bETFs[Risk CCY],$B6)+ SUMIFS(T_deposits[Market value in USD],T_deposits[Risk CCY],$B6)+ SUMIFS(T_Eq[Market value, USD],T_Eq[Risk CCY],$B6)+ SUMIFS(T_AI[Market value in USD],T_AI[Risk CCY],$B6)+ SUMIFS(Cash!H:H,Cash!E:E,$B6)+ SUMIFS('Real Estate'!$F:$F,'Real Estate'!$D:$D,B6)+ SUMIFS('JPM - DP (3R)'!$J:$J,'JPM - DP (3R)'!$C:$C,Results!B6)),"") | S6: EUR | T6: {=IFERROR(SUMPRODUCT(Loans!D:D,Loans!F:F,IF(Loans!C:C=LTV!F7,1,0))/SUMIFS(Loans!D:D,Loans!C:C,LTV!F7),0)} -> 0.025230202 | U6: =-SUMIFS(Loans!D:D,Loans!C:C,LTV!F7) -> 24672588 | V6: =-SUMIFS(Loans!G:G,Loans!C:C,LTV!F7) -> 28548652 | W6: =U6*T6 -> 622494.39 | X6: =INDEX('Tech list'!$A$2:$C$8,MATCH(S6,'Tech list'!$A$2:$A$8,0),3)*W6 -> 720288.25 | Y6: =Results!F6
B7: CAD | C7: =I7/$I$11 -> 0.0091288238 | D7: =IFERROR((SUMIFS(T_Bonds[Coupon in Loc.Curr],T_Bonds[Risk CCY],Results!$B7)+SUMIFS(T_bETFs[Coupon in CCY],T_bETFs[Risk CCY],$B7)+SUMIFS(T_deposits[Coupon in Loc.Curr],T_deposits[Risk CCY],$B7)+SUMIFS(T_Eq[Dividend in Loc.Curr],T_Eq[Risk CCY],B7))/(SUMIFS(T_Bonds[Quantity],T_Bonds[Risk CCY],$B7)+SUMIFS(T_bETFs[Market Value, CCY],T_bETFs[Risk CCY],B7)+SUMIFS(T_deposits[Quantity],T_deposits[Risk CCY],B7)+SUMIFS(T_Eq[Market value, CCY],T_Eq[Risk CCY],B7)),"") -> 0.0011969776 | E7: =IFERROR((SUMIFS(T_Bonds[Coupon in Loc.Curr],T_Bonds[Risk CCY],Results!$B7)+SUMIFS(T_bETFs[Coupon in CCY],T_bETFs[Risk CCY],$B7)+SUMIFS(T_deposits[Coupon in Loc.Curr],T_deposits[Risk CCY],$B7)+SUMIFS(T_Eq[Dividend in Loc.Curr],T_Eq[Risk CCY],B7))/ (SUMIFS(T_Bonds[Cost value],T_Bonds[Risk CCY],$B7)+SUMIFS(T_bETFs[Market Value, CCY],T_bETFs[Risk CCY],$B7)+SUMIFS(T_deposits[Quantity],T_deposits[Risk CCY],$B7)+SUMIFS(T_Eq[Market value, CCY],T_Eq[Risk CCY],B7)),"") -> 0.0011969776 | F7: =IFERROR( SUMIFS(T_Bonds[Coupon in Loc.Curr],T_Bonds[Risk CCY],Results!$B7)+ SUMIFS(T_bETFs[Coupon in CCY],T_bETFs[Risk CCY],$B7)+ SUMIFS(T_deposits[Coupon in Loc.Curr],T_deposits[Risk CCY],$B7)+ SUMIFS(T_Eq[Dividend in Loc.Curr],T_Eq[Risk CCY],B7)+ SUMIFS('Real Estate'!X:X,'Real Estate'!D:D,B7),"") -> 812 | G7: =IFERROR( SUMIFS(T_Bonds[Coupon in USD],T_Bonds[Risk CCY],Results!$B7)+ SUMIFS(T_bETFs[Coupon in USD],T_bETFs[Risk CCY],$B7)+ SUMIFS(T_deposits[Coupon in USD],T_deposits[Risk CCY],$B7)+ SUMIFS(T_Eq[Dividend in USD],T_Eq[Risk CCY],B7)+ SUMIFS('Real Estate'!Y:Y,'Real Estate'!D:D,B7),"") -> 598.038 | H7: =IFERROR((SUMIFS(T_Bonds[Full MV in CCY],T_Bonds[Risk CCY],Results!$B7)+ SUMIFS(T_bETFs[Market value in CCY],T_bETFs[Risk CCY],$B7)+ SUMIFS(T_deposits[Market value in USD],T_deposits[Risk CCY],$B7)+ SUMIFS(T_Eq[Market value, CCY],T_Eq[Risk CCY],$B7)+ SUMIFS(T_AI[Market value in CCY],T_AI[Risk CCY],$B7)+ SUMIFS(Cash!F:F,Cash!E:E,$B7))+ SUMIFS('Real Estate'!$G:$G,'Real Estate'!$D:$D,B7)+ SUMIFS('JPM - DP (3R)'!$F:$F,'JPM - DP (3R)'!$C:$C,B7),"") -> 678375.25 | I7: =IFERROR((SUMIFS(T_Bonds[Full MV in USD],T_Bonds[Risk CCY],Results!$B7)+ SUMIFS(T_bETFs[Market value in USD],T_bETFs[Risk CCY],$B7)+ SUMIFS(T_deposits[Market value in USD],T_deposits[Risk CCY],$B7)+ SUMIFS(T_Eq[Market value, USD],T_Eq[Risk CCY],$B7)+ SUMIFS(T_AI[Market value in USD],T_AI[Risk CCY],$B7)+ SUMIFS(Cash!H:H,Cash!E:E,$B7)+ SUMIFS('Real Estate'!$F:$F,'Real Estate'!$D:$D,B7)+ SUMIFS('JPM - DP (3R)'!$J:$J,'JPM - DP (3R)'!$C:$C,Results!B7)),"") -> 499623.37 | S7: CHF | T7: {=IFERROR(SUMPRODUCT(Loans!D:D,Loans!F:F,IF(Loans!C:C=LTV!F8,1,0))/SUMIFS(Loans!D:D,Loans!C:C,LTV!F8),0)} -> 0.0066570933 | U7: =-SUMIFS(Loans!D:D,Loans!C:C,LTV!F8) -> 13640419 | V7: =-SUMIFS(Loans!G:G,Loans!C:C,LTV!F8) -> 17503386 | W7: =U7*T7 -> 90805.541 | X7: =INDEX('Tech list'!$A$2:$C$8,MATCH(S7,'Tech list'!$A$2:$A$8,0),3)*W7 -> 116521.67 | Y7: 0
B8: BRL | C8: =I8/$I$11 -> 0.043523631 | D8: =IFERROR((SUMIFS(T_Bonds[Coupon in Loc.Curr],T_Bonds[Risk CCY],Results!$B8)+SUMIFS(T_bETFs[Coupon in CCY],T_bETFs[Risk CCY],$B8)+SUMIFS(T_deposits[Coupon in Loc.Curr],T_deposits[Risk CCY],$B8)+SUMIFS(T_Eq[Dividend in Loc.Curr],T_Eq[Risk CCY],B8))/(SUMIFS(T_Bonds[Quantity],T_Bonds[Risk CCY],$B8)+SUMIFS(T_bETFs[Market Value, CCY],T_bETFs[Risk CCY],B8)+SUMIFS(T_deposits[Quantity],T_deposits[Risk CCY],B8)+SUMIFS(T_Eq[Market value, CCY],T_Eq[Risk CCY],B8)),"") -> 0.10375 | E8: =IFERROR((SUMIFS(T_Bonds[Coupon in Loc.Curr],T_Bonds[Risk CCY],Results!$B8)+SUMIFS(T_bETFs[Coupon in CCY],T_bETFs[Risk CCY],$B8)+SUMIFS(T_deposits[Coupon in Loc.Curr],T_deposits[Risk CCY],$B8)+SUMIFS(T_Eq[Dividend in Loc.Curr],T_Eq[Risk CCY],B8))/ (SUMIFS(T_Bonds[Cost value],T_Bonds[Risk CCY],$B8)+SUMIFS(T_bETFs[Market Value, CCY],T_bETFs[Risk CCY],$B8)+SUMIFS(T_deposits[Quantity],T_deposits[Risk CCY],$B8)+SUMIFS(T_Eq[Market value, CCY],T_Eq[Risk CCY],B8)),"") -> 0.11026809 | F8: =IFERROR( SUMIFS(T_Bonds[Coupon in Loc.Curr],T_Bonds[Risk CCY],Results!$B8)+ SUMIFS(T_bETFs[Coupon in CCY],T_bETFs[Risk CCY],$B8)+ SUMIFS(T_deposits[Coupon in Loc.Curr],T_deposits[Risk CCY],$B8)+ SUMIFS(T_Eq[Dividend in Loc.Curr],T_Eq[Risk CCY],B8)+ SUMIFS('Real Estate'!X:X,'Real Estate'!D:D,B8),"") -> 1245000 | G8: =IFERROR( SUMIFS(T_Bonds[Coupon in USD],T_Bonds[Risk CCY],Results!$B8)+ SUMIFS(T_bETFs[Coupon in USD],T_bETFs[Risk CCY],$B8)+ SUMIFS(T_deposits[Coupon in USD],T_deposits[Risk CCY],$B8)+ SUMIFS(T_Eq[Dividend in USD],T_Eq[Risk CCY],B8)+ SUMIFS('Real Estate'!Y:Y,'Real Estate'!D:D,B8),"") -> 239040 | H8: =IFERROR((SUMIFS(T_Bonds[Full MV in CCY],T_Bonds[Risk CCY],Results!$B8)+ SUMIFS(T_bETFs[Market value in CCY],T_bETFs[Risk CCY],$B8)+ SUMIFS(T_deposits[Market value in USD],T_deposits[Risk CCY],$B8)+ SUMIFS(T_Eq[Market value, CCY],T_Eq[Risk CCY],$B8)+ SUMIFS(T_AI[Market value in CCY],T_AI[Risk CCY],$B8)+ SUMIFS(Cash!F:F,Cash!E:E,$B8))+ SUMIFS('Real Estate'!$G:$G,'Real Estate'!$D:$D,B8)+ SUMIFS('JPM - DP (3R)'!$F:$F,'JPM - DP (3R)'!$C:$C,B8),"") -> 12406572 | I8: =IFERROR((SUMIFS(T_Bonds[Full MV in USD],T_Bonds[Risk CCY],Results!$B8)+ SUMIFS(T_bETFs[Market value in USD],T_bETFs[Risk CCY],$B8)+ SUMIFS(T_deposits[Market value in USD],T_deposits[Risk CCY],$B8)+ SUMIFS(T_Eq[Market value, USD],T_Eq[Risk CCY],$B8)+ SUMIFS(T_AI[Market value in USD],T_AI[Risk CCY],$B8)+ SUMIFS(Cash!H:H,Cash!E:E,$B8)+ SUMIFS('Real Estate'!$F:$F,'Real Estate'!$D:$D,B8)+ SUMIFS('JPM - DP (3R)'!$J:$J,'JPM - DP (3R)'!$C:$C,Results!B8)),"") -> 2382061.9 | S8: JPY | T8: {=IFERROR(SUMPRODUCT(Loans!D:D,Loans!F:F,IF(Loans!C:C=LTV!F9,1,0))/SUMIFS(Loans!D:D,Loans!C:C,LTV!F9),0)} -> 0.015 | U8: =-SUMIFS(Loans!D:D,Loans!C:C,LTV!F9) -> 148246000 | V8: =-SUMIFS(Loans!G:G,Loans!C:C,LTV!F9) -> 935728.75 | W8: =U8*T8 -> 2223690 | X8: =INDEX('Tech list'!$A$2:$C$8,MATCH(S8,'Tech list'!$A$2:$A$8,0),3)*W8 -> 14035.931 | Y8: 0
B9: TRY | C9: =I9/$I$11 -> 0.016885032 | D9: =IFERROR((SUMIFS(T_Bonds[Coupon in Loc.Curr],T_Bonds[Risk CCY],Results!$B9)+SUMIFS(T_bETFs[Coupon in CCY],T_bETFs[Risk CCY],$B9)+SUMIFS(T_deposits[Coupon in Loc.Curr],T_deposits[Risk CCY],$B9)+SUMIFS(T_Eq[Dividend in Loc.Curr],T_Eq[Risk CCY],B9))/(SUMIFS(T_Bonds[Quantity],T_Bonds[Risk CCY],$B9)+SUMIFS(T_bETFs[Market Value, CCY],T_bETFs[Risk CCY],B9)+SUMIFS(T_deposits[Quantity],T_deposits[Risk CCY],B9)+SUMIFS(T_Eq[Market value, CCY],T_Eq[Risk CCY],B9)),"") -> 0.275 | E9: =IFERROR((SUMIFS(T_Bonds[Coupon in Loc.Curr],T_Bonds[Risk CCY],Results!$B9)+SUMIFS(T_bETFs[Coupon in CCY],T_bETFs[Risk CCY],$B9)+SUMIFS(T_deposits[Coupon in Loc.Curr],T_deposits[Risk CCY],$B9)+SUMIFS(T_Eq[Dividend in Loc.Curr],T_Eq[Risk CCY],B9))/ (SUMIFS(T_Bonds[Cost value],T_Bonds[Risk CCY],$B9)+SUMIFS(T_bETFs[Market Value, CCY],T_bETFs[Risk CCY],$B9)+SUMIFS(T_deposits[Quantity],T_deposits[Risk CCY],$B9)+SUMIFS(T_Eq[Market value, CCY],T_Eq[Risk CCY],B9)),"") -> 0.30082429 | F9: =IFERROR( SUMIFS(T_Bonds[Coupon in Loc.Curr],T_Bonds[Risk CCY],Results!$B9)+ SUMIFS(T_bETFs[Coupon in CCY],T_bETFs[Risk CCY],$B9)+ SUMIFS(T_deposits[Coupon in Loc.Curr],T_deposits[Risk CCY],$B9)+ SUMIFS(T_Eq[Dividend in Loc.Curr],T_Eq[Risk CCY],B9)+ SUMIFS('Real Estate'!X:X,'Real Estate'!D:D,B9),"") -> 9020000 | G9: =IFERROR( SUMIFS(T_Bonds[Coupon in USD],T_Bonds[Risk CCY],Results!$B9)+ SUMIFS(T_bETFs[Coupon in USD],T_bETFs[Risk CCY],$B9)+ SUMIFS(T_deposits[Coupon in USD],T_deposits[Risk CCY],$B9)+ SUMIFS(T_Eq[Dividend in USD],T_Eq[Risk CCY],B9)+ SUMIFS('Real Estate'!Y:Y,'Real Estate'!D:D,B9),"") -> 204754 | H9: =IFERROR((SUMIFS(T_Bonds[Full MV in CCY],T_Bonds[Risk CCY],Results!$B9)+ SUMIFS(T_bETFs[Market value in CCY],T_bETFs[Risk CCY],$B9)+ SUMIFS(T_deposits[Market value in USD],T_deposits[Risk CCY],$B9)+ SUMIFS(T_Eq[Market value, CCY],T_Eq[Risk CCY],$B9)+ SUMIFS(T_AI[Market value in CCY],T_AI[Risk CCY],$B9)+ SUMIFS(Cash!F:F,Cash!E:E,$B9))+ SUMIFS('Real Estate'!$G:$G,'Real Estate'!$D:$D,B9)+ SUMIFS('JPM - DP (3R)'!$F:$F,'JPM - DP (3R)'!$C:$C,B9),"") -> 40710267 | I9: =IFERROR((SUMIFS(T_Bonds[Full MV in USD],T_Bonds[Risk CCY],Results!$B9)+ SUMIFS(T_bETFs[Market value in USD],T_bETFs[Risk CCY],$B9)+ SUMIFS(T_deposits[Market value in USD],T_deposits[Risk CCY],$B9)+ SUMIFS(T_Eq[Market value, USD],T_Eq[Risk CCY],$B9)+ SUMIFS(T_AI[Market value in USD],T_AI[Risk CCY],$B9)+ SUMIFS(Cash!H:H,Cash!E:E,$B9)+ SUMIFS('Real Estate'!$F:$F,'Real Estate'!$D:$D,B9)+ SUMIFS('JPM - DP (3R)'!$J:$J,'JPM - DP (3R)'!$C:$C,Results!B9)),"") -> 924123.05 | V9: =SUM(V4:V8) -> 49481316 | X9: =SUM(X4:X8) -> 959760.96
B10: Other (JPM DP) | C10: =I10/$I$11 -> 0.011918192 | F10: =IFERROR( SUMIFS(T_Bonds[Coupon in Loc.Curr],T_Bonds[Risk CCY],Results!$B10)+ SUMIFS(T_bETFs[Coupon in CCY],T_bETFs[Risk CCY],$B10)+ SUMIFS(T_deposits[Coupon in Loc.Curr],T_deposits[Risk CCY],$B10)+ SUMIFS(T_Eq[Dividend in Loc.Curr],T_Eq[Risk CCY],B10)+ SUMIFS('Real Estate'!X:X,'Real Estate'!D:D,B10),"") -> 0 | G10: =IFERROR( SUMIFS(T_Bonds[Coupon in USD],T_Bonds[Risk CCY],Results!$B10)+ SUMIFS(T_bETFs[Coupon in USD],T_bETFs[Risk CCY],$B10)+ SUMIFS(T_deposits[Coupon in USD],T_deposits[Risk CCY],$B10)+ SUMIFS(T_Eq[Dividend in USD],T_Eq[Risk CCY],B10)+ SUMIFS('Real Estate'!Y:Y,'Real Estate'!D:D,B10),"") -> 0 | H10: =IFERROR((SUMIFS(T_Bonds[Full MV in CCY],T_Bonds[Risk CCY],Results!$B10)+ SUMIFS(T_bETFs[Market value in CCY],T_bETFs[Risk CCY],$B10)+ SUMIFS(T_deposits[Market value in USD],T_deposits[Risk CCY],$B10)+ SUMIFS(T_Eq[Market value, CCY],T_Eq[Risk CCY],$B10)+ SUMIFS(T_AI[Market value in CCY],T_AI[Risk CCY],$B10)+ SUMIFS(Cash!F:F,Cash!E:E,$B10))+ SUMIFS('Real Estate'!$G:$G,'Real Estate'!$D:$D,B10)+ SUMIFS('JPM - DP (3R)'!$F:$F,'JPM - DP (3R)'!$C:$C,B10),"") -> 0 | I10: ='JPM - DP (3R)'!$X$37 -> 652286.37
D11: =SUMPRODUCT(C4:C9,D4:D9) -> #VALUE! | E11: =SUMPRODUCT($C$4:$C$9,E4:E9) -> #VALUE! | G11: =SUM(G4:G10) -> 2983081.5 | I11: =SUM(I4:I10)+I68+I70 -> 54730311
B13: Bonds
B14: Currency | C14: Weights | D14: AW coupon (CCY) | E14: AW Current yield (CCY) | F14: Total coupon (CCY) | G14: Total coupon (USD) | H14: Total MV of positions (CCY) | I14: Total MV of positions (USD) | J14: YTM/YTC | S14: Portfolio Loans, Current by bank '000
B15: USD | C15: =SUMIFS(T_Bonds[Market value in USD],T_Bonds[Risk CCY],Results!B4)/SUM(T_Bonds[Market value in USD]) -> 0.66087242 | D15: =SUMIFS(T_Bonds[Coupon in Loc.Curr],T_Bonds[Risk CCY],Results!$B15)/SUMIFS(T_Bonds[Quantity],T_Bonds[Risk CCY],$B15) -> 0.067320568 | E15: =SUMIFS(T_Bonds[Coupon in Loc.Curr],T_Bonds[Risk CCY],Results!$B15)/SUMIFS(T_Bonds[Cost value],T_Bonds[Risk CCY],$B15) -> 0.073590258 | F15: =SUMIFS(T_Bonds[Coupon in Loc.Curr],T_Bonds[Risk CCY],Results!$B15) -> 3261681.5 | G15: =SUMIFS(T_Bonds[Coupon in USD],T_Bonds[Risk CCY],Results!$B15) -> 3261681.5 | H15: =SUMIFS(T_Bonds[Full MV in CCY],T_Bonds[Risk CCY],Results!$B15) -> 47090795 | I15: =SUMIFS(T_Bonds[Full MV in USD],T_Bonds[Risk CCY],Results!$B15) -> 47090795 | J15: =SUMIFS(T_Bonds[for WYTC],T_Bonds[Risk CCY],Results!B15)/ (SUMIFS(T_Bonds[Quantity],T_Bonds[Risk CCY],Results!B15)- SUMIFS(T_Bonds[Quantity],T_Bonds[Risk CCY],Results!B15,T_Bonds[YTM/YTC],0)) -> 0.072490096 | S15: CCY | T15: JPM | U15: UBS | V15: Vontobel
B16: GBP | C16: =SUMIFS(T_Bonds[Market value in USD],T_Bonds[Risk CCY],Results!B5)/SUM(T_Bonds[Market value in USD]) -> 0.16705908 | D16: =SUMIFS(T_Bonds[Coupon in Loc.Curr],T_Bonds[Risk CCY],Results!$B16)/SUMIFS(T_Bonds[Quantity],T_Bonds[Risk CCY],$B16) -> 0.064311489 | E16: =SUMIFS(T_Bonds[Coupon in Loc.Curr],T_Bonds[Risk CCY],Results!$B16)/SUMIFS(T_Bonds[Cost value],T_Bonds[Risk CCY],$B16) -> 0.072290702 | F16: =SUMIFS(T_Bonds[Coupon in Loc.Curr],T_Bonds[Risk CCY],Results!$B16) -> 604528 | G16: =SUMIFS(T_Bonds[Coupon in USD],T_Bonds[Risk CCY],Results!$B16) -> 808495.75 | H16: =SUMIFS(T_Bonds[Full MV in CCY],T_Bonds[Risk CCY],Results!$B16) -> 9050996.4 | I16: =SUMIFS(T_Bonds[Full MV in USD],T_Bonds[Risk CCY],Results!$B16) -> 12104803 | J16: =SUMIFS(T_Bonds[for WYTC],T_Bonds[Risk CCY],Results!B16)/(SUMIFS(T_Bonds[Quantity],T_Bonds[Risk CCY],Results!B16)-SUMIFS(T_Bonds[Quantity],T_Bonds[Risk CCY],Results!B16,T_Bonds[YTM/YTC],0)) -> 0.070114952 | S16: USD | T16: =SUMIFS(Loans!$D:$D,Loans!$C:$C,Results!$S16,Loans!$A:$A,Results!T$15)/1000 -> -210.49239 | U16: =SUMIFS(Loans!$D:$D,Loans!$C:$C,Results!$S16,Loans!$A:$A,Results!U$15)/1000 -> 0 | V16: =SUMIFS(Loans!$D:$D,Loans!$C:$C,Results!$S16,Loans!$A:$A,Results!V$15)/1000 -> 0
B17: EUR | C17: =SUMIFS(T_Bonds[Market value in USD],T_Bonds[Risk CCY],Results!B6)/SUM(T_Bonds[Market value in USD]) -> 0.13006061 | D17: =SUMIFS(T_Bonds[Coupon in Loc.Curr],T_Bonds[Risk CCY],Results!$B17)/SUMIFS(T_Bonds[Quantity],T_Bonds[Risk CCY],$B17) -> 0.066554054 | E17: =SUMIFS(T_Bonds[Coupon in Loc.Curr],T_Bonds[Risk CCY],Results!$B17)/SUMIFS(T_Bonds[Cost value],T_Bonds[Risk CCY],$B17) -> 0.066466178 | F17: =SUMIFS(T_Bonds[Coupon in Loc.Curr],T_Bonds[Risk CCY],Results!$B17) -> 492500 | G17: =SUMIFS(T_Bonds[Coupon in USD],T_Bonds[Risk CCY],Results!$B17) -> 569871.75 | H17: =SUMIFS(T_Bonds[Full MV in CCY],T_Bonds[Risk CCY],Results!$B17) -> 7979789.6 | I17: =SUMIFS(T_Bonds[Full MV in USD],T_Bonds[Risk CCY],Results!$B17) -> 9233414.5 | J17: =SUMIFS(T_Bonds[for WYTC],T_Bonds[Risk CCY],Results!B17)/(SUMIFS(T_Bonds[Quantity],T_Bonds[Risk CCY],Results!B17)-SUMIFS(T_Bonds[Quantity],T_Bonds[Risk CCY],Results!B17,T_Bonds[YTM/YTC],0)) -> 0.055439351 | S17: GBP | T17: =SUMIFS(Loans!$D:$D,Loans!$C:$C,Results!$S17,Loans!$A:$A,Results!T$15)/1000 -> -1467.0865 | U17: =SUMIFS(Loans!$D:$D,Loans!$C:$C,Results!$S17,Loans!$A:$A,Results!U$15)/1000 -> 0 | V17: =SUMIFS(Loans!$D:$D,Loans!$C:$C,Results!$S17,Loans!$A:$A,Results!V$15)/1000 -> -240
B18: BRL | C18: =SUMIFS(T_Bonds[Market value in USD],T_Bonds[Risk CCY],Results!B8)/SUM(T_Bonds[Market value in USD]) -> 0.031904403 | D18: =SUMIFS(T_Bonds[Coupon in Loc.Curr],T_Bonds[Risk CCY],Results!$B18)/SUMIFS(T_Bonds[Quantity],T_Bonds[Risk CCY],$B18) -> 0.10375 | E18: =SUMIFS(T_Bonds[Coupon in Loc.Curr],T_Bonds[Risk CCY],Results!$B18)/SUMIFS(T_Bonds[Cost value],T_Bonds[Risk CCY],$B18) -> 0.11026809 | F18: =SUMIFS(T_Bonds[Coupon in Loc.Curr],T_Bonds[Risk CCY],Results!$B18) -> 1245000 | G18: =SUMIFS(T_Bonds[Coupon in USD],T_Bonds[Risk CCY],Results!$B18) -> 239040 | H18: =SUMIFS(T_Bonds[Full MV in CCY],T_Bonds[Risk CCY],Results!$B18) -> 12406572 | I18: =SUMIFS(T_Bonds[Full MV in USD],T_Bonds[Risk CCY],Results!$B18) -> 2382061.9 | J18: =SUMIFS(T_Bonds[for WYTC],T_Bonds[Risk CCY],Results!B18)/(SUMIFS(T_Bonds[Quantity],T_Bonds[Risk CCY],Results!B18)-SUMIFS(T_Bonds[Quantity],T_Bonds[Risk CCY],Results!B18,T_Bonds[YTM/YTC],0)) -> 0.11900345 | S18: EUR | T18: =SUMIFS(Loans!$D:$D,Loans!$C:$C,Results!$S18,Loans!$A:$A,Results!T$15)/1000 -> -5388.8953 | U18: =SUMIFS(Loans!$D:$D,Loans!$C:$C,Results!$S18,Loans!$A:$A,Results!U$15)/1000 -> -2265.693 | V18: =SUMIFS(Loans!$D:$D,Loans!$C:$C,Results!$S18,Loans!$A:$A,Results!V$15)/1000 -> -17018
B19: TRY | C19: =SUMIFS(T_Bonds[Market value in USD],T_Bonds[Risk CCY],Results!B9)/SUM(T_Bonds[Market value in USD]) -> 0.010103489 | D19: =SUMIFS(T_Bonds[Coupon in Loc.Curr],T_Bonds[Risk CCY],Results!$B19)/SUMIFS(T_Bonds[Quantity],T_Bonds[Risk CCY],$B19) -> 0.275 | E19: =SUMIFS(T_Bonds[Coupon in Loc.Curr],T_Bonds[Risk CCY],Results!$B19)/SUMIFS(T_Bonds[Cost value],T_Bonds[Risk CCY],$B19) -> 0.30082429 | F19: =SUMIFS(T_Bonds[Coupon in Loc.Curr],T_Bonds[Risk CCY],Results!$B19) -> 9020000 | G19: =SUMIFS(T_Bonds[Coupon in USD],T_Bonds[Risk CCY],Results!$B19) -> 204754 | H19: =SUMIFS(T_Bonds[Full MV in CCY],T_Bonds[Risk CCY],Results!$B19) -> 40710267 | I19: =SUMIFS(T_Bonds[Full MV in USD],T_Bonds[Risk CCY],Results!$B19) -> 924123.05 | J19: =SUMIFS(T_Bonds[for WYTC],T_Bonds[Risk CCY],Results!B19)/(SUMIFS(T_Bonds[Quantity],T_Bonds[Risk CCY],Results!B19)-SUMIFS(T_Bonds[Quantity],T_Bonds[Risk CCY],Results!B19,T_Bonds[YTM/YTC],0)) -> 0.31121346 | S19: CHF | T19: =SUMIFS(Loans!$D:$D,Loans!$C:$C,Results!$S19,Loans!$A:$A,Results!T$15)/1000 -> -25.7689 | U19: =SUMIFS(Loans!$D:$D,Loans!$C:$C,Results!$S19,Loans!$A:$A,Results!U$15)/1000 -> -2000 | V19: =SUMIFS(Loans!$D:$D,Loans!$C:$C,Results!$S19,Loans!$A:$A,Results!V$15)/1000 -> -11614.65
D20: =SUMPRODUCT($C$15:$C$19,D15:D19) -> 0.069978727 | E20: =SUMPRODUCT($C$15:$C$19,E15:E19) -> 0.075912634 | G20: =SUM(G15:G19) -> 5083843 | I20: =SUM(I15:I19) -> 71735197 | J20: =SUMPRODUCT($C$15:$C$19,J15:J19) -> 0.073771596 | M20: Bonds | N20: =I20/I11 -> 1.3107033 | S20: JPY | T20: =SUMIFS(Loans!$D:$D,Loans!$C:$C,Results!$S20,Loans!$A:$A,Results!T$15)/1000 -> 0 | U20: =SUMIFS(Loans!$D:$D,Loans!$C:$C,Results!$S20,Loans!$A:$A,Results!U$15)/1000 -> 0 | V20: =SUMIFS(Loans!$D:$D,Loans!$C:$C,Results!$S20,Loans!$A:$A,Results!V$15)/1000 -> -148246
M21: Deposits | N21: =I27/I11 -> 0.23653137 | S21: Total in USD | T21: =SUMIFS(Loans!$G:$G,Loans!$A:$A,Results!T$15)/1000 -> -8441.1313 | U21: =SUMIFS(Loans!$G2:$G20,Loans!$A2:$A20,Results!U$15)/1000 -> -5188.0334 | V21: =SUMIFS(Loans!$G2:$G20,Loans!$A2:$A20,Results!V$15)/1000 -> -35852.151
M22: Bond Funds | N22: =I34/I11 -> 0.6799215
B23: Deposits | M23: Equities (incl. ETF) | N23: =I44/I11 -> #N/A
B24: Currency | C24: Weights | D24: AW % (no reinvest) | E24: AW % (with reinvest) | F24: Interest, CCY 2024 | G24: Interest, USD 2024 | H24: Total MV of positions, CCY | I24: Total MV of positions (USD) | M24: AI | N24: =I52/I11 -> 0.17406237 | S24: =LTV!F25 -> LTV by banks (Collateral assets) | V24: =LTV!I25 -> In tousands of USD
B25: USD | C25: =SUMIFS(Deposits!U:U,Deposits!D:D,Results!B4)/SUM(Deposits!V:V) -> 1 | D25: =IFERROR(SUMIFS(T_deposits[Coupon in Loc.Curr],T_deposits[Risk CCY],Results!$B25)/SUMIFS(T_deposits[Quantity],T_deposits[Risk CCY],Results!$B25),"") -> 0.037294218 | E25: =IFERROR(SUMIFS(#REF!,T_deposits[Risk CCY],Results!$B25)/SUMIFS(T_deposits[Quantity],T_deposits[Risk CCY],Results!$B25),"") | F25: =SUMIFS(T_deposits[Coupon in Loc.Curr],T_deposits[Risk CCY],Results!B25) -> 379207.61 | G25: =SUMIFS(T_deposits[Coupon in USD, real],T_deposits[Risk CCY],Results!B25) -> 374581.66 | H25: =SUMIFS(T_deposits[Market value in USD],T_deposits[Risk CCY],Results!B25) -> 12945435 | I25: =SUMIFS(T_deposits[Market value in USD],T_deposits[Risk CCY],Results!B25) -> 12945435 | M25: Real Estate | N25: =I60/I11 -> 1.3166054 | S25: =LTV!F26 -> Bank | T25: =LTV!G26 -> Collateral Market Value | U25: =LTV!H26 -> Loans | V25: =LTV!I26 -> LTV
B26: GBP | C26: =SUMIFS(Deposits!U:U,Deposits!D:D,Results!B5)/SUM(Deposits!V:V) -> 0 | D26: =IFERROR(SUMIFS(T_deposits[Coupon in Loc.Curr],T_deposits[Risk CCY],Results!$B26)/SUMIFS(T_deposits[Quantity],T_deposits[Risk CCY],Results!$B26),"") | E26: =IFERROR(SUMIFS(#REF!,T_deposits[Risk CCY],Results!$B26)/SUMIFS(T_deposits[Quantity],T_deposits[Risk CCY],Results!$B26),"") | F26: =SUMIFS(T_deposits[Coupon in Loc.Curr],T_deposits[Risk CCY],Results!B26) -> 0 | G26: =SUMIFS(T_deposits[Coupon in USD],T_deposits[Risk CCY],Results!B26) -> 0 | H26: =SUMIFS(T_deposits[Quantity],T_deposits[Risk CCY],Results!B26) -> 0 | I26: =SUMIFS(T_deposits[Market value in USD],T_deposits[Risk CCY],Results!B26) -> 0 | M26: Cash | N26: =I73/I11 -> -0.047473235 | S26: =LTV!F27 -> Vontobel | T26: =LTV!G27 -> #VALUE! | U26: =LTV!H27 -> 35852.151 | V26: =LTV!I27 -> #VALUE!
D27: =SUMPRODUCT(C25:C26,D25:D26) -> 0.037294218 | E27: =SUMPRODUCT(C25:C26,E25:E26) -> 0 | G27: =SUM(G24:G26) -> 374581.66 | I27: =SUM(I24:I26) -> 12945435 | S27: =LTV!F28 -> UBS | T27: =LTV!G28 -> 20902.871 | U27: =LTV!H28 -> 5188.0334 | V27: =LTV!I28 -> 0.24819717
S28: =LTV!F29 -> JPM | T28: =LTV!G29 -> 25945.878 | U28: =LTV!H29 -> 8441.1313 | V28: =LTV!I29 -> 0.32533612
S29: =LTV!F30 -> Total in USD | T29: =LTV!G30 -> #VALUE! | U29: =LTV!H30 -> 49481.316 | V29: =LTV!I30 -> #VALUE!
B30: Bonds ETF
B31: Currency | C31: Weights | D31: AW % | E31: Gross P&L | F31: Distributions, CCY 2024 | G31: Distributions, USD 2024 | H31: Total MV of funds (CCY) | I31: Total MV of funds (USD)
B32: USD | C32: =I32/$I$34 -> 1 | D32: =IFERROR(SUMIFS(T_bETFs[Coupon in CCY],T_bETFs[Risk CCY],Results!B32)/SUMIFS(T_bETFs[Market Value, CCY],T_bETFs[Risk CCY],Results!B32),"") -> 0.066976206 | E32: =IFERROR(SUMIFS('Bonds ETFs'!R:R,'Bonds ETFs'!O:O,Results!B32)/SUMIFS('Bonds ETFs'!Z:Z,'Bonds ETFs'!O:O,Results!B32)-1,"") -> -0.050186672 | F32: =SUMIFS(T_bETFs[Coupon in CCY],T_bETFs[Risk CCY],Results!B32) -> 2492339.7 | G32: =SUMIFS(T_bETFs[Coupon in USD],T_bETFs[Risk CCY],Results!B32) -> 2492339.7 | H32: =SUMIFS(T_bETFs[Market Value, CCY],T_bETFs[Risk CCY],Results!B32) -> 37212315 | I32: =SUMIFS(T_bETFs[Market Value, USD],T_bETFs[Risk CCY],Results!B32) -> 37212315 | S32: =LTV!F34 -> LTV by banks (All assets) | V32: =LTV!I34 -> In tousands of USD
B33: EUR | C33: =I33/$I$34 -> 0 | D33: =IFERROR(SUMIFS(T_bETFs[Coupon in CCY],T_bETFs[Risk CCY],Results!B33)/SUMIFS(T_bETFs[Market Value, CCY],T_bETFs[Risk CCY],Results!B33),"") | E33: =IFERROR(SUMIFS('Bonds ETFs'!R:R,'Bonds ETFs'!O:O,Results!B33)/SUMIFS('Bonds ETFs'!Z:Z,'Bonds ETFs'!O:O,Results!B33)-1,"") | F33: =SUMIFS(T_bETFs[Coupon in CCY],T_bETFs[Risk CCY],Results!B33) -> 0 | G33: =SUMIFS(T_bETFs[Coupon in USD],T_bETFs[Risk CCY],Results!B33) -> 0 | H33: =SUMIFS(T_bETFs[Market Value, CCY],T_bETFs[Risk CCY],Results!B33) -> 0 | I33: =SUMIFS(T_bETFs[Market Value, USD],T_bETFs[Risk CCY],Results!B33) -> 0 | S33: =LTV!F35 -> Bank | T33: =LTV!G35 -> Market Value | U33: =LTV!H35 -> Loans | V33: =LTV!I35 -> LTV
G34: =SUM(G32:G33) -> 2492339.7 | I34: =SUM(I32:I33) -> 37212315 | S34: =LTV!F36 -> Vontobel | T34: =LTV!G36 -> #VALUE! | U34: =LTV!H36 -> 35852.151 | V34: =LTV!I36 -> -
S35: =LTV!F37 -> UBS | T35: =LTV!G37 -> 20902.871 | U35: =LTV!H37 -> 5188.0334 | V35: =LTV!I37 -> 0.24819717
S36: =LTV!F38 -> JPM | T36: =LTV!G38 -> 35945.878 | U36: =LTV!H38 -> 8441.1313 | V36: =LTV!I38 -> 0.23482891
B37: Equities | S37: =LTV!F39 -> Non-bank | T37: =LTV!G39 -> 53636.191 | U37: =LTV!H39 -> 0 | V37: =LTV!I39 -> 0
B38: CCY | C38: Weights | D38: AW yield, CCY | E38: P&L, total | F38: Total annual DIV, CCY | G38: Total annual DIV, USD | H38: Total MV of positions (CCY) | I38: Total MV of positions (USD) | S38: =LTV!F40 -> Total in USD | T38: =LTV!G40 -> #VALUE! | U38: =LTV!H40 -> 49481.316 | V38: =LTV!I40 -> -
B39: USD | C39: =I39/$I$44 -> #N/A | D39: =SUMIFS(T_Eq[Dividend in Loc.Curr],T_Eq[Risk CCY],B39)/SUMIFS(T_Eq[Market value, CCY],T_Eq[Risk CCY],B39) -> #N/A | E39: =SUMIFS(T_Eq[Market value, CCY],T_Eq[Risk CCY],B39)/SUMIFS(T_Eq[Cost value],T_Eq[Risk CCY],B39)-1 -> #N/A | F39: =SUMIFS(T_Eq[Dividend in Loc.Curr],T_Eq[Risk CCY],B39) -> #N/A | G39: =SUMIFS(T_Eq[Dividend in USD],T_Eq[Risk CCY],B39) -> #N/A | H39: =SUMIFS(T_Eq[Market value, CCY],T_Eq[Risk CCY],B39) -> #N/A | I39: =SUMIFS(T_Eq[Market value, USD],T_Eq[Risk CCY],B39) -> #N/A
B40: EUR | C40: =I40/$I$44 -> #N/A | D40: =SUMIFS(T_Eq[Dividend in Loc.Curr],T_Eq[Risk CCY],B40)/SUMIFS(T_Eq[Market value, CCY],T_Eq[Risk CCY],B40) -> #N/A | E40: =SUMIFS(T_Eq[Market value, CCY],T_Eq[Risk CCY],B40)/SUMIFS(T_Eq[Cost value],T_Eq[Risk CCY],B40)-1 -> #N/A | F40: =SUMIFS(T_Eq[Dividend in Loc.Curr],T_Eq[Risk CCY],B40) -> #N/A | G40: =SUMIFS(T_Eq[Dividend in USD],T_Eq[Risk CCY],B40) -> #N/A | H40: =SUMIFS(T_Eq[Market value, CCY],T_Eq[Risk CCY],B40) -> #N/A | I40: =SUMIFS(T_Eq[Market value, USD],T_Eq[Risk CCY],B40) -> #N/A
B41: GBP | C41: =I41/$I$44 -> #N/A | D41: =SUMIFS(T_Eq[Dividend in Loc.Curr],T_Eq[Risk CCY],B41)/SUMIFS(T_Eq[Market value, CCY],T_Eq[Risk CCY],B41) -> 0.055718021 | E41: =SUMIFS(T_Eq[Market value, CCY],T_Eq[Risk CCY],B41)/SUMIFS(T_Eq[Cost value],T_Eq[Risk CCY],B41)-1 -> 0.15332466 | F41: =SUMIFS(T_Eq[Dividend in Loc.Curr],T_Eq[Risk CCY],B41) -> 93699.514 | G41: =SUMIFS(T_Eq[Dividend in USD],T_Eq[Risk CCY],B41) -> 125313.73 | H41: =SUMIFS(T_Eq[Market value, CCY],T_Eq[Risk CCY],B41) -> 1681673.4 | I41: =SUMIFS(T_Eq[Market value, USD],T_Eq[Risk CCY],B41) -> 2249070
B42: CAD | C42: =I42/$I$44 -> #N/A | D42: =SUMIFS(T_Eq[Dividend in Loc.Curr],T_Eq[Risk CCY],B42)/SUMIFS(T_Eq[Market value, CCY],T_Eq[Risk CCY],B42) -> 0.0011969776 | E42: =SUMIFS(T_Eq[Market value, CCY],T_Eq[Risk CCY],B42)/SUMIFS(T_Eq[Cost value],T_Eq[Risk CCY],B42)-1 -> 1.8361994 | F42: =SUMIFS(T_Eq[Dividend in Loc.Curr],T_Eq[Risk CCY],B42) -> 812 | G42: =SUMIFS(T_Eq[Dividend in USD],T_Eq[Risk CCY],B42) -> 598.038 | H42: =SUMIFS(T_Eq[Market value, CCY],T_Eq[Risk CCY],B42) -> 678375.25 | I42: =SUMIFS(T_Eq[Market value, USD],T_Eq[Risk CCY],B42) -> 499623.37 | S42: JPM Discretionary part Results
B43: JPM DP | C43: =I43/$I$44 -> #N/A | D43: - | E43: =W47 -> 0.21090312 | F43: =SUMIFS(T_Eq[Dividend in Loc.Curr],T_Eq[Risk CCY],B43) -> 0 | G43: =SUMIFS(T_Eq[Dividend in USD],T_Eq[Risk CCY],B43) -> 0 | H43: 0 | I43: =T47 -> 13293212 | T43: ='JPM - DP (3R)'!W1 -> MV, USD at 24.02.2026 | U43: ='JPM - DP (3R)'!X1 -> MV, USD at 09.02.2026 | V43: ='JPM - DP (3R)'!Z1 -> CCY | W43: ='JPM - DP (3R)'!AA1 -> P&L % (USD) | X43: ='JPM - DP (3R)'!AB1 -> Unrealized P&L | Y43: ='JPM - DP (3R)'!AC1 -> Annualized P&L | Z43: ='JPM - DP (3R)'!AD1 -> Inception date | AA43: ='JPM - DP (3R)'!AE1 -> YTD P&L
G44: =SUM(G39:G43) -> #N/A | I44: =SUM(I39:I43) -> #N/A | S44: ='JPM - DP (3R)'!U2 -> Digital EVO | T44: ='JPM - DP (3R)'!W2 -> 3794226.7 | U44: ='JPM - DP (3R)'!X2 -> 3921967.8 | V44: ='JPM - DP (3R)'!Z2 -> USD | W44: ='JPM - DP (3R)'!AA2 -> 0.47106793 | X44: ='JPM - DP (3R)'!AB2 -> 1551226.7 | Y44: ='JPM - DP (3R)'!AC2 -> 0.10800238 | Z44: ='JPM - DP (3R)'!AD2 -> 44499 | AA44: ='JPM - DP (3R)'!AE2 -> -0.071088341
S45: ='JPM - DP (3R)'!U3 -> US Equity income | T45: ='JPM - DP (3R)'!W3 -> 2307577.7 | U45: ='JPM - DP (3R)'!X3 -> 2462169.3 | V45: ='JPM - DP (3R)'!Z3 -> USD | W45: ='JPM - DP (3R)'!AA3 -> 0.12022826 | X45: ='JPM - DP (3R)'!AB3 -> 733392.41 | Y45: ='JPM - DP (3R)'!AC3 -> 0.023914614 | Z45: ='JPM - DP (3R)'!AD3 -> 44256 | AA45: ='JPM - DP (3R)'!AE3 -> -0.0020683535
S46: ='JPM - DP (3R)'!U4 -> GEM | T46: ='JPM - DP (3R)'!W4 -> 7191407.7 | U46: ='JPM - DP (3R)'!X4 -> 7525411.2 | V46: ='JPM - DP (3R)'!Z4 -> USD | W46: ='JPM - DP (3R)'!AA4 -> 0.13989173 | X46: ='JPM - DP (3R)'!AB4 -> 983803.21 | Y46: ='JPM - DP (3R)'!AC4 -> 0.069375655 | Z46: ='JPM - DP (3R)'!AD4 -> 45355 | AA46: ='JPM - DP (3R)'!AE4 -> -0.033877128
B47: Alternative assets | S47: ='JPM - DP (3R)'!U5 -> Total in USD | T47: ='JPM - DP (3R)'!W5 -> 13293212 | U47: ='JPM - DP (3R)'!X5 -> 13909548 | W47: ='JPM - DP (3R)'!AA5 -> 0.21090312 | X47: ='JPM - DP (3R)'!AB5 -> 3268422.3 | Y47: ='JPM - DP (3R)'!AC5 -> 0.070879492 | AA47: ='JPM - DP (3R)'!AE5 -> -0.039544494
B48: CCY | C48: Weights | D48: AW yield, CCY | E48: AW yield, USD | F48: Distributions, CCY 2025 | G48: Distributions, USD 2025 | H48: Total MV of positions (CCY) | I48: Total MV of positions (USD)
B49: USD | C49: =I49/$I$52 -> 0.91702197 | D49: 0 | E49: 0 | F49: 0 | G49: 0 | H49: =SUMIFS(T_AI[Market value in CCY],T_AI[Risk CCY],B49) -> 8735998.6 | I49: =SUMIFS(T_AI[Market value in USD],T_AI[Risk CCY],$B49) -> 8735998.6
B50: GBP | C50: =I50/$I$52 -> 0.028077504 | D50: 0 | E50: 0 | F50: 0 | G50: 0 | H50: =SUMIFS(T_AI[Market value in CCY],T_AI[Risk CCY],B50) -> 200000 | I50: =SUMIFS(T_AI[Market value in USD],T_AI[Risk CCY],$B50) -> 267480
B51: EUR | C51: =I51/$I$52 -> 0.054900527 | D51: 0 | E51: 0 | F51: 0 | G51: 0 | H51: =SUMIFS(T_AI[Market value in CCY],T_AI[Risk CCY],B51) -> 452000 | I51: =SUMIFS(T_AI[Market value in USD],T_AI[Risk CCY],$B51) -> 523009.2
I52: =SUM(I49:I51) -> 9526487.8
B55: Real Estate
B56: CCY | C56: Weights | D56: AW yield, CCY | E56: AW yield, USD | F56: Distributions, CCY 2025 | G56: Distributions, USD 2025 | H56: Total MV of positions (CCY) | I56: Total MV of positions (USD)
B57: USD | C57: =I57/$I$60 -> 0.13811054 | D57: 0 | E57: 0 | F57: 0 | G57: 0 | H57: =SUMIFS('Real Estate'!$G:$G,'Real Estate'!D:D,B57) -> 9952000 | I57: =SUMIFS('Real Estate'!$F:$F,'Real Estate'!D:D,B57) -> 9952000
B58: EUR | C58: =I58/$I$60 -> 0.36163881 | D58: 0 | E58: 0 | F58: 0 | G58: 0 | H58: =SUMIFS('Real Estate'!$G:$G,'Real Estate'!D:D,B58) -> 22521002 | I58: =SUMIFS('Real Estate'!$F:$F,'Real Estate'!D:D,B58) -> 26059051
B59: GBP | C59: =I59/$I$60 -> 0.50025065 | D59: 0 | E59: 0 | F59: 0 | G59: 0 | H59: =SUMIFS('Real Estate'!$G:$G,'Real Estate'!D:D,B59) -> 26953173 | I59: =SUMIFS('Real Estate'!$F:$F,'Real Estate'!D:D,B59) -> 36047173
I60: =SUM(I57:I59) -> 72058224
B63: Cash
B64: CCY | C64: Weights | H64: Total MV of positions (CCY) | I64: Total MV of positions (USD)
B65: USD | C65: =I65/$I$73 -> 0.025310303 | H65: =SUMIFS(Cash!F:F,Cash!E:E,Results!B65) -> -65761.86 | I65: =SUMIFS(Cash!H:H,Cash!E:E,Results!B65) -> -65761.86
B66: GBP | C66: =I66/$I$73 -> 0.14126727 | H66: =SUMIFS(Cash!F:F,Cash!E:E,Results!B66) -> -274446.04 | I66: =SUMIFS(Cash!H:H,Cash!E:E,Results!B66) -> -367044.13
B67: EUR | C67: =I67/$I$73 -> 0.82215895 | H67: =SUMIFS(Cash!F:F,Cash!E:E,Results!B67) -> -1846127.3 | I67: =SUMIFS(Cash!H:H,Cash!E:E,Results!B67) -> -2136153.9
B68: CHF | C68: =I68/$I$73 -> 0.012315169 | H68: =SUMIFS(Cash!F:F,Cash!E:E,Results!B68) -> -24935.77 | I68: =SUMIFS(Cash!H:H,Cash!E:E,Results!B68) -> -31997.58
B69: BRL | C69: =I69/$I$73 -> 0 | H69: =SUMIFS(Cash!F:F,Cash!E:E,Results!B69) -> 0 | I69: =SUMIFS(Cash!H:H,Cash!E:E,Results!B69) -> 0
B70: JPY | C70: =I70/$I$73 -> -0.0010516878 | H70: =SUMIFS(Cash!F:F,Cash!E:E,Results!B70) -> 432909 | I70: =SUMIFS(Cash!H:H,Cash!E:E,Results!B70) -> 2732.5216
B71: TRY | C71: =I71/$I$73 -> 0 | H71: =SUMIFS(Cash!F:F,Cash!E:E,Results!B71) -> 0 | I71: =SUMIFS(Cash!H:H,Cash!E:E,Results!B71) -> 0
B72: Other | C72: =I72/$I$73 -> 0 | H72: =SUMIFS(Cash!F:F,Cash!E:E,Results!B72) -> 0 | I72: =SUM(Cash!H:H)-SUM(Results!I65:I71) -> 0
I73: =SUM(I65:I72) -> -2598225

Sheet LTV
F3: Total Loans, by CCY
F4: CCY | G4: Cost of debt, 2025 | H4: Curent debt CCY | I4: Current Debt USD | J4: Annual interest, CCY | K4: Annual interest, USD | L4: Total coupon, CCY
F5: USD | G5: {=IFERROR(SUMPRODUCT(Loans!D:D,Loans!F:F,IF(Loans!C:C=LTV!F5,1,0))/SUMIFS(Loans!D:D,Loans!C:C,LTV!F5),0)} -> 0.044834337 | H5: =-SUMIFS(Loans!D:D,Loans!C:C,LTV!F5) -> 210492.39 | I5: =-SUMIFS(Loans!G:G,Loans!C:C,LTV!F5) -> 210492.39 | J5: =H5*G5 -> 9437.2868 | K5: =INDEX('Tech list'!$A$2:$C$8,MATCH(F5,'Tech list'!$A$2:$A$8,0),3)*J5 -> 9437.2868 | L5: =IFERROR(VLOOKUP(F5,Results!$B$4:$F$9,5,0),"-")
F6: GBP | G6: {=IFERROR(SUMPRODUCT(Loans!D:D,Loans!F:F,IF(Loans!C:C=LTV!F6,1,0))/SUMIFS(Loans!D:D,Loans!C:C,LTV!F6),0)} -> 0.043572191 | H6: =-SUMIFS(Loans!D:D,Loans!C:C,LTV!F6) -> 1707086.5 | I6: =-SUMIFS(Loans!G:G,Loans!C:C,LTV!F6) -> 2283057.5 | J6: =H6*G6 -> 74381.498 | K6: =INDEX('Tech list'!$A$2:$C$8,MATCH(F6,'Tech list'!$A$2:$A$8,0),3)*J6 -> 99477.815 | L6: =IFERROR(VLOOKUP(F6,Results!$B$4:$F$9,5,0),"-") -> 1898227.5
F7: EUR | G7: {=IFERROR(SUMPRODUCT(Loans!D:D,Loans!F:F,IF(Loans!C:C=LTV!F7,1,0))/SUMIFS(Loans!D:D,Loans!C:C,LTV!F7),0)} -> 0.025230202 | H7: =-SUMIFS(Loans!D:D,Loans!C:C,LTV!F7) -> 24672588 | I7: =-SUMIFS(Loans!G:G,Loans!C:C,LTV!F7) -> 28548652 | J7: =H7*G7 -> 622494.39 | K7: =INDEX('Tech list'!$A$2:$C$8,MATCH(F7,'Tech list'!$A$2:$A$8,0),3)*J7 -> 720288.25 | L7: =IFERROR(VLOOKUP(F7,Results!$B$4:$F$9,5,0),"-")
F8: CHF | G8: {=IFERROR(SUMPRODUCT(Loans!D:D,Loans!F:F,IF(Loans!C:C=LTV!F8,1,0))/SUMIFS(Loans!D:D,Loans!C:C,LTV!F8),0)} -> 0.0066570933 | H8: =-SUMIFS(Loans!D:D,Loans!C:C,LTV!F8) -> 13640419 | I8: =-SUMIFS(Loans!G:G,Loans!C:C,LTV!F8) -> 17503386 | J8: =H8*G8 -> 90805.541 | K8: =INDEX('Tech list'!$A$2:$C$8,MATCH(F8,'Tech list'!$A$2:$A$8,0),3)*J8 -> 116521.67 | L8: =IFERROR(VLOOKUP(F8,Results!$B$4:$F$9,5,0),"-") -> -
F9: JPY | G9: {=IFERROR(SUMPRODUCT(Loans!D:D,Loans!F:F,IF(Loans!C:C=LTV!F9,1,0))/SUMIFS(Loans!D:D,Loans!C:C,LTV!F9),0)} -> 0.015 | H9: =-SUMIFS(Loans!D:D,Loans!C:C,LTV!F9) -> 148246000 | I9: =-SUMIFS(Loans!G:G,Loans!C:C,LTV!F9) -> 935728.75 | J9: =H9*G9 -> 2223690 | K9: =INDEX('Tech list'!$A$2:$C$8,MATCH(F9,'Tech list'!$A$2:$A$8,0),3)*J9 -> 14035.931 | L9: =IFERROR(VLOOKUP(F9,Results!$B$4:$F$9,5,0),"-") -> -
I10: =SUM(I5:I9) -> 49481316 | K10: =SUM(K5:K9) -> 959760.96
F12: Total current Loans by bank '000
F13: CCY | G13: JPM | H13: UBS | I13: Vontobel
F14: USD | G14: =SUMIFS(Loans!$D:$D,Loans!$C:$C,LTV!$F14,Loans!$A:$A,LTV!G$13)/1000 -> -210.49239 | H14: =SUMIFS(Loans!$D:$D,Loans!$C:$C,LTV!$F14,Loans!$A:$A,LTV!H$13)/1000 -> 0 | I14: =SUMIFS(Loans!$D:$D,Loans!$C:$C,LTV!$F14,Loans!$A:$A,LTV!I$13)/1000 -> 0
F15: GBP | G15: =SUMIFS(Loans!$D:$D,Loans!$C:$C,LTV!$F15,Loans!$A:$A,LTV!G$13)/1000 -> -1467.0865 | H15: =SUMIFS(Loans!$D:$D,Loans!$C:$C,LTV!$F15,Loans!$A:$A,LTV!H$13)/1000 -> 0 | I15: =SUMIFS(Loans!$D:$D,Loans!$C:$C,LTV!$F15,Loans!$A:$A,LTV!I$13)/1000 -> -240
F16: EUR | G16: =SUMIFS(Loans!$D:$D,Loans!$C:$C,LTV!$F16,Loans!$A:$A,LTV!G$13)/1000 -> -5388.8953 | H16: =SUMIFS(Loans!$D:$D,Loans!$C:$C,LTV!$F16,Loans!$A:$A,LTV!H$13)/1000 -> -2265.693 | I16: =SUMIFS(Loans!$D:$D,Loans!$C:$C,LTV!$F16,Loans!$A:$A,LTV!I$13)/1000 -> -17018
F17: CHF | G17: =SUMIFS(Loans!$D:$D,Loans!$C:$C,LTV!$F17,Loans!$A:$A,LTV!G$13)/1000 -> -25.7689 | H17: =SUMIFS(Loans!$D:$D,Loans!$C:$C,LTV!$F17,Loans!$A:$A,LTV!H$13)/1000 -> -2000 | I17: =SUMIFS(Loans!$D:$D,Loans!$C:$C,LTV!$F17,Loans!$A:$A,LTV!I$13)/1000 -> -11614.65
F18: JPY | G18: =SUMIFS(Loans!$D:$D,Loans!$C:$C,LTV!$F18,Loans!$A:$A,LTV!G$13)/1000 -> 0 | H18: =SUMIFS(Loans!$D:$D,Loans!$C:$C,LTV!$F18,Loans!$A:$A,LTV!H$13)/1000 -> 0 | I18: =SUMIFS(Loans!$D:$D,Loans!$C:$C,LTV!$F18,Loans!$A:$A,LTV!I$13)/1000 -> -148246
F19: Total in USD | G19: =SUMIFS(Loans!$G:$G,Loans!$A:$A,LTV!G$13)/1000 -> -8441.1313 | H19: =SUMIFS(Loans!$G:$G,Loans!$A:$A,LTV!H$13)/1000 -> -5188.0334 | I19: =SUMIFS(Loans!$G:$G,Loans!$A:$A,LTV!I$13)/1000 -> -35852.151
B25: INPUTs for LTV Calculation (in thouthands of USD) | F25: LTV by banks (Collateral assets) | I25: In tousands of USD | K25: LTV Calculation (By facility) | S25: In tousands of USD
F26: Bank | G26: Collateral Market Value | H26: Loans | I26: LTV | K26: Bank | L26: Source | M26: Collateral Market Value | N26: Assets Adj. 1 | O26: Assets Adj. 2 | P26: Total loans | Q26: Loans Adj. | R26: LTV | S26: Collateral
B27: LHC bonds | C27: =IF(D27="Including",1,0) -> 1 | D27: Including | F27: Vontobel | G27: =SUMIFS($M$27:$M$30,$K$27:$K$30,F27) -> #VALUE! | H27: =SUMIFS($P$27:$P$30,$K$27:$K$30,F27) -> 35852.151 | I27: =H27/G27 -> #VALUE! | K27: Vontobel | L27: Vontobel | M27: =IFERROR((SUMIFS(Bonds!AC:AC,Bonds!B:B,LTV!L27)+ SUMIFS('Bonds ETFs'!S:S,'Bonds ETFs'!A:A,LTV!L27)+ SUMIFS(Deposits!V:V,Deposits!A:A,LTV!L27)+ SUMIFS(Equities!L:L,Equities!A:A,LTV!L27)+ SUMIFS('Alternative assets'!Z:Z,'Alternative assets'!A:A,LTV!L27)+ SUMIFS(Cash!H:H,Cash!A:A,LTV!L27)+ SUMIFS('JPM - DP (3R)'!$J:$J,'JPM - DP (3R)'!$A:$A,LTV!L27)),"")/1000*$N27+$O27 -> #VALUE! | N27: 1 | P27: =-(SUMIFS(Loans!G:G,Loans!A:A,L27)/1000+$Q27) -> 35852.151 | R27: =P27/M27 -> #VALUE! | S27: Antrarras portfolio in Vontobel
B28: Private Equity | C28: =IF(D28="Including",1,0) -> 1 | D28: Including | F28: UBS | G28: =SUMIFS($M$27:$M$30,$K$27:$K$30,F28) -> 20902.871 | H28: =SUMIFS($P$27:$P$30,$K$27:$K$30,F28) -> 5188.0334 | I28: =H28/G28 -> 0.24819717 | K28: UBS | L28: UBS | M28: =IFERROR((SUMIFS(Bonds!AC:AC,Bonds!B:B,LTV!L28)+ SUMIFS('Bonds ETFs'!S:S,'Bonds ETFs'!A:A,LTV!L28)+ SUMIFS(Deposits!V:V,Deposits!A:A,LTV!L28)+ SUMIFS(Equities!L:L,Equities!A:A,LTV!L28)+ SUMIFS('Alternative assets'!Z:Z,'Alternative assets'!A:A,LTV!L28)+ SUMIFS(Cash!H:H,Cash!A:A,LTV!L28)+ SUMIFS('JPM - DP (3R)'!$J:$J,'JPM - DP (3R)'!$A:$A,LTV!L28)),"")/1000*$N28+$O28 -> 20902.871 | N28: 1 | P28: =-(SUMIFS(Loans!G:G,Loans!A:A,L28)/1000+$Q28) -> 5188.0334 | R28: =P28/M28 -> 0.24819717 | S28: Antrarras portfolio in UBS
B29: Mercury portfolio | C29: =IF(D29="Including",1,0) -> 1 | D29: Including | F29: JPM | G29: =SUMIFS($M$27:$M$30,$K$27:$K$30,F29) -> 25945.878 | H29: =SUMIFS($P$27:$P$30,$K$27:$K$30,F29) -> 8441.1313 | I29: =H29/G29 -> 0.32533612 | K29: JPM | L29: JPM Personal | M29: =IFERROR((SUMIFS(Bonds!AC:AC,Bonds!B:B,LTV!L29)+ SUMIFS('Bonds ETFs'!S:S,'Bonds ETFs'!A:A,LTV!L29)+ SUMIFS(Deposits!V:V,Deposits!A:A,LTV!L29)+ SUMIFS(Equities!L:L,Equities!A:A,LTV!L29)+ SUMIFS('Alternative assets'!Z:Z,'Alternative assets'!A:A,LTV!L29)+ SUMIFS(Cash!H:H,Cash!A:A,LTV!L29)+ SUMIFS('JPM - DP (3R)'!$J:$J,'JPM - DP (3R)'!$A:$A,LTV!L29)),"")/1000*$N29+$O29 -> 10000 | N29: 1 | O29: =Deposits!V2/1000 -> 10000 | P29: =-(SUMIFS(Loans!G:G,Loans!A:A,L29)/1000+$Q29) -> 2735.1775 | Q29: =SUMIFS(Loans!$G:$G,Loans!$B:$B,9867456)/1000 -> -2735.1775 | R29: =P29/M29 -> 0.27351775 | S29: USD Liquidity LVNAV Fund in JPM
B30: US Real Estate | C30: =IF(D30="Including",1,0) -> 1 | D30: Including | F30: Total in USD | G30: =SUM(G27:G29) -> #VALUE! | H30: =SUM(H27:H29) -> 49481.316 | I30: =H30/G30 -> #VALUE! | K30: JPM | L30: JPM | M30: =IFERROR((SUMIFS(Bonds!AC:AC,Bonds!B:B,LTV!L30)+ SUMIFS('Bonds ETFs'!S:S,'Bonds ETFs'!A:A,LTV!L30)+ SUMIFS(Deposits!V:V,Deposits!A:A,LTV!L30)+ SUMIFS(Equities!L:L,Equities!A:A,LTV!L30)+ SUMIFS('Alternative assets'!Z:Z,'Alternative assets'!A:A,LTV!L30)+ SUMIFS(Cash!H:H,Cash!A:A,LTV!L30)+ SUMIFS('JPM - DP (3R)'!$J:$J,'JPM - DP (3R)'!$A:$A,LTV!L30)),"")/1000*$N30+$O30 -> 15945.878 | N30: 1 | O30: =-O29 -> -10000 | P30: =-(SUMIFS(Loans!G:G,Loans!A:A,L30)/1000+$Q30) -> 5705.9537 | Q30: =-Q29 -> 2735.1775 | R30: =P30/M30 -> 0.35783252 | S30: 3R portfolio in JPM
B31: Transfer from 3R to Antarras (V) | D31: 0 | K31: Total in USD | M31: =SUM(M27:M30) -> #VALUE! | P31: =SUM(P27:P30) -> 49481.316 | R31: =P31/M31 -> #VALUE!
B32: New credit line in Vontobel | D32: 0
B33: Currency of New credit line in Vontobel | D33: EUR
B34: Transfer from Vontobel to JPM | D34: 6400 | F34: LTV by banks (All assets) | I34: In tousands of USD | K34: LTV Calculation (All assets) | S34: In tousands of USD
B35: Pay off JPM Personal loans | D35: 3200 | F35: Bank | G35: Market Value | H35: Loans | I35: LTV | K35: Asset class | L35: Bank | M35: Market Value | N35: Assets Adj. 1 | O35: Assets Adj. 2 | P35: Total loans | Q35: Loans Adj. | R35: LTV | S35: Source / Group
B36: Pay off JPM 3R loans | D36: =D34-D35 -> 3200 | F36: Vontobel | G36: =SUMIFS($M$36:$M$47,$L$36:$L$47,F36) -> #VALUE! | H36: =SUMIFS($P$36:$P$47,$L$36:$L$47,F36) -> 35852.151 | I36: =IFERROR(H36/G36,"-") -> - | K36: Personal Portfolio | L36: Vontobel | M36: =IFERROR((SUMIFS(Bonds!AC:AC,Bonds!B:B,LTV!S36)+ SUMIFS('Bonds ETFs'!S:S,'Bonds ETFs'!A:A,LTV!S36)+ SUMIFS(Deposits!V:V,Deposits!A:A,LTV!S36)+ SUMIFS(Equities!L:L,Equities!A:A,LTV!S36)+ SUMIFS('Alternative assets'!Z:Z,'Alternative assets'!A:A,LTV!S36)+ SUMIFS(Cash!H:H,Cash!A:A,LTV!S36))+ SUMIFS('Real Estate'!F:F,'Real Estate'!A:A,S36,'Real Estate'!B:B,LTV!K36)+ SUMIFS('JPM - DP (3R)'!$J:$J,'JPM - DP (3R)'!$A:$A,LTV!S36),"")/1000*$N36+$O36 -> 8419.6917 | N36: 1 | O36: =-O37 -> -10000 | S36: Personal
F37: UBS | G37: =SUMIFS($M$36:$M$47,$L$36:$L$47,F37) -> 20902.871 | H37: =SUMIFS($P$36:$P$47,$L$36:$L$47,F37) -> 5188.0334 | I37: =IFERROR(H37/G37,"-") -> 0.24819717 | K37: Personal Portfolio | L37: JPM | M37: =IFERROR((SUMIFS(Bonds!AC:AC,Bonds!B:B,LTV!S37)+ SUMIFS('Bonds ETFs'!S:S,'Bonds ETFs'!A:A,LTV!S37)+ SUMIFS(Deposits!V:V,Deposits!A:A,LTV!S37)+ SUMIFS(Equities!L:L,Equities!A:A,LTV!S37)+ SUMIFS('Alternative assets'!Z:Z,'Alternative assets'!A:A,LTV!S37)+ SUMIFS(Cash!H:H,Cash!A:A,LTV!S37))+ SUMIFS('Real Estate'!F:F,'Real Estate'!A:A,S37,'Real Estate'!B:B,LTV!K37)+ SUMIFS('JPM - DP (3R)'!$J:$J,'JPM - DP (3R)'!$A:$A,LTV!S37),"")/1000*$N37+$O37 -> 10000 | O37: =Deposits!F2/1000 -> 10000 | S37: Personal
F38: JPM | G38: =SUMIFS($M$36:$M$47,$L$36:$L$47,F38) -> 35945.878 | H38: =SUMIFS($P$36:$P$47,$L$36:$L$47,F38) -> 8441.1313 | I38: =IFERROR(H38/G38,"-") -> 0.23482891 | K38: Antarras Portfolio | L38: Vontobel | M38: =IFERROR((SUMIFS(Bonds!AC:AC,Bonds!B:B,LTV!S38)+ SUMIFS('Bonds ETFs'!S:S,'Bonds ETFs'!A:A,LTV!S38)+ SUMIFS(Deposits!V:V,Deposits!A:A,LTV!S38)+ SUMIFS(Equities!L:L,Equities!A:A,LTV!S38)+ SUMIFS('Alternative assets'!Z:Z,'Alternative assets'!A:A,LTV!S38)+ SUMIFS(Cash!H:H,Cash!A:A,LTV!S38))+ SUMIFS('Real Estate'!F:F,'Real Estate'!A:A,S38,'Real Estate'!B:B,LTV!K38)+ SUMIFS('JPM - DP (3R)'!$J:$J,'JPM - DP (3R)'!$A:$A,LTV!S38),"")/1000*$N38+$O38 -> #VALUE! | N38: 1 | P38: =-(SUMIFS(Loans!G:G,Loans!A:A,S38)/1000+$Q38) -> 35852.151 | R38: =P38/M38 -> #VALUE! | S38: Vontobel
F39: Non-bank | G39: =SUMIFS($M$36:$M$47,$L$36:$L$47,F39) -> 53636.191 | H39: =SUMIFS($P$36:$P$47,$L$36:$L$47,F39) -> 0 | I39: =IFERROR(H39/G39,"-") -> 0 | K39: Antarras Portfolio | L39: UBS | M39: =IFERROR((SUMIFS(Bonds!AC:AC,Bonds!B:B,LTV!S39)+ SUMIFS('Bonds ETFs'!S:S,'Bonds ETFs'!A:A,LTV!S39)+ SUMIFS(Deposits!V:V,Deposits!A:A,LTV!S39)+ SUMIFS(Equities!L:L,Equities!A:A,LTV!S39)+ SUMIFS('Alternative assets'!Z:Z,'Alternative assets'!A:A,LTV!S39)+ SUMIFS(Cash!H:H,Cash!A:A,LTV!S39))+ SUMIFS('Real Estate'!F:F,'Real Estate'!A:A,S39,'Real Estate'!B:B,LTV!K39)+ SUMIFS('JPM - DP (3R)'!$J:$J,'JPM - DP (3R)'!$A:$A,LTV!S39),"")/1000*$N39+$O39 -> 20902.871 | N39: 1 | P39: =-(SUMIFS(Loans!G:G,Loans!A:A,S39)/1000+$Q39) -> 5188.0334 | R39: =P39/M39 -> 0.24819717 | S39: UBS
F40: Total in USD | G40: =SUM(G36:G39) -> #VALUE! | H40: =SUM(H36:H39) -> 49481.316 | I40: =IFERROR(H40/G40,"-") -> - | K40: Antarras Portfolio | L40: JPM | M40: =IFERROR((SUMIFS(Bonds!AC:AC,Bonds!B:B,LTV!S40)+ SUMIFS('Bonds ETFs'!S:S,'Bonds ETFs'!A:A,LTV!S40)+ SUMIFS(Deposits!V:V,Deposits!A:A,LTV!S40)+ SUMIFS(Equities!L:L,Equities!A:A,LTV!S40)+ SUMIFS('Alternative assets'!Z:Z,'Alternative assets'!A:A,LTV!S40)+ SUMIFS(Cash!H:H,Cash!A:A,LTV!S40))+ SUMIFS('Real Estate'!F:F,'Real Estate'!A:A,S40,'Real Estate'!B:B,LTV!K40)+ SUMIFS('JPM - DP (3R)'!$J:$J,'JPM - DP (3R)'!$A:$A,LTV!S40),"")/1000*$N40+$O40 -> 12652.666 | N40: 1 | O40: =-SUM('JPM - DP (3R)'!J:J)/1000 -> -13293.212 | P40: =-(SUMIFS(Loans!G:G,Loans!A:A,S40)/1000+$Q40) -> 8441.1313 | R40: =P40/M40 -> 0.66714251 | S40: JPM
K41: Discretionary part JPM | L41: JPM | M41: =IFERROR((SUMIFS(Bonds!AC:AC,Bonds!B:B,LTV!S41)+ SUMIFS('Bonds ETFs'!S:S,'Bonds ETFs'!A:A,LTV!S41)+ SUMIFS(Deposits!V:V,Deposits!A:A,LTV!S41)+ SUMIFS(Equities!L:L,Equities!A:A,LTV!S41)+ SUMIFS('Alternative assets'!Z:Z,'Alternative assets'!A:A,LTV!S41)+ SUMIFS(Cash!H:H,Cash!A:A,LTV!S41))+ SUMIFS('Real Estate'!F:F,'Real Estate'!A:A,S41,'Real Estate'!B:B,LTV!K41)+ SUMIFS('JPM - DP (3R)'!$J:$J,'JPM - DP (3R)'!$A:$A,LTV!S41),"")/1000*$N41+$O41 -> 13293.212 | N41: 0 | O41: =-O40 -> 13293.212 | P41: =-(SUMIFS(Loans!G:G,Loans!A:A,S41)/1000+$Q41) -> 0 | Q41: =P40 -> 8441.1313 | S41: JPM
K42: Private Equity | L42: Non-bank | M42: =IFERROR((SUMIFS(Bonds!AC:AC,Bonds!B:B,LTV!S42)+ SUMIFS('Bonds ETFs'!S:S,'Bonds ETFs'!A:A,LTV!S42)+ SUMIFS(Deposits!V:V,Deposits!A:A,LTV!S42)+ SUMIFS(Equities!L:L,Equities!A:A,LTV!S42)+ SUMIFS('Alternative assets'!Z:Z,'Alternative assets'!A:A,LTV!S42)+ SUMIFS(Cash!H:H,Cash!A:A,LTV!S42))+ SUMIFS('Real Estate'!F:F,'Real Estate'!A:A,S42,'Real Estate'!B:B,LTV!K42)+ SUMIFS('JPM - DP (3R)'!$J:$J,'JPM - DP (3R)'!$A:$A,LTV!S42),"")/1000*$N42+$O42 -> 7637.0178 | N42: 1 | P42: =-(SUMIFS(Loans!G:G,Loans!A:A,S42)/1000+$Q42) -> 0 | S42: Non-bank
K43: LHC Bonds | L43: Vontobel | M43: =SUM('Real Estate'!F2:F4)/1000 -> 26059.051 | N43: 1 | O43: =SUM('Real Estate'!F3:F4)/1000 -> 25121.8 | P43: =-(SUMIFS(Loans!G:G,Loans!A:A,S43)/1000+$Q43) -> 0 | Q43: =P38 -> 35852.151 | S43: Vontobel
K44: Real Estate | L44: Non-bank | M44: =IFERROR((SUMIFS(Bonds!AC:AC,Bonds!B:B,LTV!S44)+ SUMIFS('Bonds ETFs'!S:S,'Bonds ETFs'!A:A,LTV!S44)+ SUMIFS(Deposits!V:V,Deposits!A:A,LTV!S44)+ SUMIFS(Equities!L:L,Equities!A:A,LTV!S44)+ SUMIFS('Alternative assets'!Z:Z,'Alternative assets'!A:A,LTV!S44)+ SUMIFS(Cash!H:H,Cash!A:A,LTV!S44))+ SUMIFS('Real Estate'!F:F,'Real Estate'!A:A,S44,'Real Estate'!B:B,LTV!K44)+ SUMIFS('JPM - DP (3R)'!$J:$J,'JPM - DP (3R)'!$A:$A,LTV!S44),"")/1000*$N44+$O44 -> 24886.57 | N44: 1 | P44: =-(SUMIFS(Loans!G:G,Loans!A:A,S44)/1000+$Q44) -> 0 | S44: Valorem
K45: Real Estate | L45: Non-bank | M45: =IFERROR((SUMIFS(Bonds!AC:AC,Bonds!B:B,LTV!S45)+ SUMIFS('Bonds ETFs'!S:S,'Bonds ETFs'!A:A,LTV!S45)+ SUMIFS(Deposits!V:V,Deposits!A:A,LTV!S45)+ SUMIFS(Equities!L:L,Equities!A:A,LTV!S45)+ SUMIFS('Alternative assets'!Z:Z,'Alternative assets'!A:A,LTV!S45)+ SUMIFS(Cash!H:H,Cash!A:A,LTV!S45))+ SUMIFS('Real Estate'!F:F,'Real Estate'!A:A,S45,'Real Estate'!B:B,LTV!K45)+ SUMIFS('JPM - DP (3R)'!$J:$J,'JPM - DP (3R)'!$A:$A,LTV!S45),"")/1000*$N45+$O45 -> 193.923 | N45: 1 | P45: =-(SUMIFS(Loans!G:G,Loans!A:A,S45)/1000+$Q45) -> 0 | S45: UK PRS
K46: Real Estate | L46: Non-bank | M46: =IFERROR((SUMIFS(Bonds!AC:AC,Bonds!B:B,LTV!S46)+ SUMIFS('Bonds ETFs'!S:S,'Bonds ETFs'!A:A,LTV!S46)+ SUMIFS(Deposits!V:V,Deposits!A:A,LTV!S46)+ SUMIFS(Equities!L:L,Equities!A:A,LTV!S46)+ SUMIFS('Alternative assets'!Z:Z,'Alternative assets'!A:A,LTV!S46)+ SUMIFS(Cash!H:H,Cash!A:A,LTV!S46))+ SUMIFS('Real Estate'!F:F,'Real Estate'!A:A,S46,'Real Estate'!B:B,LTV!K46)+ SUMIFS('JPM - DP (3R)'!$J:$J,'JPM - DP (3R)'!$A:$A,LTV!S46),"")/1000*$N46+$O46 -> 10966.68 | N46: 1 | P46: =-(SUMIFS(Loans!G:G,Loans!A:A,S46)/1000+$Q46) -> 0 | S46: CFP
K47: Real Estate | L47: Non-bank | M47: =IFERROR((SUMIFS(Bonds!AC:AC,Bonds!B:B,LTV!S47)+ SUMIFS('Bonds ETFs'!S:S,'Bonds ETFs'!A:A,LTV!S47)+ SUMIFS(Deposits!V:V,Deposits!A:A,LTV!S47)+ SUMIFS(Equities!L:L,Equities!A:A,LTV!S47)+ SUMIFS('Alternative assets'!Z:Z,'Alternative assets'!A:A,LTV!S47)+ SUMIFS(Cash!H:H,Cash!A:A,LTV!S47))+ SUMIFS('Real Estate'!F:F,'Real Estate'!A:A,S47,'Real Estate'!B:B,LTV!K47)+ SUMIFS('JPM - DP (3R)'!$J:$J,'JPM - DP (3R)'!$A:$A,LTV!S47),"")/1000*$N47+$O47 -> 9952 | N47: 1 | P47: =-(SUMIFS(Loans!G:G,Loans!A:A,S47)/1000+$Q47) -> 0 | S47: US RE
K48: Total in USD | M48: =SUM(M36:M47) -> #VALUE! | P48: =SUM(P38:P47) -> 49481.316 | R48: =P48/M48 -> #VALUE!
M49: (Check with Results)

Sheet Bonds_Analysis
S1: sectors | T1: All in USD | X1: Country | Y1: Region | AD1: Issuer | AG1: Coupon dates | AH1: week | AI1: year | AJ1: USD | AK1: EUR | AL1: GBP | AM1: Total in USD
B2: Top 15 sectors, double cross - quartile | H2: Top 15 bonds, double cross - quartile | M2: Top 15 issuers, double cross - quartile | S2: {=_xlfn.UNIQUE(T_Bonds[Sector marker])} -> Fertilizers | T2: =SUMIFS(T_Bonds[Market value in USD],T_Bonds[Sector marker],S2) -> 408745.58 | U2: =T2/Results!$I$20 -> 0.005697978 | V2: =T2/Results!$I$11 -> 0.0074683583 | X2: {=_xlfn.UNIQUE(T_Bonds[Country])} -> Hungary | Y2: Europe | Z2: =SUMIFS(T_Bonds[Market value in USD],T_Bonds[Country],X2) -> 408745.58 | AA2: {=_xlfn.UNIQUE(Y2:Y29)} -> Europe | AB2: =SUMIFS(Z:Z,Y:Y,AA2)/Results!$I$20 -> 0.22849201 | AD2: {=_xlfn.UNIQUE(T_Bonds[Issuer])} -> Nitrogenmuvek | AE2: =SUMIFS(T_Bonds[Market value in USD],T_Bonds[Issuer],AD2) -> 408745.58 | AG2: {=_xlfn.UNIQUE(#REF!,FALSE,FALSE)} -> #REF! | AH2: =_xlfn.ISOWEEKNUM(AG2) -> #REF! | AI2: =YEAR(AG2) -> #REF! | AJ2: =SUMIFS(#REF!,#REF!,$AG2,T_Bonds[Risk CCY],AJ$1) -> #REF! | AK2: =SUMIFS(#REF!,#REF!,$AG2,T_Bonds[Risk CCY],AK$1) -> #REF! | AL2: =SUMIFS(#REF!,#REF!,$AG2,T_Bonds[Risk CCY],AL$1) -> #REF!
B3: Name | D3: Share in bonds | E3: Share in total | F3: USD total | H3: Name | I3: Share in bonds | J3: Share in total | K3: USD total | M3: Name | N3: Share in bonds | O3: Share in total | P3: USD total | S3: Power | T3: =SUMIFS(T_Bonds[Market value in USD],T_Bonds[Sector marker],S3) -> 3822868.9 | U3: =T3/Results!$I$20 -> 0.053291398 | V3: =T3/Results!$I$11 -> 0.069849208 | X3: Italy | Y3: US+Canada | Z3: =SUMIFS(T_Bonds[Market value in USD],T_Bonds[Country],X3) -> 527256.58 | AA3: US+Canada | AB3: =SUMIFS(Z:Z,Y:Y,AA3)/Results!$I$20 -> 0.11099745 | AD3: Enel | AE3: =SUMIFS(T_Bonds[Market value in USD],T_Bonds[Issuer],AD3) -> 527256.58 | AH3: =_xlfn.ISOWEEKNUM(AG3) -> 52 | AI3: =YEAR(AG3) -> 1900 | AJ3: =SUMIFS(#REF!,#REF!,$AG3,T_Bonds[Risk CCY],AJ$1) -> #REF! | AK3: =SUMIFS(#REF!,#REF!,$AG3,T_Bonds[Risk CCY],AK$1) -> #REF! | AL3: =SUMIFS(#REF!,#REF!,$AG3,T_Bonds[Risk CCY],AL$1) -> #REF!
B4: 1 | C4: =INDEX(S:U,MATCH(D4,U:U,0),1) -> Government | D4: =LARGE(U:U,B4) -> 0.2192013 | E4: =LARGE(V:V,B4) -> 0.28730786 | F4: =LARGE(T:T,B4) -> 15724449 | H4: =INDEX(T_Bonds[[Description]:[Market value in USD]],MATCH(LARGE(T_Bonds[[#All],[Market value in USD]],B4),T_Bonds[Market value in USD],0),1) -> 5.625% United Mex States 19.03.2114 Reg-S Senior | I4: =LARGE(T_Bonds[[#All],[Market value in USD]],B4)/Results!$I$20 -> 0.062090351 | J4: =LARGE(T_Bonds[[#All],[Market value in USD]],B4)/Results!$I$11 -> 0.081382025 | K4: =LARGE(T_Bonds[[#All],[Market value in USD]],B4) -> 4454063.6 | M4: =INDEX(AD:AE,MATCH(P4,AE:AE,0),1) -> Mexico | N4: =LARGE(AE:AE,B4)/Results!$I$20 -> 0.062090351 | O4: =LARGE(AE:AE,B4)/Results!$I$11 -> 0.081382025 | P4: =LARGE(AE:AE,B4) -> 4454063.6 | S4: Oil and Gas Extraction and Refining | T4: =SUMIFS(T_Bonds[Market value in USD],T_Bonds[Sector marker],S4) -> 9150480.4 | U4: =T4/Results!$I$20 -> 0.12755914 | V4: =T4/Results!$I$11 -> 0.16719219 | X4: Brazil | Y4: Latin America | Z4: =SUMIFS(T_Bonds[Market value in USD],T_Bonds[Country],X4) -> 8617695.4 | AA4: Latin America | AB4: =SUMIFS(Z:Z,Y:Y,AA4)/Results!$I$20 -> 0.28287195 | AD4: Petrobras | AE4: =SUMIFS(T_Bonds[Market value in USD],T_Bonds[Issuer],AD4) -> 4244120.4 | AH4: =_xlfn.ISOWEEKNUM(AG4) -> 52 | AI4: =YEAR(AG4) -> 1900 | AJ4: =SUMIFS(#REF!,#REF!,$AG4,T_Bonds[Risk CCY],AJ$1) -> #REF! | AK4: =SUMIFS(#REF!,#REF!,$AG4,T_Bonds[Risk CCY],AK$1) -> #REF! | AL4: =SUMIFS(#REF!,#REF!,$AG4,T_Bonds[Risk CCY],AL$1) -> #REF!
B5: 2 | C5: =INDEX(S:U,MATCH(D5,U:U,0),1) -> AT1 | D5: =LARGE(U:U,B5) -> 0.14577922 | E5: =LARGE(V:V,B5) -> 0.1910733 | F5: =LARGE(T:T,B5) -> 10457501 | H5: =INDEX(T_Bonds[[Description]:[Market value in USD]],MATCH(LARGE(T_Bonds[[#All],[Market value in USD]],B5),T_Bonds[Market value in USD],0),1) -> 6.625% Turkey 17.02.2045 Senior | I5: =LARGE(T_Bonds[[#All],[Market value in USD]],B5)/Results!$I$20 -> 0.03809427 | J5: =LARGE(T_Bonds[[#All],[Market value in USD]],B5)/Results!$I$11 -> 0.049930284 | K5: =LARGE(T_Bonds[[#All],[Market value in USD]],B5) -> 2732700 | M5: =INDEX(AD:AE,MATCH(P5,AE:AE,0),1) -> Petrobras | N5: =LARGE(AE:AE,B5)/Results!$I$20 -> 0.059163709 | O5: =LARGE(AE:AE,B5)/Results!$I$11 -> 0.077546066 | P5: =LARGE(AE:AE,B5) -> 4244120.4 | S5: Leasing and Rental | T5: =SUMIFS(T_Bonds[Market value in USD],T_Bonds[Sector marker],S5) -> 539293.18 | U5: =T5/Results!$I$20 -> 0.0075178322 | V5: =T5/Results!$I$11 -> 0.0098536471 | X5: USA | Y5: US+Canada | Z5: =SUMIFS(T_Bonds[Market value in USD],T_Bonds[Country],X5) -> 7435167.2 | AA5: Australia & Pacific | AB5: =SUMIFS(Z:Z,Y:Y,AA5)/Results!$I$20 -> 0.069355654 | AD5: Ford Motor Credit Company | AE5: =SUMIFS(T_Bonds[Market value in USD],T_Bonds[Issuer],AD5) -> 539293.18 | AH5: =_xlfn.ISOWEEKNUM(AG5) -> 52 | AI5: =YEAR(AG5) -> 1900 | AJ5: =SUMIFS(#REF!,#REF!,$AG5,T_Bonds[Risk CCY],AJ$1) -> #REF! | AK5: =SUMIFS(#REF!,#REF!,$AG5,T_Bonds[Risk CCY],AK$1) -> #REF! | AL5: =SUMIFS(#REF!,#REF!,$AG5,T_Bonds[Risk CCY],AL$1) -> #REF!
B6: 3 | C6: =INDEX(S:U,MATCH(D6,U:U,0),1) -> Oil and Gas Extraction and Refining | D6: =LARGE(U:U,B6) -> 0.12755914 | E6: =LARGE(V:V,B6) -> 0.16719219 | F6: =LARGE(T:T,B6) -> 9150480.4 | H6: =INDEX(T_Bonds[[Description]:[Market value in USD]],MATCH(LARGE(T_Bonds[[#All],[Market value in USD]],B6),T_Bonds[Market value in USD],0),1) -> 6.375% ABN AMRO Open End FRN Subordinated | I6: =LARGE(T_Bonds[[#All],[Market value in USD]],B6)/Results!$I$20 -> 0.034573379 | J6: =LARGE(T_Bonds[[#All],[Market value in USD]],B6)/Results!$I$11 -> 0.04531544 | K6: =LARGE(T_Bonds[[#All],[Market value in USD]],B6) -> 2480128.1 | M6: =INDEX(AD:AE,MATCH(P6,AE:AE,0),1) -> Turkey | N6: =LARGE(AE:AE,B6)/Results!$I$20 -> 0.03809427 | O6: =LARGE(AE:AE,B6)/Results!$I$11 -> 0.049930284 | P6: =LARGE(AE:AE,B6) -> 2732700 | S6: AT1 | T6: =SUMIFS(T_Bonds[Market value in USD],T_Bonds[Sector marker],S6) -> 10457501 | U6: =T6/Results!$I$20 -> 0.14577922 | V6: =T6/Results!$I$11 -> 0.1910733 | X6: Denmark | Y6: Australia & Pacific | Z6: =SUMIFS(T_Bonds[Market value in USD],T_Bonds[Country],X6) -> 474081.55 | AA6: Asia | AB6: =SUMIFS(Z:Z,Y:Y,AA6)/Results!$I$20 -> 0.094701127 | AD6: Orsted | AE6: =SUMIFS(T_Bonds[Market value in USD],T_Bonds[Issuer],AD6) -> 474081.55 | AH6: =_xlfn.ISOWEEKNUM(AG6) -> 52 | AI6: =YEAR(AG6) -> 1900 | AJ6: =SUMIFS(#REF!,#REF!,$AG6,T_Bonds[Risk CCY],AJ$1) -> #REF! | AK6: =SUMIFS(#REF!,#REF!,$AG6,T_Bonds[Risk CCY],AK$1) -> #REF! | AL6: =SUMIFS(#REF!,#REF!,$AG6,T_Bonds[Risk CCY],AL$1) -> #REF!
B7: 4 | C7: =INDEX(S:U,MATCH(D7,U:U,0),1) -> Banks | D7: =LARGE(U:U,B7) -> 0.11568944 | E7: =LARGE(V:V,B7) -> 0.15163453 | F7: =LARGE(T:T,B7) -> 8299004.9 | H7: =INDEX(T_Bonds[[Description]:[Market value in USD]],MATCH(LARGE(T_Bonds[[#All],[Market value in USD]],B7),T_Bonds[Market value in USD],0),1) -> 6.85% Petrobras Glob 05.06.2115 Senior | I7: =LARGE(T_Bonds[[#All],[Market value in USD]],B7)/Results!$I$20 -> 0.026185193 | J7: =LARGE(T_Bonds[[#All],[Market value in USD]],B7)/Results!$I$11 -> 0.034321018 | K7: =LARGE(T_Bonds[[#All],[Market value in USD]],B7) -> 1878400 | M7: =INDEX(AD:AE,MATCH(P7,AE:AE,0),1) -> ABN AMRO | N7: =LARGE(AE:AE,B7)/Results!$I$20 -> 0.034573379 | O7: =LARGE(AE:AE,B7)/Results!$I$11 -> 0.04531544 | P7: =LARGE(AE:AE,B7) -> 2480128.1 | S7: Utilities | T7: =SUMIFS(T_Bonds[Market value in USD],T_Bonds[Sector marker],S7) -> 279302.62 | U7: =T7/Results!$I$20 -> 0.0038935227 | V7: =T7/Results!$I$11 -> 0.0051032528 | X7: United Kingdom | Y7: Europe | Z7: =SUMIFS(T_Bonds[Market value in USD],T_Bonds[Country],X7) -> 5723683.9 | AA7: Mid.East & Africa | AB7: =SUMIFS(Z:Z,Y:Y,AA7)/Results!$I$20 -> 0.16837862 | AD7: Lloyds Banking Group | AE7: =SUMIFS(T_Bonds[Market value in USD],T_Bonds[Issuer],AD7) -> 842802.73 | AH7: =_xlfn.ISOWEEKNUM(AG7) -> 52 | AI7: =YEAR(AG7) -> 1900 | AJ7: =SUMIFS(#REF!,#REF!,$AG7,T_Bonds[Risk CCY],AJ$1) -> #REF! | AK7: =SUMIFS(#REF!,#REF!,$AG7,T_Bonds[Risk CCY],AK$1) -> #REF! | AL7: =SUMIFS(#REF!,#REF!,$AG7,T_Bonds[Risk CCY],AL$1) -> #REF!
B8: 5 | C8: =INDEX(S:U,MATCH(D8,U:U,0),1) -> Chemical and petrochemical industry | D8: =LARGE(U:U,B8) -> 0.055599816 | E8: =LARGE(V:V,B8) -> 0.07287486 | F8: =LARGE(T:T,B8) -> 3988463.8 | H8: =INDEX(T_Bonds[[Description]:[Market value in USD]],MATCH(LARGE(T_Bonds[[#All],[Market value in USD]],B8),T_Bonds[Market value in USD],0),1) -> 7.125% Brazil 13.05.2054 Senior | I8: =LARGE(T_Bonds[[#All],[Market value in USD]],B8)/Results!$I$20 -> 0.024966823 | J8: =LARGE(T_Bonds[[#All],[Market value in USD]],B8)/Results!$I$11 -> 0.032724097 | K8: =LARGE(T_Bonds[[#All],[Market value in USD]],B8) -> 1791000 | M8: =INDEX(AD:AE,MATCH(P8,AE:AE,0),1) -> Credit Agricole SA | N8: =LARGE(AE:AE,B8)/Results!$I$20 -> 0.030836169 | O8: =LARGE(AE:AE,B8)/Results!$I$11 -> 0.040417067 | P8: =LARGE(AE:AE,B8) -> 2212038.7 | S8: Media | T8: =SUMIFS(T_Bonds[Market value in USD],T_Bonds[Sector marker],S8) -> 820386 | U8: =T8/Results!$I$20 -> 0.011436311 | V8: =T8/Results!$I$11 -> 0.01498961 | X8: France | Y8: Latin America | Z8: =SUMIFS(T_Bonds[Market value in USD],T_Bonds[Country],X8) -> 6446876.6 | AA8: Africa | AB8: =SUMIFS(Z:Z,Y:Y,AA8)/Results!$I$20 -> 0.014201118 | AD8: Electricité de France | AE8: =SUMIFS(T_Bonds[Market value in USD],T_Bonds[Issuer],AD8) -> 279302.62 | AH8: =_xlfn.ISOWEEKNUM(AG8) -> 52 | AI8: =YEAR(AG8) -> 1900 | AJ8: =SUMIFS(#REF!,#REF!,$AG8,T_Bonds[Risk CCY],AJ$1) -> #REF! | AK8: =SUMIFS(#REF!,#REF!,$AG8,T_Bonds[Risk CCY],AK$1) -> #REF! | AL8: =SUMIFS(#REF!,#REF!,$AG8,T_Bonds[Risk CCY],AL$1) -> #REF!
B9: 6 | C9: =INDEX(S:U,MATCH(D9,U:U,0),1) -> Power | D9: =LARGE(U:U,B9) -> 0.053291398 | E9: =LARGE(V:V,B9) -> 0.069849208 | F9: =LARGE(T:T,B9) -> 3822868.9 | H9: =INDEX(T_Bonds[[Description]:[Market value in USD]],MATCH(LARGE(T_Bonds[[#All],[Market value in USD]],B9),T_Bonds[Market value in USD],0),1) -> 7% Erste Group Bk Open End FRN Subordinated | I9: =LARGE(T_Bonds[[#All],[Market value in USD]],B9)/Results!$I$20 -> 0.024603329 | J9: =LARGE(T_Bonds[[#All],[Market value in USD]],B9)/Results!$I$11 -> 0.032247663 | K9: =LARGE(T_Bonds[[#All],[Market value in USD]],B9) -> 1764924.6 | M9: =INDEX(AD:AE,MATCH(P9,AE:AE,0),1) -> Ecopetrol | N9: =LARGE(AE:AE,B9)/Results!$I$20 -> 0.028484762 | O9: =LARGE(AE:AE,B9)/Results!$I$11 -> 0.03733507 | P9: =LARGE(AE:AE,B9) -> 2043360 | S9: Government | T9: =SUMIFS(T_Bonds[Market value in USD],T_Bonds[Sector marker],S9) -> 15724449 | U9: =T9/Results!$I$20 -> 0.2192013 | V9: =T9/Results!$I$11 -> 0.28730786 | X9: Israel | Y9: Asia | Z9: =SUMIFS(T_Bonds[Market value in USD],T_Bonds[Country],X9) -> 3106640 | AD9: Warnermedia Holdings | AE9: =SUMIFS(T_Bonds[Market value in USD],T_Bonds[Issuer],AD9) -> 820386 | AH9: =_xlfn.ISOWEEKNUM(AG9) -> 52 | AI9: =YEAR(AG9) -> 1900 | AJ9: =SUMIFS(#REF!,#REF!,$AG9,T_Bonds[Risk CCY],AJ$1) -> #REF! | AK9: =SUMIFS(#REF!,#REF!,$AG9,T_Bonds[Risk CCY],AK$1) -> #REF! | AL9: =SUMIFS(#REF!,#REF!,$AG9,T_Bonds[Risk CCY],AL$1) -> #REF!
B10: 7 | C10: =INDEX(S:U,MATCH(D10,U:U,0),1) -> Non-ferrous metals | D10: =LARGE(U:U,B10) -> 0.050227282 | E10: =LARGE(V:V,B10) -> 0.065833062 | F10: =LARGE(T:T,B10) -> 3603064 | H10: =INDEX(T_Bonds[[Description]:[Market value in USD]],MATCH(LARGE(T_Bonds[[#All],[Market value in USD]],B10),T_Bonds[Market value in USD],0),1) -> 7.375% EDF Open End FRN Reg-S Subordinated | I10: =LARGE(T_Bonds[[#All],[Market value in USD]],B10)/Results!$I$20 -> 0.023155311 | J10: =LARGE(T_Bonds[[#All],[Market value in USD]],B10)/Results!$I$11 -> 0.030349741 | K10: =LARGE(T_Bonds[[#All],[Market value in USD]],B10) -> 1661050.8 | M10: =INDEX(AD:AE,MATCH(P10,AE:AE,0),1) -> Vedanta Resources | N10: =LARGE(AE:AE,B10)/Results!$I$20 -> 0.027239961 | O10: =LARGE(AE:AE,B10)/Results!$I$11 -> 0.035703506 | P10: =LARGE(AE:AE,B10) -> 1954064 | S10: Semiconductors | T10: =SUMIFS(T_Bonds[Market value in USD],T_Bonds[Sector marker],S10) -> 345780 | U10: =T10/Results!$I$20 -> 0.0048202279 | V10: =T10/Results!$I$11 -> 0.0063178884 | X10: Australia | Y10: Europe | Z10: =SUMIFS(T_Bonds[Market value in USD],T_Bonds[Country],X10) -> 374920 | AD10: Israel | AE10: =SUMIFS(T_Bonds[Market value in USD],T_Bonds[Issuer],AD10) -> 592240 | AH10: =_xlfn.ISOWEEKNUM(AG10) -> 52 | AI10: =YEAR(AG10) -> 1900 | AJ10: =SUMIFS(#REF!,#REF!,$AG10,T_Bonds[Risk CCY],AJ$1) -> #REF! | AK10: =SUMIFS(#REF!,#REF!,$AG10,T_Bonds[Risk CCY],AK$1) -> #REF! | AL10: =SUMIFS(#REF!,#REF!,$AG10,T_Bonds[Risk CCY],AL$1) -> #REF!
B11: 8 | C11: =INDEX(S:U,MATCH(D11,U:U,0),1) -> Insurance and Reinsurance | D11: =LARGE(U:U,B11) -> 0.025845673 | E11: =LARGE(V:V,B11) -> 0.033876008 | F11: =LARGE(T:T,B11) -> 1854044.5 | H11: =INDEX(T_Bonds[[Description]:[Market value in USD]],MATCH(LARGE(T_Bonds[[#All],[Market value in USD]],B11),T_Bonds[Market value in USD],0),1) -> 6.375% KazMunayGaz 24.10.2048 Reg-S Senior | I11: =LARGE(T_Bonds[[#All],[Market value in USD]],B11)/Results!$I$20 -> 0.018916446 | J11: =LARGE(T_Bonds[[#All],[Market value in USD]],B11)/Results!$I$11 -> 0.024793848 | K11: =LARGE(T_Bonds[[#All],[Market value in USD]],B11) -> 1356975 | M11: =INDEX(AD:AE,MATCH(P11,AE:AE,0),1) -> OCP SA | N11: =LARGE(AE:AE,B11)/Results!$I$20 -> 0.026419667 | O11: =LARGE(AE:AE,B11)/Results!$I$11 -> 0.034628343 | P11: =LARGE(AE:AE,B11) -> 1895220 | S11: Chemical and petrochemical industry | T11: =SUMIFS(T_Bonds[Market value in USD],T_Bonds[Sector marker],S11) -> 3988463.8 | U11: =T11/Results!$I$20 -> 0.055599816 | V11: =T11/Results!$I$11 -> 0.07287486 | X11: Mexico | Y11: Mid.East & Africa | Z11: =SUMIFS(T_Bonds[Market value in USD],T_Bonds[Country],X11) -> 6103828.6 | AD11: Intel | AE11: =SUMIFS(T_Bonds[Market value in USD],T_Bonds[Issuer],AD11) -> 345780 | AH11: =_xlfn.ISOWEEKNUM(AG11) -> 52 | AI11: =YEAR(AG11) -> 1900 | AJ11: =SUMIFS(#REF!,#REF!,$AG11,T_Bonds[Risk CCY],AJ$1) -> #REF! | AK11: =SUMIFS(#REF!,#REF!,$AG11,T_Bonds[Risk CCY],AK$1) -> #REF! | AL11: =SUMIFS(#REF!,#REF!,$AG11,T_Bonds[Risk CCY],AL$1) -> #REF!
B12: 9 | C12: =INDEX(S:U,MATCH(D12,U:U,0),1) -> Food and Beverage Production | D12: =LARGE(U:U,B12) -> 0.018547729 | E12: =LARGE(V:V,B12) -> 0.024310569 | F12: =LARGE(T:T,B12) -> 1330525 | H12: =INDEX(T_Bonds[[Description]:[Market value in USD]],MATCH(LARGE(T_Bonds[[#All],[Market value in USD]],B12),T_Bonds[Market value in USD],0),1) -> 6.5% Cooperatieve Rabobank Open End FRN Reg-S Junior Subordinated | I12: =LARGE(T_Bonds[[#All],[Market value in USD]],B12)/Results!$I$20 -> 0.018681141 | J12: =LARGE(T_Bonds[[#All],[Market value in USD]],B12)/Results!$I$11 -> 0.024485433 | K12: =LARGE(T_Bonds[[#All],[Market value in USD]],B12) -> 1340095.4 | M12: =INDEX(AD:AE,MATCH(P12,AE:AE,0),1) -> IBRD | N12: =LARGE(AE:AE,B12)/Results!$I$20 -> 0.025642575 | O12: =LARGE(AE:AE,B12)/Results!$I$11 -> 0.033609807 | P12: =LARGE(AE:AE,B12) -> 1839475.2 | S12: Non-ferrous metals | T12: =SUMIFS(T_Bonds[Market value in USD],T_Bonds[Sector marker],S12) -> 3603064 | U12: =T12/Results!$I$20 -> 0.050227282 | V12: =T12/Results!$I$11 -> 0.065833062 | X12: India | Y12: Asia | Z12: =SUMIFS(T_Bonds[Market value in USD],T_Bonds[Country],X12) -> 3686764 | AD12: Albemarle | AE12: =SUMIFS(T_Bonds[Market value in USD],T_Bonds[Issuer],AD12) -> 368823.8 | AH12: =_xlfn.ISOWEEKNUM(AG12) -> 52 | AI12: =YEAR(AG12) -> 1900 | AJ12: =SUMIFS(#REF!,#REF!,$AG12,T_Bonds[Risk CCY],AJ$1) -> #REF! | AK12: =SUMIFS(#REF!,#REF!,$AG12,T_Bonds[Risk CCY],AK$1) -> #REF! | AL12: =SUMIFS(#REF!,#REF!,$AG12,T_Bonds[Risk CCY],AL$1) -> #REF!
B13: 10 | C13: =INDEX(S:U,MATCH(D13,U:U,0),1) -> Ferrous metals | D13: =LARGE(U:U,B13) -> 0.017594292 | E13: =LARGE(V:V,B13) -> 0.023060896 | F13: =LARGE(T:T,B13) -> 1262130 | H13: =INDEX(T_Bonds[[Description]:[Market value in USD]],MATCH(LARGE(T_Bonds[[#All],[Market value in USD]],B13),T_Bonds[Market value in USD],0),1) -> 6.875% OCP 25.04.2044 Reg-S Senior | I13: =LARGE(T_Bonds[[#All],[Market value in USD]],B13)/Results!$I$20 -> 0.017337932 | J13: =LARGE(T_Bonds[[#All],[Market value in USD]],B13)/Results!$I$11 -> 0.022724884 | K13: =LARGE(T_Bonds[[#All],[Market value in USD]],B13) -> 1243740 | M13: =INDEX(AD:AE,MATCH(P13,AE:AE,0),1) -> Brazil | N13: =LARGE(AE:AE,B13)/Results!$I$20 -> 0.024966823 | O13: =LARGE(AE:AE,B13)/Results!$I$11 -> 0.032724097 | P13: =LARGE(AE:AE,B13) -> 1791000 | S13: Other Financial Institutions | T13: =SUMIFS(T_Bonds[Market value in USD],T_Bonds[Sector marker],S13) -> 1235880 | U13: =T13/Results!$I$20 -> 0.017228363 | V13: =T13/Results!$I$11 -> 0.022581271 | X13: Kazakhstan | Y13: Europe | Z13: =SUMIFS(T_Bonds[Market value in USD],T_Bonds[Country],X13) -> 1356975 | AD13: Woodside Energy | AE13: =SUMIFS(T_Bonds[Market value in USD],T_Bonds[Issuer],AD13) -> 374920 | AH13: =_xlfn.ISOWEEKNUM(AG13) -> 52 | AI13: =YEAR(AG13) -> 1900 | AJ13: =SUMIFS(#REF!,#REF!,$AG13,T_Bonds[Risk CCY],AJ$1) -> #REF! | AK13: =SUMIFS(#REF!,#REF!,$AG13,T_Bonds[Risk CCY],AK$1) -> #REF! | AL13: =SUMIFS(#REF!,#REF!,$AG13,T_Bonds[Risk CCY],AL$1) -> #REF!
B14: 11 | C14: =INDEX(S:U,MATCH(D14,U:U,0),1) -> Other Financial Institutions | D14: =LARGE(U:U,B14) -> 0.017228363 | E14: =LARGE(V:V,B14) -> 0.022581271 | F14: =LARGE(T:T,B14) -> 1235880 | H14: =INDEX(T_Bonds[[Description]:[Market value in USD]],MATCH(LARGE(T_Bonds[[#All],[Market value in USD]],B14),T_Bonds[Market value in USD],0),1) -> 5.875% Credit Agricole Open End FRN Reg-S Junior Subordinated | I14: =LARGE(T_Bonds[[#All],[Market value in USD]],B14)/Results!$I$20 -> 0.016626966 | J14: =LARGE(T_Bonds[[#All],[Market value in USD]],B14)/Results!$I$11 -> 0.021793018 | K14: =LARGE(T_Bonds[[#All],[Market value in USD]],B14) -> 1192738.7 | M14: =INDEX(AD:AE,MATCH(P14,AE:AE,0),1) -> Erste Group | N14: =LARGE(AE:AE,B14)/Results!$I$20 -> 0.024603329 | O14: =LARGE(AE:AE,B14)/Results!$I$11 -> 0.032247663 | P14: =LARGE(AE:AE,B14) -> 1764924.6 | S14: Precious Metal Mining | T14: =SUMIFS(T_Bonds[Market value in USD],T_Bonds[Sector marker],S14) -> 0 | U14: =T14/Results!$I$20 -> 0 | V14: =T14/Results!$I$11 -> 0 | X14: Colombia | Y14: Europe | Z14: =SUMIFS(T_Bonds[Market value in USD],T_Bonds[Country],X14) -> 3564420 | AD14: Pemex | AE14: =SUMIFS(T_Bonds[Market value in USD],T_Bonds[Issuer],AD14) -> 898325 | AH14: =_xlfn.ISOWEEKNUM(AG14) -> 52 | AI14: =YEAR(AG14) -> 1900 | AJ14: =SUMIFS(#REF!,#REF!,$AG14,T_Bonds[Risk CCY],AJ$1) -> #REF! | AK14: =SUMIFS(#REF!,#REF!,$AG14,T_Bonds[Risk CCY],AK$1) -> #REF! | AL14: =SUMIFS(#REF!,#REF!,$AG14,T_Bonds[Risk CCY],AL$1) -> #REF!
B15: 12 | C15: =INDEX(S:U,MATCH(D15,U:U,0),1) -> Communication Services | D15: =LARGE(U:U,B15) -> 0.014750081 | E15: =LARGE(V:V,B15) -> 0.01933298 | F15: =LARGE(T:T,B15) -> 1058100 | H15: =INDEX(T_Bonds[[Description]:[Market value in USD]],MATCH(LARGE(T_Bonds[[#All],[Market value in USD]],B15),T_Bonds[Market value in USD],0),1) -> 7.75% Aviva Open End FRN Conv Subordinated | I15: =LARGE(T_Bonds[[#All],[Market value in USD]],B15)/Results!$I$20 -> 0.015996181 | J15: =LARGE(T_Bonds[[#All],[Market value in USD]],B15)/Results!$I$11 -> 0.020966246 | K15: =LARGE(T_Bonds[[#All],[Market value in USD]],B15) -> 1147489.2 | M15: =INDEX(AD:AE,MATCH(P15,AE:AE,0),1) -> Electricite de France (EDF) | N15: =LARGE(AE:AE,B15)/Results!$I$20 -> 0.023155311 | O15: =LARGE(AE:AE,B15)/Results!$I$11 -> 0.030349741 | P15: =LARGE(AE:AE,B15) -> 1661050.8 | S15: Ferrous metals | T15: =SUMIFS(T_Bonds[Market value in USD],T_Bonds[Sector marker],S15) -> 1262130 | U15: =T15/Results!$I$20 -> 0.017594292 | V15: =T15/Results!$I$11 -> 0.023060896 | X15: South Africa | Y15: Europe | Z15: =SUMIFS(T_Bonds[Market value in USD],T_Bonds[Country],X15) -> 2221600 | AD15: Vedanta Resources | AE15: =SUMIFS(T_Bonds[Market value in USD],T_Bonds[Issuer],AD15) -> 1954064 | AH15: =_xlfn.ISOWEEKNUM(AG15) -> 52 | AI15: =YEAR(AG15) -> 1900 | AJ15: =SUMIFS(#REF!,#REF!,$AG15,T_Bonds[Risk CCY],AJ$1) -> #REF! | AK15: =SUMIFS(#REF!,#REF!,$AG15,T_Bonds[Risk CCY],AK$1) -> #REF! | AL15: =SUMIFS(#REF!,#REF!,$AG15,T_Bonds[Risk CCY],AL$1) -> #REF!
B16: 13 | C16: =INDEX(S:U,MATCH(D16,U:U,0),1) -> Holding Companies | D16: =LARGE(U:U,B16) -> 0.012563707 | E16: =LARGE(V:V,B16) -> 0.016467292 | F16: =LARGE(T:T,B16) -> 901260 | H16: =INDEX(T_Bonds[[Description]:[Market value in USD]],MATCH(LARGE(T_Bonds[[#All],[Market value in USD]],B16),T_Bonds[Market value in USD],0),1) -> 10.75% IBRD 09.10.2031 Reg-S Senior | I16: =LARGE(T_Bonds[[#All],[Market value in USD]],B16)/Results!$I$20 -> 0.015363705 | J16: =LARGE(T_Bonds[[#All],[Market value in USD]],B16)/Results!$I$11 -> 0.020137258 | K16: =LARGE(T_Bonds[[#All],[Market value in USD]],B16) -> 1102118.4 | M16: =INDEX(AD:AE,MATCH(P16,AE:AE,0),1) -> Colombia | N16: =LARGE(AE:AE,B16)/Results!$I$20 -> 0.021203817 | O16: =LARGE(AE:AE,B16)/Results!$I$11 -> 0.027791912 | P16: =LARGE(AE:AE,B16) -> 1521060 | S16: Food and Beverage Production | T16: =SUMIFS(T_Bonds[Market value in USD],T_Bonds[Sector marker],S16) -> 1330525 | U16: =T16/Results!$I$20 -> 0.018547729 | V16: =T16/Results!$I$11 -> 0.024310569 | X16: Turkey | Y16: Mid.East & Africa | Z16: =SUMIFS(T_Bonds[Market value in USD],T_Bonds[Country],X16) -> 4209920 | AD16: Energean Israel Finance | AE16: =SUMIFS(T_Bonds[Market value in USD],T_Bonds[Issuer],AD16) -> 857640 | AH16: =_xlfn.ISOWEEKNUM(AG16) -> 52 | AI16: =YEAR(AG16) -> 1900 | AJ16: =SUMIFS(#REF!,#REF!,$AG16,T_Bonds[Risk CCY],AJ$1) -> #REF! | AK16: =SUMIFS(#REF!,#REF!,$AG16,T_Bonds[Risk CCY],AK$1) -> #REF! | AL16: =SUMIFS(#REF!,#REF!,$AG16,T_Bonds[Risk CCY],AL$1) -> #REF!
B17: 14 | C17: =INDEX(S:U,MATCH(D17,U:U,0),1) -> Media | D17: =LARGE(U:U,B17) -> 0.011436311 | E17: =LARGE(V:V,B17) -> 0.01498961 | F17: =LARGE(T:T,B17) -> 820386 | H17: =INDEX(T_Bonds[[Description]:[Market value in USD]],MATCH(LARGE(T_Bonds[[#All],[Market value in USD]],B17),T_Bonds[Market value in USD],0),1) -> 7.65% Turkcell Iletisim 24.01.2032 Reg-S Senior | I17: =LARGE(T_Bonds[[#All],[Market value in USD]],B17)/Results!$I$20 -> 0.014750081 | J17: =LARGE(T_Bonds[[#All],[Market value in USD]],B17)/Results!$I$11 -> 0.01933298 | K17: =LARGE(T_Bonds[[#All],[Market value in USD]],B17) -> 1058100 | M17: =INDEX(AD:AE,MATCH(P17,AE:AE,0),1) -> Romania | N17: =LARGE(AE:AE,B17)/Results!$I$20 -> 0.019614918 | O17: =LARGE(AE:AE,B17)/Results!$I$11 -> 0.025709337 | P17: =LARGE(AE:AE,B17) -> 1407080 | S17: Online Retail | T17: =SUMIFS(T_Bonds[Market value in USD],T_Bonds[Sector marker],S17) -> 668940 | U17: =T17/Results!$I$20 -> 0.0093251294 | V17: =T17/Results!$I$11 -> 0.012222477 | X17: Panama | Y17: Europe | Z17: =SUMIFS(T_Bonds[Market value in USD],T_Bonds[Country],X17) -> 822160 | AD17: KazMunayGas | AE17: =SUMIFS(T_Bonds[Market value in USD],T_Bonds[Issuer],AD17) -> 1356975 | AH17: =_xlfn.ISOWEEKNUM(AG17) -> 52 | AI17: =YEAR(AG17) -> 1900 | AJ17: =SUMIFS(#REF!,#REF!,$AG17,T_Bonds[Risk CCY],AJ$1) -> #REF! | AK17: =SUMIFS(#REF!,#REF!,$AG17,T_Bonds[Risk CCY],AK$1) -> #REF! | AL17: =SUMIFS(#REF!,#REF!,$AG17,T_Bonds[Risk CCY],AL$1) -> #REF!
B18: 15 | C18: =INDEX(S:U,MATCH(D18,U:U,0),1) -> Technology | D18: =LARGE(U:U,B18) -> 0.011080809 | E18: =LARGE(V:V,B18) -> 0.014523652 | F18: =LARGE(T:T,B18) -> 794884 | H18: =INDEX(T_Bonds[[Description]:[Market value in USD]],MATCH(LARGE(T_Bonds[[#All],[Market value in USD]],B18),T_Bonds[Market value in USD],0),1) -> 9.125% Vedanta Resourc 15.10.2032 Senior | I18: =LARGE(T_Bonds[[#All],[Market value in USD]],B18)/Results!$I$20 -> 0.014518675 | J18: =LARGE(T_Bonds[[#All],[Market value in USD]],B18)/Results!$I$11 -> 0.019029674 | K18: =LARGE(T_Bonds[[#All],[Market value in USD]],B18) -> 1041500 | M18: =INDEX(AD:AE,MATCH(P18,AE:AE,0),1) -> KazMunayGas | N18: =LARGE(AE:AE,B18)/Results!$I$20 -> 0.018916446 | O18: =LARGE(AE:AE,B18)/Results!$I$11 -> 0.024793848 | P18: =LARGE(AE:AE,B18) -> 1356975 | S18: Banks | T18: =SUMIFS(T_Bonds[Market value in USD],T_Bonds[Sector marker],S18) -> 8299004.9 | U18: =T18/Results!$I$20 -> 0.11568944 | V18: =T18/Results!$I$11 -> 0.15163453 | X18: Japan | Y18: Australia & Pacific | Z18: =SUMIFS(T_Bonds[Market value in USD],T_Bonds[Country],X18) -> 2605940 | AD18: Leviathan Bond | AE18: =SUMIFS(T_Bonds[Market value in USD],T_Bonds[Issuer],AD18) -> 616260 | AH18: =_xlfn.ISOWEEKNUM(AG18) -> 52 | AI18: =YEAR(AG18) -> 1900 | AJ18: =SUMIFS(#REF!,#REF!,$AG18,T_Bonds[Risk CCY],AJ$1) -> #REF! | AK18: =SUMIFS(#REF!,#REF!,$AG18,T_Bonds[Risk CCY],AK$1) -> #REF! | AL18: =SUMIFS(#REF!,#REF!,$AG18,T_Bonds[Risk CCY],AL$1) -> #REF!
S19: Transportation Support Activities | T19: =SUMIFS(T_Bonds[Market value in USD],T_Bonds[Sector marker],S19) -> 691200 | U19: =T19/Results!$I$20 -> 0.0096354374 | V19: =T19/Results!$I$11 -> 0.012629199 | X19: Morocco | Y19: Australia & Pacific | Z19: =SUMIFS(T_Bonds[Market value in USD],T_Bonds[Country],X19) -> 1895220 | AD19: Ecopetrol | AE19: =SUMIFS(T_Bonds[Market value in USD],T_Bonds[Issuer],AD19) -> 2043360 | AH19: =_xlfn.ISOWEEKNUM(AG19) -> 52 | AI19: =YEAR(AG19) -> 1900 | AJ19: =SUMIFS(#REF!,#REF!,$AG19,T_Bonds[Risk CCY],AJ$1) -> #REF! | AK19: =SUMIFS(#REF!,#REF!,$AG19,T_Bonds[Risk CCY],AK$1) -> #REF! | AL19: =SUMIFS(#REF!,#REF!,$AG19,T_Bonds[Risk CCY],AL$1) -> #REF!
B20: Duration ranges | I20: Top geography | S20: Holding Companies | T20: =SUMIFS(T_Bonds[Market value in USD],T_Bonds[Sector marker],S20) -> 901260 | U20: =T20/Results!$I$20 -> 0.012563707 | V20: =T20/Results!$I$11 -> 0.016467292 | X20: Canada | Y20: Europe | Z20: =SUMIFS(T_Bonds[Market value in USD],T_Bonds[Country],X20) -> 211480 | AD20: Sibanye Gold | AE20: =SUMIFS(T_Bonds[Market value in USD],T_Bonds[Issuer],AD20) -> 0 | AH20: =_xlfn.ISOWEEKNUM(AG20) -> 52 | AI20: =YEAR(AG20) -> 1900 | AJ20: =SUMIFS(#REF!,#REF!,$AG20,T_Bonds[Risk CCY],AJ$1) -> #REF! | AK20: =SUMIFS(#REF!,#REF!,$AG20,T_Bonds[Risk CCY],AK$1) -> #REF! | AL20: =SUMIFS(#REF!,#REF!,$AG20,T_Bonds[Risk CCY],AL$1) -> #REF!
B21: <1 year | C21: =SUMIFS(T_Bonds[Market value in USD],T_Bonds[Duration],"<1")/(Results!$I$20-SUMIFS(T_Bonds[Market value in USD],T_Bonds[Duration],"")) -> 0.025875735 | I21: 1 | L21: =INDEX(AA:AB,MATCH(M21,AB:AB,0),1) -> Latin America | M21: =LARGE(AB:AB,B4) -> 0.28287195 | S21: Aircraft Production and Defense | T21: =SUMIFS(T_Bonds[Market value in USD],T_Bonds[Sector marker],S21) -> 0 | U21: =T21/Results!$I$20 -> 0 | V21: =T21/Results!$I$11 -> 0 | X21: Uzbekistan | Y21: Europe | Z21: =SUMIFS(T_Bonds[Market value in USD],T_Bonds[Country],X21) -> 0 | AD21: Cia Siderurgica Nacional (CSN) | AE21: =SUMIFS(T_Bonds[Market value in USD],T_Bonds[Issuer],AD21) -> 579900 | AH21: =_xlfn.ISOWEEKNUM(AG21) -> 52 | AI21: =YEAR(AG21) -> 1900 | AJ21: =SUMIFS(#REF!,#REF!,$AG21,T_Bonds[Risk CCY],AJ$1) -> #REF! | AK21: =SUMIFS(#REF!,#REF!,$AG21,T_Bonds[Risk CCY],AK$1) -> #REF! | AL21: =SUMIFS(#REF!,#REF!,$AG21,T_Bonds[Risk CCY],AL$1) -> #REF!
B22: 1-3 years | C22: =SUMIFS(T_Bonds[Market value in USD],T_Bonds[Duration],">=1",T_Bonds[Duration],"<3")/(Results!$I$20-SUMIFS(T_Bonds[Market value in USD],T_Bonds[Duration],"")) -> 0.040062335 | I22: 2 | L22: =INDEX(AA:AB,MATCH(M22,AB:AB,0),1) -> Europe | M22: =LARGE(AB:AB,B5) -> 0.22849201 | S22: Insurance and Reinsurance | T22: =SUMIFS(T_Bonds[Market value in USD],T_Bonds[Sector marker],S22) -> 1854044.5 | U22: =T22/Results!$I$20 -> 0.025845673 | V22: =T22/Results!$I$11 -> 0.033876008 | X22: Chile | Y22: Europe | Z22: =SUMIFS(T_Bonds[Market value in USD],T_Bonds[Country],X22) -> 1298875 | AD22: Sasol | AE22: =SUMIFS(T_Bonds[Market value in USD],T_Bonds[Issuer],AD22) -> 683920 | AH22: =_xlfn.ISOWEEKNUM(AG22) -> 52 | AI22: =YEAR(AG22) -> 1900 | AJ22: =SUMIFS(#REF!,#REF!,$AG22,T_Bonds[Risk CCY],AJ$1) -> #REF! | AK22: =SUMIFS(#REF!,#REF!,$AG22,T_Bonds[Risk CCY],AK$1) -> #REF! | AL22: =SUMIFS(#REF!,#REF!,$AG22,T_Bonds[Risk CCY],AL$1) -> #REF!
B23: 3-5 years | C23: =SUMIFS(T_Bonds[Market value in USD],T_Bonds[Duration],">=3",T_Bonds[Duration],"<5")/(Results!$I$20-SUMIFS(T_Bonds[Market value in USD],T_Bonds[Duration],"")) -> 0.14673202 | I23: 3 | L23: =INDEX(AA:AB,MATCH(M23,AB:AB,0),1) -> Mid.East & Africa | M23: =LARGE(AB:AB,B6) -> 0.16837862 | S23: Motor Vehicle Production | T23: =SUMIFS(T_Bonds[Market value in USD],T_Bonds[Sector marker],S23) -> 580560 | U23: =T23/Results!$I$20 -> 0.0080930983 | V23: =T23/Results!$I$11 -> 0.01060765 | X23: Netherlands | Y23: Latin America | Z23: =SUMIFS(T_Bonds[Market value in USD],T_Bonds[Country],X23) -> 3820223.5 | AD23: Turkey | AE23: =SUMIFS(T_Bonds[Market value in USD],T_Bonds[Issuer],AD23) -> 2732700 | AH23: =_xlfn.ISOWEEKNUM(AG23) -> 52 | AI23: =YEAR(AG23) -> 1900 | AJ23: =SUMIFS(#REF!,#REF!,$AG23,T_Bonds[Risk CCY],AJ$1) -> #REF! | AK23: =SUMIFS(#REF!,#REF!,$AG23,T_Bonds[Risk CCY],AK$1) -> #REF! | AL23: =SUMIFS(#REF!,#REF!,$AG23,T_Bonds[Risk CCY],AL$1) -> #REF!
B24: 5-7 years | C24: =SUMIFS(T_Bonds[Market value in USD],T_Bonds[Duration],">=5",T_Bonds[Duration],"<7")/(Results!$I$20-SUMIFS(T_Bonds[Market value in USD],T_Bonds[Duration],"")) -> 0.26693847 | I24: 4 | L24: =INDEX(AA:AB,MATCH(M24,AB:AB,0),1) -> US+Canada | M24: =LARGE(AB:AB,B7) -> 0.11099745 | S24: Mining: Other | T24: =SUMIFS(T_Bonds[Market value in USD],T_Bonds[Sector marker],S24) -> 408060 | U24: =T24/Results!$I$20 -> 0.005688421 | V24: =T24/Results!$I$11 -> 0.0074558319 | X24: Indonesia | Y24: Europe | Z24: =SUMIFS(T_Bonds[Market value in USD],T_Bonds[Country],X24) -> 408060 | AD24: Colombia | AE24: =SUMIFS(T_Bonds[Market value in USD],T_Bonds[Issuer],AD24) -> 1521060 | AH24: =_xlfn.ISOWEEKNUM(AG24) -> 52 | AI24: =YEAR(AG24) -> 1900 | AJ24: =SUMIFS(#REF!,#REF!,$AG24,T_Bonds[Risk CCY],AJ$1) -> #REF! | AK24: =SUMIFS(#REF!,#REF!,$AG24,T_Bonds[Risk CCY],AK$1) -> #REF! | AL24: =SUMIFS(#REF!,#REF!,$AG24,T_Bonds[Risk CCY],AL$1) -> #REF!
B25: 7-10 years | C25: =SUMIFS(T_Bonds[Market value in USD],T_Bonds[Duration],">=7",T_Bonds[Duration],"<10")/(Results!$I$20-SUMIFS(T_Bonds[Market value in USD],T_Bonds[Duration],"")) -> 0.073003247 | I25: 5 | L25: =INDEX(AA:AB,MATCH(M25,AB:AB,0),1) -> Asia | M25: =LARGE(AB:AB,B8) -> 0.094701127 | S25: Air Transportation | T25: =SUMIFS(T_Bonds[Market value in USD],T_Bonds[Sector marker],S25) -> 691375 | U25: =T25/Results!$I$20 -> 0.0096378769 | V25: =T25/Results!$I$11 -> 0.012632397 | X25: Luxembourg | Y25: Europe | Z25: =SUMIFS(T_Bonds[Market value in USD],T_Bonds[Country],X25) -> 0 | AD25: Panama | AE25: =SUMIFS(T_Bonds[Market value in USD],T_Bonds[Issuer],AD25) -> 822160 | AH25: =_xlfn.ISOWEEKNUM(AG25) -> 52 | AI25: =YEAR(AG25) -> 1900 | AJ25: =SUMIFS(#REF!,#REF!,$AG25,T_Bonds[Risk CCY],AJ$1) -> #REF! | AK25: =SUMIFS(#REF!,#REF!,$AG25,T_Bonds[Risk CCY],AK$1) -> #REF! | AL25: =SUMIFS(#REF!,#REF!,$AG25,T_Bonds[Risk CCY],AL$1) -> #REF!
B26: 10+ years | C26: =SUMIFS(T_Bonds[Market value in USD],T_Bonds[Duration],">=10")/(Results!$I$20-SUMIFS(T_Bonds[Market value in USD],T_Bonds[Duration],"")) -> 0.41478439 | I26: 6 | L26: =INDEX(AA:AB,MATCH(M26,AB:AB,0),1) -> Australia & Pacific | M26: =LARGE(AB:AB,B9) -> 0.069355654 | S26: Communication Services | T26: =SUMIFS(T_Bonds[Market value in USD],T_Bonds[Sector marker],S26) -> 1058100 | U26: =T26/Results!$I$20 -> 0.014750081 | V26: =T26/Results!$I$11 -> 0.01933298 | X26: Austria | Y26: Mid.East & Africa | Z26: =SUMIFS(T_Bonds[Market value in USD],T_Bonds[Country],X26) -> 1764924.6 | AD26: Mexico | AE26: =SUMIFS(T_Bonds[Market value in USD],T_Bonds[Issuer],AD26) -> 4454063.6 | AH26: =_xlfn.ISOWEEKNUM(AG26) -> 52 | AI26: =YEAR(AG26) -> 1900 | AJ26: =SUMIFS(#REF!,#REF!,$AG26,T_Bonds[Risk CCY],AJ$1) -> #REF! | AK26: =SUMIFS(#REF!,#REF!,$AG26,T_Bonds[Risk CCY],AK$1) -> #REF! | AL26: =SUMIFS(#REF!,#REF!,$AG26,T_Bonds[Risk CCY],AL$1) -> #REF!
I27: 7 | L27: =INDEX(AA:AB,MATCH(M27,AB:AB,0),1) -> Africa | M27: =LARGE(AB:AB,B10) -> 0.014201118 | S27: Energy | T27: =SUMIFS(T_Bonds[Market value in USD],T_Bonds[Sector marker],S27) -> 594960 | U27: =T27/Results!$I$20 -> 0.0082938365 | V27: =T27/Results!$I$11 -> 0.010870759 | X27: Romania | Y27: Latin America | Z27: =SUMIFS(T_Bonds[Market value in USD],T_Bonds[Country],X27) -> 1407080 | AD27: Ulker Biskuvi Sanayi | AE27: =SUMIFS(T_Bonds[Market value in USD],T_Bonds[Issuer],AD27) -> 419120 | AH27: =_xlfn.ISOWEEKNUM(AG27) -> 52 | AI27: =YEAR(AG27) -> 1900 | AJ27: =SUMIFS(#REF!,#REF!,$AG27,T_Bonds[Risk CCY],AJ$1) -> #REF! | AK27: =SUMIFS(#REF!,#REF!,$AG27,T_Bonds[Risk CCY],AK$1) -> #REF! | AL27: =SUMIFS(#REF!,#REF!,$AG27,T_Bonds[Risk CCY],AL$1) -> #REF!
I28: 8 | L28: =_xlfn.IFNA(INDEX(AA:AB,MATCH(M28,AB:AB,0),1),"") | M28: =IFERROR(LARGE(AB:AB,B11),"") | S28: Technology | T28: =SUMIFS(T_Bonds[Market value in USD],T_Bonds[Sector marker],S28) -> 794884 | U28: =T28/Results!$I$20 -> 0.011080809 | V28: =T28/Results!$I$11 -> 0.014523652 | X28: Finland | Y28: Europe | Z28: =SUMIFS(T_Bonds[Market value in USD],T_Bonds[Country],X28) -> 0 | AD28: Rakuten Group | AE28: =SUMIFS(T_Bonds[Market value in USD],T_Bonds[Issuer],AD28) -> 668940 | AH28: =_xlfn.ISOWEEKNUM(AG28) -> 52 | AI28: =YEAR(AG28) -> 1900 | AJ28: =SUMIFS(#REF!,#REF!,$AG28,T_Bonds[Risk CCY],AJ$1) -> #REF! | AK28: =SUMIFS(#REF!,#REF!,$AG28,T_Bonds[Risk CCY],AK$1) -> #REF! | AL28: =SUMIFS(#REF!,#REF!,$AG28,T_Bonds[Risk CCY],AL$1) -> #REF!
I29: 9 | L29: =_xlfn.IFNA(INDEX(AA:AB,MATCH(M29,AB:AB,0),1),"") | M29: =IFERROR(LARGE(AB:AB,B12),"") | T29: =SUMIFS(T_Bonds[Market value in USD],T_Bonds[Sector marker],S29) -> 0 | U29: =T29/Results!$I$20 -> 0 | V29: =T29/Results!$I$11 -> 0 | X29: Switzerland | Y29: Africa | Z29: =SUMIFS(T_Bonds[Market value in USD],T_Bonds[Country],X29) -> 1018720 | AD29: Comision Federal de Electricidad | AE29: =SUMIFS(T_Bonds[Market value in USD],T_Bonds[Issuer],AD29) -> 751440 | AH29: =_xlfn.ISOWEEKNUM(AG29) -> 52 | AI29: =YEAR(AG29) -> 1900 | AJ29: =SUMIFS(#REF!,#REF!,$AG29,T_Bonds[Risk CCY],AJ$1) -> #REF! | AK29: =SUMIFS(#REF!,#REF!,$AG29,T_Bonds[Risk CCY],AK$1) -> #REF! | AL29: =SUMIFS(#REF!,#REF!,$AG29,T_Bonds[Risk CCY],AL$1) -> #REF!
I30: 10 | L30: =_xlfn.IFNA(INDEX(AA:AB,MATCH(M30,AB:AB,0),1),"") | M30: =IFERROR(LARGE(AB:AB,B13),"") | T30: =SUMIFS(T_Bonds[Market value in USD],T_Bonds[Sector marker],S30) -> 0 | U30: =T30/Results!$I$20 -> 0 | V30: =T30/Results!$I$11 -> 0 | Z30: =SUMIFS(T_Bonds[Market value in USD],T_Bonds[Country],X30) -> 0 | AD30: OCP SA | AE30: =SUMIFS(T_Bonds[Market value in USD],T_Bonds[Issuer],AD30) -> 1895220 | AH30: =_xlfn.ISOWEEKNUM(AG30) -> 52 | AI30: =YEAR(AG30) -> 1900 | AJ30: =SUMIFS(#REF!,#REF!,$AG30,T_Bonds[Risk CCY],AJ$1) -> #REF! | AK30: =SUMIFS(#REF!,#REF!,$AG30,T_Bonds[Risk CCY],AK$1) -> #REF! | AL30: =SUMIFS(#REF!,#REF!,$AG30,T_Bonds[Risk CCY],AL$1) -> #REF!
T31: =SUMIFS(T_Bonds[Market value in USD],T_Bonds[Sector marker],S31) -> 0 | U31: =T31/Results!$I$20 -> 0 | V31: =T31/Results!$I$11 -> 0 | Z31: =SUMIFS(T_Bonds[Market value in USD],T_Bonds[Country],X31) -> 0 | AD31: BRF | AE31: =SUMIFS(T_Bonds[Market value in USD],T_Bonds[Issuer],AD31) -> 911405 | AH31: =_xlfn.ISOWEEKNUM(AG31) -> 52 | AI31: =YEAR(AG31) -> 1900 | AJ31: =SUMIFS(#REF!,#REF!,$AG31,T_Bonds[Risk CCY],AJ$1) -> #REF! | AK31: =SUMIFS(#REF!,#REF!,$AG31,T_Bonds[Risk CCY],AK$1) -> #REF! | AL31: =SUMIFS(#REF!,#REF!,$AG31,T_Bonds[Risk CCY],AL$1) -> #REF!
T32: =SUMIFS(T_Bonds[Market value in USD],T_Bonds[Sector marker],S32) -> 0 | U32: =T32/Results!$I$20 -> 0 | V32: =T32/Results!$I$11 -> 0 | Z32: =SUMIFS(T_Bonds[Market value in USD],T_Bonds[Country],X32) -> 0 | AD32: Electricite de France (EDF) | AE32: =SUMIFS(T_Bonds[Market value in USD],T_Bonds[Issuer],AD32) -> 1661050.8 | AH32: =_xlfn.ISOWEEKNUM(AG32) -> 52 | AI32: =YEAR(AG32) -> 1900 | AJ32: =SUMIFS(#REF!,#REF!,$AG32,T_Bonds[Risk CCY],AJ$1) -> #REF! | AK32: =SUMIFS(#REF!,#REF!,$AG32,T_Bonds[Risk CCY],AK$1) -> #REF! | AL32: =SUMIFS(#REF!,#REF!,$AG32,T_Bonds[Risk CCY],AL$1) -> #REF!
T33: =SUMIFS(T_Bonds[Market value in USD],T_Bonds[Sector marker],S33) -> 0 | U33: =T33/Results!$I$20 -> 0 | V33: =T33/Results!$I$11 -> 0 | Z33: =SUMIFS(T_Bonds[Market value in USD],T_Bonds[Country],X33) -> 0 | AD33: Enbridge | AE33: =SUMIFS(T_Bonds[Market value in USD],T_Bonds[Issuer],AD33) -> 211480 | AH33: =_xlfn.ISOWEEKNUM(AG33) -> 52 | AI33: =YEAR(AG33) -> 1900 | AJ33: =SUMIFS(#REF!,#REF!,$AG33,T_Bonds[Risk CCY],AJ$1) -> #REF! | AK33: =SUMIFS(#REF!,#REF!,$AG33,T_Bonds[Risk CCY],AK$1) -> #REF! | AL33: =SUMIFS(#REF!,#REF!,$AG33,T_Bonds[Risk CCY],AL$1) -> #REF!
T34: =SUMIFS(T_Bonds[Market value in USD],T_Bonds[Sector marker],S34) -> 0 | U34: =T34/Results!$I$20 -> 0 | V34: =T34/Results!$I$11 -> 0 | Z34: =SUMIFS(T_Bonds[Market value in USD],T_Bonds[Country],X34) -> 0 | AD34: Eletrobras | AE34: =SUMIFS(T_Bonds[Market value in USD],T_Bonds[Issuer],AD34) -> 409040 | AH34: =_xlfn.ISOWEEKNUM(AG34) -> 52 | AI34: =YEAR(AG34) -> 1900 | AJ34: =SUMIFS(#REF!,#REF!,$AG34,T_Bonds[Risk CCY],AJ$1) -> #REF! | AK34: =SUMIFS(#REF!,#REF!,$AG34,T_Bonds[Risk CCY],AK$1) -> #REF! | AL34: =SUMIFS(#REF!,#REF!,$AG34,T_Bonds[Risk CCY],AL$1) -> #REF!
T35: =SUMIFS(T_Bonds[Market value in USD],T_Bonds[Sector marker],S35) -> 0 | U35: =T35/Results!$I$20 -> 0 | V35: =T35/Results!$I$11 -> 0 | Z35: =SUMIFS(T_Bonds[Market value in USD],T_Bonds[Country],X35) -> 0 | AD35: Israel Chemicals | AE35: =SUMIFS(T_Bonds[Market value in USD],T_Bonds[Issuer],AD35) -> 1040500 | AH35: =_xlfn.ISOWEEKNUM(AG35) -> 52 | AI35: =YEAR(AG35) -> 1900 | AJ35: =SUMIFS(#REF!,#REF!,$AG35,T_Bonds[Risk CCY],AJ$1) -> #REF! | AK35: =SUMIFS(#REF!,#REF!,$AG35,T_Bonds[Risk CCY],AK$1) -> #REF! | AL35: =SUMIFS(#REF!,#REF!,$AG35,T_Bonds[Risk CCY],AL$1) -> #REF!
T36: =SUMIFS(T_Bonds[Market value in USD],T_Bonds[Sector marker],S36) -> 0 | U36: =T36/Results!$I$20 -> 0 | V36: =T36/Results!$I$11 -> 0 | Z36: =SUMIFS(T_Bonds[Market value in USD],T_Bonds[Country],X36) -> 0 | AD36: Toronto-Dominion Bank | AE36: =SUMIFS(T_Bonds[Market value in USD],T_Bonds[Issuer],AD36) -> 0 | AH36: =_xlfn.ISOWEEKNUM(AG36) -> 52 | AI36: =YEAR(AG36) -> 1900 | AJ36: =SUMIFS(#REF!,#REF!,$AG36,T_Bonds[Risk CCY],AJ$1) -> #REF! | AK36: =SUMIFS(#REF!,#REF!,$AG36,T_Bonds[Risk CCY],AK$1) -> #REF! | AL36: =SUMIFS(#REF!,#REF!,$AG36,T_Bonds[Risk CCY],AL$1) -> #REF!
T37: =SUMIFS(T_Bonds[Market value in USD],T_Bonds[Sector marker],S37) -> 0 | U37: =T37/Results!$I$20 -> 0 | V37: =T37/Results!$I$11 -> 0 | Z37: =SUMIFS(T_Bonds[Market value in USD],T_Bonds[Country],X37) -> 0 | AD37: Navoi Mining | AE37: =SUMIFS(T_Bonds[Market value in USD],T_Bonds[Issuer],AD37) -> 0 | AH37: =_xlfn.ISOWEEKNUM(AG37) -> 52 | AI37: =YEAR(AG37) -> 1900 | AJ37: =SUMIFS(#REF!,#REF!,$AG37,T_Bonds[Risk CCY],AJ$1) -> #REF! | AK37: =SUMIFS(#REF!,#REF!,$AG37,T_Bonds[Risk CCY],AK$1) -> #REF! | AL37: =SUMIFS(#REF!,#REF!,$AG37,T_Bonds[Risk CCY],AL$1) -> #REF!
T38: =SUMIFS(T_Bonds[Market value in USD],T_Bonds[Sector marker],S38) -> 0 | U38: =T38/Results!$I$20 -> 0 | V38: =T38/Results!$I$11 -> 0 | Z38: =SUMIFS(T_Bonds[Market value in USD],T_Bonds[Country],X38) -> 0 | AD38: Softbank | AE38: =SUMIFS(T_Bonds[Market value in USD],T_Bonds[Issuer],AD38) -> 1009200 | AH38: =_xlfn.ISOWEEKNUM(AG38) -> 52 | AI38: =YEAR(AG38) -> 1900 | AJ38: =SUMIFS(#REF!,#REF!,$AG38,T_Bonds[Risk CCY],AJ$1) -> #REF! | AK38: =SUMIFS(#REF!,#REF!,$AG38,T_Bonds[Risk CCY],AK$1) -> #REF! | AL38: =SUMIFS(#REF!,#REF!,$AG38,T_Bonds[Risk CCY],AL$1) -> #REF!
T39: =SUMIFS(T_Bonds[Market value in USD],T_Bonds[Sector marker],S39) -> 0 | U39: =T39/Results!$I$20 -> 0 | V39: =T39/Results!$I$11 -> 0 | Z39: =SUMIFS(T_Bonds[Market value in USD],T_Bonds[Country],X39) -> 0 | AD39: Adani Ports and Special Economic Zone | AE39: =SUMIFS(T_Bonds[Market value in USD],T_Bonds[Issuer],AD39) -> 691200 | AH39: =_xlfn.ISOWEEKNUM(AG39) -> 52 | AI39: =YEAR(AG39) -> 1900 | AJ39: =SUMIFS(#REF!,#REF!,$AG39,T_Bonds[Risk CCY],AJ$1) -> #REF! | AK39: =SUMIFS(#REF!,#REF!,$AG39,T_Bonds[Risk CCY],AK$1) -> #REF! | AL39: =SUMIFS(#REF!,#REF!,$AG39,T_Bonds[Risk CCY],AL$1) -> #REF!
T40: =SUMIFS(T_Bonds[Market value in USD],T_Bonds[Sector marker],S40) -> 0 | U40: =T40/Results!$I$20 -> 0 | V40: =T40/Results!$I$11 -> 0 | Z40: =SUMIFS(T_Bonds[Market value in USD],T_Bonds[Country],X40) -> 0 | AD40: Naspers | AE40: =SUMIFS(T_Bonds[Market value in USD],T_Bonds[Issuer],AD40) -> 901260 | AH40: =_xlfn.ISOWEEKNUM(AG40) -> 52 | AI40: =YEAR(AG40) -> 1900 | AJ40: =SUMIFS(#REF!,#REF!,$AG40,T_Bonds[Risk CCY],AJ$1) -> #REF! | AK40: =SUMIFS(#REF!,#REF!,$AG40,T_Bonds[Risk CCY],AK$1) -> #REF! | AL40: =SUMIFS(#REF!,#REF!,$AG40,T_Bonds[Risk CCY],AL$1) -> #REF!
T41: =SUMIFS(T_Bonds[Market value in USD],T_Bonds[Sector marker],S41) -> 0 | U41: =T41/Results!$I$20 -> 0 | V41: =T41/Results!$I$11 -> 0 | Z41: =SUMIFS(T_Bonds[Market value in USD],T_Bonds[Country],X41) -> 0 | AD41: Codelco | AE41: =SUMIFS(T_Bonds[Market value in USD],T_Bonds[Issuer],AD41) -> 607500 | AH41: =_xlfn.ISOWEEKNUM(AG41) -> 52 | AI41: =YEAR(AG41) -> 1900 | AJ41: =SUMIFS(#REF!,#REF!,$AG41,T_Bonds[Risk CCY],AJ$1) -> #REF! | AK41: =SUMIFS(#REF!,#REF!,$AG41,T_Bonds[Risk CCY],AK$1) -> #REF! | AL41: =SUMIFS(#REF!,#REF!,$AG41,T_Bonds[Risk CCY],AL$1) -> #REF!
T42: =SUMIFS(T_Bonds[Market value in USD],T_Bonds[Sector marker],S42) -> 0 | U42: =T42/Results!$I$20 -> 0 | V42: =T42/Results!$I$11 -> 0 | Z42: =SUMIFS(T_Bonds[Market value in USD],T_Bonds[Country],X42) -> 0 | AD42: Boeing | AE42: =SUMIFS(T_Bonds[Market value in USD],T_Bonds[Issuer],AD42) -> 0 | AH42: =_xlfn.ISOWEEKNUM(AG42) -> 52 | AI42: =YEAR(AG42) -> 1900 | AJ42: =SUMIFS(#REF!,#REF!,$AG42,T_Bonds[Risk CCY],AJ$1) -> #REF! | AK42: =SUMIFS(#REF!,#REF!,$AG42,T_Bonds[Risk CCY],AK$1) -> #REF! | AL42: =SUMIFS(#REF!,#REF!,$AG42,T_Bonds[Risk CCY],AL$1) -> #REF!
... T56: =SUMIFS(T_Bonds[Market value in USD],T_Bonds[Sector marker],S56) -> 0 | U56: =T56/Results!$I$20 -> 0 | V56: =T56/Results!$I$11 -> 0 | Z56: =SUMIFS(T_Bonds[Market value in USD],T_Bonds[Country],X56) -> 0 | AD56: SBL Holdings | AE56: =SUMIFS(T_Bonds[Market value in USD],T_Bonds[Issuer],AD56) -> 0 | AH56: =_xlfn.ISOWEEKNUM(AG56) -> 52 | AI56: =YEAR(AG56) -> 1900 | AJ56: =SUMIFS(#REF!,#REF!,$AG56,T_Bonds[Risk CCY],AJ$1) -> #REF! | AK56: =SUMIFS(#REF!,#REF!,$AG56,T_Bonds[Risk CCY],AK$1) -> #REF! | AL56: =SUMIFS(#REF!,#REF!,$AG56,T_Bonds[Risk CCY],AL$1) -> #REF!
T57: =SUMIFS(T_Bonds[Market value in USD],T_Bonds[Sector marker],S57) -> 0 | U57: =T57/Results!$I$20 -> 0 | V57: =T57/Results!$I$11 -> 0 | AD57: Latam Airlines | AE57: =SUMIFS(T_Bonds[Market value in USD],T_Bonds[Issuer],AD57) -> 691375 | AH57: =_xlfn.ISOWEEKNUM(AG57) -> 52 | AI57: =YEAR(AG57) -> 1900 | AJ57: =SUMIFS(#REF!,#REF!,$AG57,T_Bonds[Risk CCY],AJ$1) -> #REF! | AK57: =SUMIFS(#REF!,#REF!,$AG57,T_Bonds[Risk CCY],AK$1) -> #REF! | AL57: =SUMIFS(#REF!,#REF!,$AG57,T_Bonds[Risk CCY],AL$1) -> #REF!
T58: =SUMIFS(T_Bonds[Market value in USD],T_Bonds[Sector marker],S58) -> 0 | U58: =T58/Results!$I$20 -> 0 | V58: =T58/Results!$I$11 -> 0 | AD58: Turkcell Iletisim | AE58: =SUMIFS(T_Bonds[Market value in USD],T_Bonds[Issuer],AD58) -> 1058100 | AH58: =_xlfn.ISOWEEKNUM(AG58) -> 52 | AI58: =YEAR(AG58) -> 1900 | AJ58: =SUMIFS(#REF!,#REF!,$AG58,T_Bonds[Risk CCY],AJ$1) -> #REF! | AK58: =SUMIFS(#REF!,#REF!,$AG58,T_Bonds[Risk CCY],AK$1) -> #REF! | AL58: =SUMIFS(#REF!,#REF!,$AG58,T_Bonds[Risk CCY],AL$1) -> #REF!
T59: =SUMIFS(T_Bonds[Market value in USD],T_Bonds[Sector marker],S59) -> 0 | U59: =T59/Results!$I$20 -> 0 | V59: =T59/Results!$I$11 -> 0 | AD59: UBS Group | AE59: =SUMIFS(T_Bonds[Market value in USD],T_Bonds[Issuer],AD59) -> 1018720 | AH59: =_xlfn.ISOWEEKNUM(AG59) -> 52 | AI59: =YEAR(AG59) -> 1900 | AJ59: =SUMIFS(#REF!,#REF!,$AG59,T_Bonds[Risk CCY],AJ$1) -> #REF! | AK59: =SUMIFS(#REF!,#REF!,$AG59,T_Bonds[Risk CCY],AK$1) -> #REF! | AL59: =SUMIFS(#REF!,#REF!,$AG59,T_Bonds[Risk CCY],AL$1) -> #REF!
T60: =SUMIFS(T_Bonds[Market value in USD],T_Bonds[Sector marker],S60) -> 0 | U60: =T60/Results!$I$20 -> 0 | V60: =T60/Results!$I$11 -> 0 | AD60: Barclays | AE60: =SUMIFS(T_Bonds[Market value in USD],T_Bonds[Issuer],AD60) -> 1223064.1 | AH60: =_xlfn.ISOWEEKNUM(AG60) -> 52 | AI60: =YEAR(AG60) -> 1900 | AJ60: =SUMIFS(#REF!,#REF!,$AG60,T_Bonds[Risk CCY],AJ$1) -> #REF! | AK60: =SUMIFS(#REF!,#REF!,$AG60,T_Bonds[Risk CCY],AK$1) -> #REF! | AL60: =SUMIFS(#REF!,#REF!,$AG60,T_Bonds[Risk CCY],AL$1) -> #REF!
T61: =SUMIFS(T_Bonds[Market value in USD],T_Bonds[Sector marker],S61) -> 0 | U61: =T61/Results!$I$20 -> 0 | V61: =T61/Results!$I$11 -> 0 | AD61: IFC | AE61: =SUMIFS(T_Bonds[Market value in USD],T_Bonds[Issuer],AD61) -> 378240 | AH61: =_xlfn.ISOWEEKNUM(AG61) -> 52 | AI61: =YEAR(AG61) -> 1900 | AJ61: =SUMIFS(#REF!,#REF!,$AG61,T_Bonds[Risk CCY],AJ$1) -> #REF! | AK61: =SUMIFS(#REF!,#REF!,$AG61,T_Bonds[Risk CCY],AK$1) -> #REF! | AL61: =SUMIFS(#REF!,#REF!,$AG61,T_Bonds[Risk CCY],AL$1) -> #REF!
T62: =SUMIFS(T_Bonds[Market value in USD],T_Bonds[Sector marker],S62) -> 0 | U62: =T62/Results!$I$20 -> 0 | V62: =T62/Results!$I$11 -> 0 | AD62: South Africa | AE62: =SUMIFS(T_Bonds[Market value in USD],T_Bonds[Issuer],AD62) -> 636420 | AH62: =_xlfn.ISOWEEKNUM(AG62) -> 52 | AI62: =YEAR(AG62) -> 1900 | AJ62: =SUMIFS(#REF!,#REF!,$AG62,T_Bonds[Risk CCY],AJ$1) -> #REF! | AK62: =SUMIFS(#REF!,#REF!,$AG62,T_Bonds[Risk CCY],AK$1) -> #REF! | AL62: =SUMIFS(#REF!,#REF!,$AG62,T_Bonds[Risk CCY],AL$1) -> #REF!
T63: =SUMIFS(T_Bonds[Market value in USD],T_Bonds[Sector marker],S63) -> 0 | U63: =T63/Results!$I$20 -> 0 | V63: =T63/Results!$I$11 -> 0 | AD63: IBRD | AE63: =SUMIFS(T_Bonds[Market value in USD],T_Bonds[Issuer],AD63) -> 1839475.2 | AH63: =_xlfn.ISOWEEKNUM(AG63) -> 52 | AI63: =YEAR(AG63) -> 1900 | AJ63: =SUMIFS(#REF!,#REF!,$AG63,T_Bonds[Risk CCY],AJ$1) -> #REF! | AK63: =SUMIFS(#REF!,#REF!,$AG63,T_Bonds[Risk CCY],AK$1) -> #REF! | AL63: =SUMIFS(#REF!,#REF!,$AG63,T_Bonds[Risk CCY],AL$1) -> #REF!
T64: =SUMIFS(T_Bonds[Market value in USD],T_Bonds[Sector marker],S64) -> 0 | U64: =T64/Results!$I$20 -> 0 | V64: =T64/Results!$I$11 -> 0 | AD64: Aviva | AE64: =SUMIFS(T_Bonds[Market value in USD],T_Bonds[Issuer],AD64) -> 1147489.2 | AH64: =_xlfn.ISOWEEKNUM(AG64) -> 52 | AI64: =YEAR(AG64) -> 1900 | AJ64: =SUMIFS(#REF!,#REF!,$AG64,T_Bonds[Risk CCY],AJ$1) -> #REF! | AK64: =SUMIFS(#REF!,#REF!,$AG64,T_Bonds[Risk CCY],AK$1) -> #REF! | AL64: =SUMIFS(#REF!,#REF!,$AG64,T_Bonds[Risk CCY],AL$1) -> #REF!
T65: =SUMIFS(T_Bonds[Market value in USD],T_Bonds[Sector marker],S65) -> 0 | U65: =T65/Results!$I$20 -> 0 | V65: =T65/Results!$I$11 -> 0 | AD65: Societe Generale | AE65: =SUMIFS(T_Bonds[Market value in USD],T_Bonds[Issuer],AD65) -> 440440 | AH65: =_xlfn.ISOWEEKNUM(AG65) -> 52 | AI65: =YEAR(AG65) -> 1900 | AJ65: =SUMIFS(#REF!,#REF!,$AG65,T_Bonds[Risk CCY],AJ$1) -> #REF! | AK65: =SUMIFS(#REF!,#REF!,$AG65,T_Bonds[Risk CCY],AK$1) -> #REF! | AL65: =SUMIFS(#REF!,#REF!,$AG65,T_Bonds[Risk CCY],AL$1) -> #REF!
T66: =SUMIFS(T_Bonds[Market value in USD],T_Bonds[Sector marker],S66) -> 0 | U66: =T66/Results!$I$20 -> 0 | V66: =T66/Results!$I$11 -> 0 | AD66: HSBC Holdings plc | AE66: =SUMIFS(T_Bonds[Market value in USD],T_Bonds[Issuer],AD66) -> 1246640 | AH66: =_xlfn.ISOWEEKNUM(AG66) -> 52 | AI66: =YEAR(AG66) -> 1900 | AJ66: =SUMIFS(#REF!,#REF!,$AG66,T_Bonds[Risk CCY],AJ$1) -> #REF! | AK66: =SUMIFS(#REF!,#REF!,$AG66,T_Bonds[Risk CCY],AK$1) -> #REF! | AL66: =SUMIFS(#REF!,#REF!,$AG66,T_Bonds[Risk CCY],AL$1) -> #REF!
T67: =SUMIFS(T_Bonds[Market value in USD],T_Bonds[Sector marker],S67) -> 0 | U67: =T67/Results!$I$20 -> 0 | V67: =T67/Results!$I$11 -> 0 | AD67: Softbank Group | AE67: =SUMIFS(T_Bonds[Market value in USD],T_Bonds[Issuer],AD67) -> 927800 | AH67: =_xlfn.ISOWEEKNUM(AG67) -> 52 | AI67: =YEAR(AG67) -> 1900 | AJ67: =SUMIFS(#REF!,#REF!,$AG67,T_Bonds[Risk CCY],AJ$1) -> #REF! | AK67: =SUMIFS(#REF!,#REF!,$AG67,T_Bonds[Risk CCY],AK$1) -> #REF! | AL67: =SUMIFS(#REF!,#REF!,$AG67,T_Bonds[Risk CCY],AL$1) -> #REF!
T68: =SUMIFS(T_Bonds[Market value in USD],T_Bonds[Sector marker],S68) -> 0 | U68: =T68/Results!$I$20 -> 0 | V68: =T68/Results!$I$11 -> 0 | AD68: EBRD | AE68: =SUMIFS(T_Bonds[Market value in USD],T_Bonds[Issuer],AD68) -> 702306.22 | AH68: =_xlfn.ISOWEEKNUM(AG68) -> 52 | AI68: =YEAR(AG68) -> 1900 | AJ68: =SUMIFS(#REF!,#REF!,$AG68,T_Bonds[Risk CCY],AJ$1) -> #REF! | AK68: =SUMIFS(#REF!,#REF!,$AG68,T_Bonds[Risk CCY],AK$1) -> #REF! | AL68: =SUMIFS(#REF!,#REF!,$AG68,T_Bonds[Risk CCY],AL$1) -> #REF!
T69: =SUMIFS(T_Bonds[Market value in USD],T_Bonds[Sector marker],S69) -> 0 | U69: =T69/Results!$I$20 -> 0 | V69: =T69/Results!$I$11 -> 0 | AD69: Vedanta Resources Finance II Plc | AE69: =SUMIFS(T_Bonds[Market value in USD],T_Bonds[Issuer],AD69) -> 1041500 | AH69: =_xlfn.ISOWEEKNUM(AG69) -> 52 | AI69: =YEAR(AG69) -> 1900 | AJ69: =SUMIFS(#REF!,#REF!,$AG69,T_Bonds[Risk CCY],AJ$1) -> #REF! | AK69: =SUMIFS(#REF!,#REF!,$AG69,T_Bonds[Risk CCY],AK$1) -> #REF! | AL69: =SUMIFS(#REF!,#REF!,$AG69,T_Bonds[Risk CCY],AL$1) -> #REF!
T70: =SUMIFS(T_Bonds[Market value in USD],T_Bonds[Sector marker],S70) -> 0 | U70: =T70/Results!$I$20 -> 0 | V70: =T70/Results!$I$11 -> 0 | AD70: 0 | AE70: =SUMIFS(T_Bonds[Market value in USD],T_Bonds[Issuer],AD70) -> 0 | AH70: =_xlfn.ISOWEEKNUM(AG70) -> 52 | AI70: =YEAR(AG70) -> 1900 | AJ70: =SUMIFS(#REF!,#REF!,$AG70,T_Bonds[Risk CCY],AJ$1) -> #REF! | AK70: =SUMIFS(#REF!,#REF!,$AG70,T_Bonds[Risk CCY],AK$1) -> #REF! | AL70: =SUMIFS(#REF!,#REF!,$AG70,T_Bonds[Risk CCY],AL$1) -> #REF!
T71: =SUMIFS(T_Bonds[Market value in USD],T_Bonds[Sector marker],S71) -> 0 | U71: =T71/Results!$I$20 -> 0 | V71: =T71/Results!$I$11 -> 0 | AD71: NATWEST GROUP | AE71: =SUMIFS(T_Bonds[Market value in USD],T_Bonds[Issuer],AD71) -> 561381.67 | AH71: =_xlfn.ISOWEEKNUM(AG71) -> 52 | AI71: =YEAR(AG71) -> 1900 | AJ71: =SUMIFS(#REF!,#REF!,$AG71,T_Bonds[Risk CCY],AJ$1) -> #REF! | AK71: =SUMIFS(#REF!,#REF!,$AG71,T_Bonds[Risk CCY],AK$1) -> #REF! | AL71: =SUMIFS(#REF!,#REF!,$AG71,T_Bonds[Risk CCY],AL$1) -> #REF!
T72: =SUMIFS(T_Bonds[Market value in USD],T_Bonds[Sector marker],S72) -> 0 | U72: =T72/Results!$I$20 -> 0 | V72: =T72/Results!$I$11 -> 0 | AE72: =SUMIFS(T_Bonds[Market value in USD],T_Bonds[Issuer],AD72) -> 0 | AH72: =_xlfn.ISOWEEKNUM(AG72) -> 52 | AI72: =YEAR(AG72) -> 1900 | AJ72: =SUMIFS(#REF!,#REF!,$AG72,T_Bonds[Risk CCY],AJ$1) -> #REF! | AK72: =SUMIFS(#REF!,#REF!,$AG72,T_Bonds[Risk CCY],AK$1) -> #REF! | AL72: =SUMIFS(#REF!,#REF!,$AG72,T_Bonds[Risk CCY],AL$1) -> #REF!
AE73: =SUMIFS(T_Bonds[Market value in USD],T_Bonds[Issuer],AD73) -> 0 | AH73: =_xlfn.ISOWEEKNUM(AG73) -> 52 | AI73: =YEAR(AG73) -> 1900 | AJ73: =SUMIFS(#REF!,#REF!,$AG73,T_Bonds[Risk CCY],AJ$1) -> #REF! | AK73: =SUMIFS(#REF!,#REF!,$AG73,T_Bonds[Risk CCY],AK$1) -> #REF! | AL73: =SUMIFS(#REF!,#REF!,$AG73,T_Bonds[Risk CCY],AL$1) -> #REF!
AE74: =SUMIFS(T_Bonds[Market value in USD],T_Bonds[Issuer],AD74) -> 0 | AH74: =_xlfn.ISOWEEKNUM(AG74) -> 52 | AI74: =YEAR(AG74) -> 1900 | AJ74: =SUMIFS(#REF!,#REF!,$AG74,T_Bonds[Risk CCY],AJ$1) -> #REF! | AK74: =SUMIFS(#REF!,#REF!,$AG74,T_Bonds[Risk CCY],AK$1) -> #REF! | AL74: =SUMIFS(#REF!,#REF!,$AG74,T_Bonds[Risk CCY],AL$1) -> #REF!
AE75: =SUMIFS(T_Bonds[Market value in USD],T_Bonds[Issuer],AD75) -> 0 | AH75: =_xlfn.ISOWEEKNUM(AG75) -> 52 | AI75: =YEAR(AG75) -> 1900 | AJ75: =SUMIFS(#REF!,#REF!,$AG75,T_Bonds[Risk CCY],AJ$1) -> #REF! | AK75: =SUMIFS(#REF!,#REF!,$AG75,T_Bonds[Risk CCY],AK$1) -> #REF! | AL75: =SUMIFS(#REF!,#REF!,$AG75,T_Bonds[Risk CCY],AL$1) -> #REF!
AE76: =SUMIFS(T_Bonds[Market value in USD],T_Bonds[Issuer],AD76) -> 0 | AH76: =_xlfn.ISOWEEKNUM(AG76) -> 52 | AI76: =YEAR(AG76) -> 1900 | AJ76: =SUMIFS(#REF!,#REF!,$AG76,T_Bonds[Risk CCY],AJ$1) -> #REF! | AK76: =SUMIFS(#REF!,#REF!,$AG76,T_Bonds[Risk CCY],AK$1) -> #REF! | AL76: =SUMIFS(#REF!,#REF!,$AG76,T_Bonds[Risk CCY],AL$1) -> #REF!
AE77: =SUMIFS(T_Bonds[Market value in USD],T_Bonds[Issuer],AD77) -> 0 | AH77: =_xlfn.ISOWEEKNUM(AG77) -> 52 | AI77: =YEAR(AG77) -> 1900 | AJ77: =SUMIFS(#REF!,#REF!,$AG77,T_Bonds[Risk CCY],AJ$1) -> #REF! | AK77: =SUMIFS(#REF!,#REF!,$AG77,T_Bonds[Risk CCY],AK$1) -> #REF! | AL77: =SUMIFS(#REF!,#REF!,$AG77,T_Bonds[Risk CCY],AL$1) -> #REF!
AE78: =SUMIFS(T_Bonds[Market value in USD],T_Bonds[Issuer],AD78) -> 0 | AH78: =_xlfn.ISOWEEKNUM(AG78) -> 52 | AI78: =YEAR(AG78) -> 1900 | AJ78: =SUMIFS(#REF!,#REF!,$AG78,T_Bonds[Risk CCY],AJ$1) -> #REF! | AK78: =SUMIFS(#REF!,#REF!,$AG78,T_Bonds[Risk CCY],AK$1) -> #REF! | AL78: =SUMIFS(#REF!,#REF!,$AG78,T_Bonds[Risk CCY],AL$1) -> #REF!
AE79: =SUMIFS(T_Bonds[Market value in USD],T_Bonds[Issuer],AD79) -> 0 | AH79: =_xlfn.ISOWEEKNUM(AG79) -> 52 | AI79: =YEAR(AG79) -> 1900 | AJ79: =SUMIFS(#REF!,#REF!,$AG79,T_Bonds[Risk CCY],AJ$1) -> #REF! | AK79: =SUMIFS(#REF!,#REF!,$AG79,T_Bonds[Risk CCY],AK$1) -> #REF! | AL79: =SUMIFS(#REF!,#REF!,$AG79,T_Bonds[Risk CCY],AL$1) -> #REF!
AE80: =SUMIFS(T_Bonds[Market value in USD],T_Bonds[Issuer],AD80) -> 0 | AH80: =_xlfn.ISOWEEKNUM(AG80) -> 52 | AI80: =YEAR(AG80) -> 1900 | AJ80: =SUMIFS(#REF!,#REF!,$AG80,T_Bonds[Risk CCY],AJ$1) -> #REF! | AK80: =SUMIFS(#REF!,#REF!,$AG80,T_Bonds[Risk CCY],AK$1) -> #REF! | AL80: =SUMIFS(#REF!,#REF!,$AG80,T_Bonds[Risk CCY],AL$1) -> #REF!
AE81: =SUMIFS(T_Bonds[Market value in USD],T_Bonds[Issuer],AD81) -> 0 | AH81: =_xlfn.ISOWEEKNUM(AG81) -> 52 | AI81: =YEAR(AG81) -> 1900 | AJ81: =SUMIFS(#REF!,#REF!,$AG81,T_Bonds[Risk CCY],AJ$1) -> #REF! | AK81: =SUMIFS(#REF!,#REF!,$AG81,T_Bonds[Risk CCY],AK$1) -> #REF! | AL81: =SUMIFS(#REF!,#REF!,$AG81,T_Bonds[Risk CCY],AL$1) -> #REF!
AE82: =SUMIFS(T_Bonds[Market value in USD],T_Bonds[Issuer],AD82) -> 0 | AH82: =_xlfn.ISOWEEKNUM(AG82) -> 52 | AI82: =YEAR(AG82) -> 1900 | AJ82: =SUMIFS(#REF!,#REF!,$AG82,T_Bonds[Risk CCY],AJ$1) -> #REF! | AK82: =SUMIFS(#REF!,#REF!,$AG82,T_Bonds[Risk CCY],AK$1) -> #REF! | AL82: =SUMIFS(#REF!,#REF!,$AG82,T_Bonds[Risk CCY],AL$1) -> #REF!
AE83: =SUMIFS(T_Bonds[Market value in USD],T_Bonds[Issuer],AD83) -> 0 | AH83: =_xlfn.ISOWEEKNUM(AG83) -> 52 | AI83: =YEAR(AG83) -> 1900 | AJ83: =SUMIFS(#REF!,#REF!,$AG83,T_Bonds[Risk CCY],AJ$1) -> #REF! | AK83: =SUMIFS(#REF!,#REF!,$AG83,T_Bonds[Risk CCY],AK$1) -> #REF! | AL83: =SUMIFS(#REF!,#REF!,$AG83,T_Bonds[Risk CCY],AL$1) -> #REF!
AE84: =SUMIFS(T_Bonds[Market value in USD],T_Bonds[Issuer],AD84) -> 0 | AH84: =_xlfn.ISOWEEKNUM(AG84) -> 52 | AI84: =YEAR(AG84) -> 1900 | AJ84: =SUMIFS(#REF!,#REF!,$AG84,T_Bonds[Risk CCY],AJ$1) -> #REF! | AK84: =SUMIFS(#REF!,#REF!,$AG84,T_Bonds[Risk CCY],AK$1) -> #REF! | AL84: =SUMIFS(#REF!,#REF!,$AG84,T_Bonds[Risk CCY],AL$1) -> #REF!
... AE151: =SUMIFS(T_Bonds[Market value in USD],T_Bonds[Issuer],AD151) -> 0 | AH151: =_xlfn.ISOWEEKNUM(AG151) -> 52 | AI151: =YEAR(AG151) -> 1900 | AJ151: =SUMIFS(#REF!,#REF!,$AG151,T_Bonds[Risk CCY],AJ$1) -> #REF! | AK151: =SUMIFS(#REF!,#REF!,$AG151,T_Bonds[Risk CCY],AK$1) -> #REF! | AL151: =SUMIFS(#REF!,#REF!,$AG151,T_Bonds[Risk CCY],AL$1) -> #REF!
AE152: =SUMIFS(T_Bonds[Market value in USD],T_Bonds[Issuer],AD152) -> 0
AE153: =SUMIFS(T_Bonds[Market value in USD],T_Bonds[Issuer],AD153) -> 0
AE154: =SUMIFS(T_Bonds[Market value in USD],T_Bonds[Issuer],AD154) -> 0
AE155: =SUMIFS(T_Bonds[Market value in USD],T_Bonds[Issuer],AD155) -> 0

Sheet CF USD
A1: Start of Period | B1: 45658 | C1: =DATE(YEAR($B$1),MONTH($B$1),DAY(1)) -> 45658 | D1: =EDATE(C1,1) -> 45689 | E1: =EDATE(D1,1) -> 45717 | F1: =EDATE(E1,1) -> 45748 | G1: =EDATE(F1,1) -> 45778 | H1: =EDATE(G1,1) -> 45809 | I1: =EDATE(H1,1) -> 45839 | J1: =EDATE(I1,1) -> 45870 | K1: =EDATE(J1,1) -> 45901 | ... Z1: =EDATE(Y1,1) -> 46357
A2: End of Period | C2: =EOMONTH(C1,0) -> 45688 | D2: =EOMONTH(D1,0) -> 45716 | E2: =EOMONTH(E1,0) -> 45747 | F2: =EOMONTH(F1,0) -> 45777 | G2: =EOMONTH(G1,0) -> 45808 | H2: =EOMONTH(H1,0) -> 45838 | I2: =EOMONTH(I1,0) -> 45869 | J2: =EOMONTH(J1,0) -> 45900 | ... Z2: =EOMONTH(Z1,0) -> 46387
A7: Calculation in USD
A8: Off
A41: Total Income, USD
B42: Vontobel income | C42: =SUM(C49,C56,C63,C70) -> 371299.26 | D42: =SUM(D49,D56,D63,D70) -> 9794357.5 | E42: =SUM(E49,E56,E63,E70) -> 851766.55 | F42: =SUM(F49,F56,F63,F70) -> 403327.83 | G42: =SUM(G49,G56,G63,G70) -> 225415.49 | H42: =SUM(H49,H56,H63,H70) -> 371868.05 | I42: =SUM(I49,I56,I63,I70) -> 371299.26 | J42: =SUM(J49,J56,J63,J70) -> 273283.49 | ... Z42: =SUM(Z49,Z56,Z63,Z70) -> 504682.37 | AB42: =SUM(O42:Z42) -> 15223700
B43: UBS income | C43: =SUM(C50,C57,C64,C71) -> 137453.84 | D43: =SUM(D50,D57,D64,D71) -> 121517.18 | E43: =SUM(E50,E57,E64,E71) -> 118252.58 | F43: =SUM(F50,F57,F64,F71) -> 115453.84 | G43: =SUM(G50,G57,G64,G71) -> 115453.84 | H43: =SUM(H50,H57,H64,H71) -> 118252.58 | I43: =SUM(I50,I57,I64,I71) -> 137453.84 | J43: =SUM(J50,J57,J64,J71) -> 115453.84 | ... Z43: =SUM(Z50,Z57,Z64,Z71) -> 118252.58 | AB43: =SUM(O43:Z43) -> 1446704.4
B44: JPM | C44: =SUM(C51,C58,C65,C72) -> 104052.92 | D44: =SUM(D51,D58,D65,D72) -> 26023.944 | E44: =SUM(E51,E58,E65,E72) -> 86731.276 | F44: =SUM(F51,F58,F65,F72) -> 46293.677 | G44: =SUM(G51,G58,G65,G72) -> 64148.944 | H44: =SUM(H51,H58,H65,H72) -> 83843.272 | I44: =SUM(I51,I58,I65,I72) -> 46293.677 | J44: =SUM(J51,J58,J65,J72) -> 26023.944 | ... Z44: =SUM(Z51,Z58,Z65,Z72) -> 83843.272 | AB44: =SUM(O44:Z44) -> 764428.83
B45: Personal | C45: =SUM(C52,C59,C66,C73) -> 82829.58 | D45: =SUM(D52,D59,D66,D73) -> 38853.585 | E45: =SUM(E52,E59,E66,E73) -> 61773.958 | F45: =SUM(F52,F59,F66,F73) -> 72445.178 | G45: =SUM(G52,G59,G66,G73) -> 52421.585 | H45: =SUM(H52,H59,H66,H73) -> 56078.043 | I45: =SUM(I52,I59,I66,I73) -> 54222.913 | J45: =SUM(J52,J59,J66,J73) -> 38853.585 | ... Z45: =SUM(Z52,Z59,Z66,Z73) -> 86974.283 | AB45: =SUM(O45:Z45) -> 752565.43
A48: Bonds coupons
B49: Vontobel | C49: =SUMIFS(Bonds!AT:AT,Bonds!$B:$B,'CF USD'!$B49) -> 318192.25 | D49: =SUMIFS(Bonds!AU:AU,Bonds!$B:$B,'CF USD'!$B49) -> 9778587 | E49: =SUMIFS(Bonds!AV:AV,Bonds!$B:$B,'CF USD'!$B49) -> 759449 | F49: =SUMIFS(Bonds!AW:AW,Bonds!$B:$B,'CF USD'!$B49) -> 357587.5 | G49: =SUMIFS(Bonds!AX:AX,Bonds!$B:$B,'CF USD'!$B49) -> 205550 | H49: =SUMIFS(Bonds!AY:AY,Bonds!$B:$B,'CF USD'!$B49) -> 261100 | I49: =SUMIFS(Bonds!AZ:AZ,Bonds!$B:$B,'CF USD'!$B49) -> 318192.25 | J49: =SUMIFS(Bonds!BA:BA,Bonds!$B:$B,'CF USD'!$B49) -> 258587 | K49: =SUMIFS(Bonds!BB:BB,Bonds!$B:$B,'CF USD'!$B49) -> 523199 | L49: =SUMIFS(Bonds!BC:BC,Bonds!$B:$B,'CF USD'!$B49) -> 1102587.5 | M49: =SUMIFS(Bonds!BD:BD,Bonds!$B:$B,'CF USD'!$B49) -> 205550 | N49: =SUMIFS(Bonds!BE:BE,Bonds!$B:$B,'CF USD'!$B49) -> 261100 | O49: =SUMIFS(Bonds!AT:AT,Bonds!$B:$B,'CF USD'!$B49) -> 318192.25 | P49: =SUMIFS(Bonds!AU:AU,Bonds!$B:$B,'CF USD'!$B49) -> 9778587 | Q49: =SUMIFS(Bonds!AV:AV,Bonds!$B:$B,'CF USD'!$B49) -> 759449 | R49: =SUMIFS(Bonds!AW:AW,Bonds!$B:$B,'CF USD'!$B49) -> 357587.5 | S49: =SUMIFS(Bonds!AX:AX,Bonds!$B:$B,'CF USD'!$B49) -> 205550 | T49: =SUMIFS(Bonds!AY:AY,Bonds!$B:$B,'CF USD'!$B49) -> 261100 | U49: =SUMIFS(Bonds!AZ:AZ,Bonds!$B:$B,'CF USD'!$B49) -> 318192.25 | V49: =SUMIFS(Bonds!BA:BA,Bonds!$B:$B,'CF USD'!$B49) -> 258587 | W49: =SUMIFS(Bonds!BB:BB,Bonds!$B:$B,'CF USD'!$B49) -> 523199 | X49: =SUMIFS(Bonds!BC:BC,Bonds!$B:$B,'CF USD'!$B49) -> 1102587.5 | Y49: =SUMIFS(Bonds!BD:BD,Bonds!$B:$B,'CF USD'!$B49) -> 205550 | Z49: =SUMIFS(Bonds!BE:BE,Bonds!$B:$B,'CF USD'!$B49) -> 261100 | AB49: =SUM(O49:Z49) -> 14349681
B50: UBS | C50: =SUMIFS(Bonds!AT:AT,Bonds!$B:$B,'CF USD'!$B50) -> 22000 | D50: =SUMIFS(Bonds!AU:AU,Bonds!$B:$B,'CF USD'!$B50) -> 0 | E50: =SUMIFS(Bonds!AV:AV,Bonds!$B:$B,'CF USD'!$B50) -> 0 | F50: =SUMIFS(Bonds!AW:AW,Bonds!$B:$B,'CF USD'!$B50) -> 0 | G50: =SUMIFS(Bonds!AX:AX,Bonds!$B:$B,'CF USD'!$B50) -> 0 | H50: =SUMIFS(Bonds!AY:AY,Bonds!$B:$B,'CF USD'!$B50) -> 0 | I50: =SUMIFS(Bonds!AZ:AZ,Bonds!$B:$B,'CF USD'!$B50) -> 22000 | J50: =SUMIFS(Bonds!BA:BA,Bonds!$B:$B,'CF USD'!$B50) -> 0 | K50: =SUMIFS(Bonds!BB:BB,Bonds!$B:$B,'CF USD'!$B50) -> 0 | L50: =SUMIFS(Bonds!BC:BC,Bonds!$B:$B,'CF USD'!$B50) -> 0 | M50: =SUMIFS(Bonds!BD:BD,Bonds!$B:$B,'CF USD'!$B50) -> 0 | N50: =SUMIFS(Bonds!BE:BE,Bonds!$B:$B,'CF USD'!$B50) -> 0 | O50: =SUMIFS(Bonds!AT:AT,Bonds!$B:$B,'CF USD'!$B50) -> 22000 | P50: =SUMIFS(Bonds!AU:AU,Bonds!$B:$B,'CF USD'!$B50) -> 0 | Q50: =SUMIFS(Bonds!AV:AV,Bonds!$B:$B,'CF USD'!$B50) -> 0 | R50: =SUMIFS(Bonds!AW:AW,Bonds!$B:$B,'CF USD'!$B50) -> 0 | S50: =SUMIFS(Bonds!AX:AX,Bonds!$B:$B,'CF USD'!$B50) -> 0 | T50: =SUMIFS(Bonds!AY:AY,Bonds!$B:$B,'CF USD'!$B50) -> 0 | U50: =SUMIFS(Bonds!AZ:AZ,Bonds!$B:$B,'CF USD'!$B50) -> 22000 | V50: =SUMIFS(Bonds!BA:BA,Bonds!$B:$B,'CF USD'!$B50) -> 0 | W50: =SUMIFS(Bonds!BB:BB,Bonds!$B:$B,'CF USD'!$B50) -> 0 | X50: =SUMIFS(Bonds!BC:BC,Bonds!$B:$B,'CF USD'!$B50) -> 0 | Y50: =SUMIFS(Bonds!BD:BD,Bonds!$B:$B,'CF USD'!$B50) -> 0 | Z50: =SUMIFS(Bonds!BE:BE,Bonds!$B:$B,'CF USD'!$B50) -> 0 | AB50: =SUM(O50:Z50) -> 44000
B51: JPM | C51: =SUMIFS(Bonds!AT:AT,Bonds!$B:$B,'CF USD'!$B51) -> 0 | D51: =SUMIFS(Bonds!AU:AU,Bonds!$B:$B,'CF USD'!$B51) -> 0 | E51: =SUMIFS(Bonds!AV:AV,Bonds!$B:$B,'CF USD'!$B51) -> 0 | F51: =SUMIFS(Bonds!AW:AW,Bonds!$B:$B,'CF USD'!$B51) -> 0 | G51: =SUMIFS(Bonds!AX:AX,Bonds!$B:$B,'CF USD'!$B51) -> 38125 | H51: =SUMIFS(Bonds!AY:AY,Bonds!$B:$B,'CF USD'!$B51) -> 0 | I51: =SUMIFS(Bonds!AZ:AZ,Bonds!$B:$B,'CF USD'!$B51) -> 0 | J51: =SUMIFS(Bonds!BA:BA,Bonds!$B:$B,'CF USD'!$B51) -> 0 | K51: =SUMIFS(Bonds!BB:BB,Bonds!$B:$B,'CF USD'!$B51) -> 0 | L51: =SUMIFS(Bonds!BC:BC,Bonds!$B:$B,'CF USD'!$B51) -> 0 | M51: =SUMIFS(Bonds!BD:BD,Bonds!$B:$B,'CF USD'!$B51) -> 38125 | N51: =SUMIFS(Bonds!BE:BE,Bonds!$B:$B,'CF USD'!$B51) -> 0 | O51: =SUMIFS(Bonds!AT:AT,Bonds!$B:$B,'CF USD'!$B51) -> 0 | P51: =SUMIFS(Bonds!AU:AU,Bonds!$B:$B,'CF USD'!$B51) -> 0 | Q51: =SUMIFS(Bonds!AV:AV,Bonds!$B:$B,'CF USD'!$B51) -> 0 | R51: =SUMIFS(Bonds!AW:AW,Bonds!$B:$B,'CF USD'!$B51) -> 0 | S51: =SUMIFS(Bonds!AX:AX,Bonds!$B:$B,'CF USD'!$B51) -> 38125 | T51: =SUMIFS(Bonds!AY:AY,Bonds!$B:$B,'CF USD'!$B51) -> 0 | U51: =SUMIFS(Bonds!AZ:AZ,Bonds!$B:$B,'CF USD'!$B51) -> 0 | V51: =SUMIFS(Bonds!BA:BA,Bonds!$B:$B,'CF USD'!$B51) -> 0 | W51: =SUMIFS(Bonds!BB:BB,Bonds!$B:$B,'CF USD'!$B51) -> 0 | X51: =SUMIFS(Bonds!BC:BC,Bonds!$B:$B,'CF USD'!$B51) -> 0 | Y51: =SUMIFS(Bonds!BD:BD,Bonds!$B:$B,'CF USD'!$B51) -> 38125 | Z51: =SUMIFS(Bonds!BE:BE,Bonds!$B:$B,'CF USD'!$B51) -> 0 | AB51: =SUM(O51:Z51) -> 76250
B52: Personal | C52: =SUMIFS(Bonds!AT:AT,Bonds!$B:$B,'CF USD'!$B52) -> 26500 | D52: =SUMIFS(Bonds!AU:AU,Bonds!$B:$B,'CF USD'!$B52) -> 0 | E52: =SUMIFS(Bonds!AV:AV,Bonds!$B:$B,'CF USD'!$B52) -> 18625 | F52: =SUMIFS(Bonds!AW:AW,Bonds!$B:$B,'CF USD'!$B52) -> 23028 | G52: =SUMIFS(Bonds!AX:AX,Bonds!$B:$B,'CF USD'!$B52) -> 0 | H52: =SUMIFS(Bonds!AY:AY,Bonds!$B:$B,'CF USD'!$B52) -> 11250 | I52: =SUMIFS(Bonds!AZ:AZ,Bonds!$B:$B,'CF USD'!$B52) -> 0 | J52: =SUMIFS(Bonds!BA:BA,Bonds!$B:$B,'CF USD'!$B52) -> 0 | K52: =SUMIFS(Bonds!BB:BB,Bonds!$B:$B,'CF USD'!$B52) -> 63125 | L52: =SUMIFS(Bonds!BC:BC,Bonds!$B:$B,'CF USD'!$B52) -> 0 | M52: =SUMIFS(Bonds!BD:BD,Bonds!$B:$B,'CF USD'!$B52) -> 0 | N52: =SUMIFS(Bonds!BE:BE,Bonds!$B:$B,'CF USD'!$B52) -> 11250 | O52: =SUMIFS(Bonds!AT:AT,Bonds!$B:$B,'CF USD'!$B52) -> 26500 | P52: =SUMIFS(Bonds!AU:AU,Bonds!$B:$B,'CF USD'!$B52) -> 0 | Q52: =SUMIFS(Bonds!AV:AV,Bonds!$B:$B,'CF USD'!$B52) -> 18625 | R52: =SUMIFS(Bonds!AW:AW,Bonds!$B:$B,'CF USD'!$B52) -> 23028 | S52: =SUMIFS(Bonds!AX:AX,Bonds!$B:$B,'CF USD'!$B52) -> 0 | T52: =SUMIFS(Bonds!AY:AY,Bonds!$B:$B,'CF USD'!$B52) -> 11250 | U52: =SUMIFS(Bonds!AZ:AZ,Bonds!$B:$B,'CF USD'!$B52) -> 0 | V52: =SUMIFS(Bonds!BA:BA,Bonds!$B:$B,'CF USD'!$B52) -> 0 | W52: =SUMIFS(Bonds!BB:BB,Bonds!$B:$B,'CF USD'!$B52) -> 63125 | X52: =SUMIFS(Bonds!BC:BC,Bonds!$B:$B,'CF USD'!$B52) -> 0 | Y52: =SUMIFS(Bonds!BD:BD,Bonds!$B:$B,'CF USD'!$B52) -> 0 | Z52: =SUMIFS(Bonds!BE:BE,Bonds!$B:$B,'CF USD'!$B52) -> 11250 | AB52: =SUM(O52:Z52) -> 153778
A55: Bonds ETF distributions
B56: Vontobel | C56: =SUMIFS('Bonds ETFs'!AV:AV,'Bonds ETFs'!A:A,$B56) -> 22192.256 | D56: =SUMIFS(T_bETFs[[ 2 ]],T_bETFs[Source],$B56) -> 7590.2161 | E56: =SUMIFS(T_bETFs[[ 3 ]],T_bETFs[Source],$B56) -> 20297.437 | F56: =SUMIFS(T_bETFs[[ 4 ]],T_bETFs[Source],$B56) -> 22192.256 | G56: =SUMIFS(T_bETFs[[ 5 ]],T_bETFs[Source],$B56) -> 7590.2161 | H56: =SUMIFS(T_bETFs[[ 6 ]],T_bETFs[Source],$B56) -> 20297.437 | I56: =SUMIFS(T_bETFs[[ 7 ]],T_bETFs[Source],$B56) -> 22192.256 | J56: =SUMIFS(T_bETFs[[ 8 ]],T_bETFs[Source],$B56) -> 7590.2161 | K56: =SUMIFS(T_bETFs[[ 9 ]],T_bETFs[Source],$B56) -> 20297.437 | L56: =SUMIFS(T_bETFs[[ 10 ]],T_bETFs[Source],$B56) -> 22192.256 | M56: =SUMIFS(T_bETFs[[ 11 ]],T_bETFs[Source],$B56) -> 79533.749 | N56: =SUMIFS(T_bETFs[[ 12 ]],T_bETFs[Source],$B56) -> 139081.64 | O56: =SUMIFS('Bonds ETFs'!AV:AV,'Bonds ETFs'!A:A,$B56) -> 22192.256 | P56: =SUMIFS(T_bETFs[[ 2 ]],T_bETFs[Source],$B56) -> 7590.2161 | Q56: =SUMIFS(T_bETFs[[ 3 ]],T_bETFs[Source],$B56) -> 20297.437 | R56: =SUMIFS(T_bETFs[[ 4 ]],T_bETFs[Source],$B56) -> 22192.256 | S56: =SUMIFS(T_bETFs[[ 5 ]],T_bETFs[Source],$B56) -> 7590.2161 | T56: =SUMIFS(T_bETFs[[ 6 ]],T_bETFs[Source],$B56) -> 20297.437 | U56: =SUMIFS(T_bETFs[[ 7 ]],T_bETFs[Source],$B56) -> 22192.256 | V56: =SUMIFS(T_bETFs[[ 8 ]],T_bETFs[Source],$B56) -> 7590.2161 | W56: =SUMIFS(T_bETFs[[ 9 ]],T_bETFs[Source],$B56) -> 20297.437 | X56: =SUMIFS(T_bETFs[[ 10 ]],T_bETFs[Source],$B56) -> 22192.256 | Y56: =SUMIFS(T_bETFs[[ 11 ]],T_bETFs[Source],$B56) -> 79533.749 | Z56: =SUMIFS(T_bETFs[[ 12 ]],T_bETFs[Source],$B56) -> 139081.64 | AB56: =SUM(O56:Z56) -> 391047.37
B57: UBS | C57: =SUMIFS('Bonds ETFs'!AV:AV,'Bonds ETFs'!A:A,$B57) -> 115453.84 | D57: =SUMIFS(T_bETFs[[ 2 ]],T_bETFs[Source],$B57) -> 115453.84 | E57: =SUMIFS(T_bETFs[[ 3 ]],T_bETFs[Source],$B57) -> 115453.84 | F57: =SUMIFS(T_bETFs[[ 4 ]],T_bETFs[Source],$B57) -> 115453.84 | G57: =SUMIFS(T_bETFs[[ 5 ]],T_bETFs[Source],$B57) -> 115453.84 | H57: =SUMIFS(T_bETFs[[ 6 ]],T_bETFs[Source],$B57) -> 115453.84 | I57: =SUMIFS(T_bETFs[[ 7 ]],T_bETFs[Source],$B57) -> 115453.84 | J57: =SUMIFS(T_bETFs[[ 8 ]],T_bETFs[Source],$B57) -> 115453.84 | K57: =SUMIFS(T_bETFs[[ 9 ]],T_bETFs[Source],$B57) -> 115453.84 | L57: =SUMIFS(T_bETFs[[ 10 ]],T_bETFs[Source],$B57) -> 115453.84 | M57: =SUMIFS(T_bETFs[[ 11 ]],T_bETFs[Source],$B57) -> 115453.84 | N57: =SUMIFS(T_bETFs[[ 12 ]],T_bETFs[Source],$B57) -> 115453.84 | O57: =SUMIFS('Bonds ETFs'!AV:AV,'Bonds ETFs'!A:A,$B57) -> 115453.84 | P57: =SUMIFS(T_bETFs[[ 2 ]],T_bETFs[Source],$B57) -> 115453.84 | Q57: =SUMIFS(T_bETFs[[ 3 ]],T_bETFs[Source],$B57) -> 115453.84 | R57: =SUMIFS(T_bETFs[[ 4 ]],T_bETFs[Source],$B57) -> 115453.84 | S57: =SUMIFS(T_bETFs[[ 5 ]],T_bETFs[Source],$B57) -> 115453.84 | T57: =SUMIFS(T_bETFs[[ 6 ]],T_bETFs[Source],$B57) -> 115453.84 | U57: =SUMIFS(T_bETFs[[ 7 ]],T_bETFs[Source],$B57) -> 115453.84 | V57: =SUMIFS(T_bETFs[[ 8 ]],T_bETFs[Source],$B57) -> 115453.84 | W57: =SUMIFS(T_bETFs[[ 9 ]],T_bETFs[Source],$B57) -> 115453.84 | X57: =SUMIFS(T_bETFs[[ 10 ]],T_bETFs[Source],$B57) -> 115453.84 | Y57: =SUMIFS(T_bETFs[[ 11 ]],T_bETFs[Source],$B57) -> 115453.84 | Z57: =SUMIFS(T_bETFs[[ 12 ]],T_bETFs[Source],$B57) -> 115453.84 | AB57: =SUM(O57:Z57) -> 1385446.1
B58: JPM | C58: =SUMIFS('Bonds ETFs'!AV:AV,'Bonds ETFs'!A:A,$B58) -> 104052.92 | D58: =SUMIFS(T_bETFs[[ 2 ]],T_bETFs[Source],$B58) -> 26023.944 | E58: =SUMIFS(T_bETFs[[ 3 ]],T_bETFs[Source],$B58) -> 83783.189 | F58: =SUMIFS(T_bETFs[[ 4 ]],T_bETFs[Source],$B58) -> 46293.677 | G58: =SUMIFS(T_bETFs[[ 5 ]],T_bETFs[Source],$B58) -> 26023.944 | H58: =SUMIFS(T_bETFs[[ 6 ]],T_bETFs[Source],$B58) -> 83783.189 | I58: =SUMIFS(T_bETFs[[ 7 ]],T_bETFs[Source],$B58) -> 46293.677 | J58: =SUMIFS(T_bETFs[[ 8 ]],T_bETFs[Source],$B58) -> 26023.944 | K58: =SUMIFS(T_bETFs[[ 9 ]],T_bETFs[Source],$B58) -> 83783.189 | L58: =SUMIFS(T_bETFs[[ 10 ]],T_bETFs[Source],$B58) -> 46293.677 | M58: =SUMIFS(T_bETFs[[ 11 ]],T_bETFs[Source],$B58) -> 26023.944 | N58: =SUMIFS(T_bETFs[[ 12 ]],T_bETFs[Source],$B58) -> 83783.189 | O58: =SUMIFS('Bonds ETFs'!AV:AV,'Bonds ETFs'!A:A,$B58) -> 104052.92 | P58: =SUMIFS(T_bETFs[[ 2 ]],T_bETFs[Source],$B58) -> 26023.944 | Q58: =SUMIFS(T_bETFs[[ 3 ]],T_bETFs[Source],$B58) -> 83783.189 | R58: =SUMIFS(T_bETFs[[ 4 ]],T_bETFs[Source],$B58) -> 46293.677 | S58: =SUMIFS(T_bETFs[[ 5 ]],T_bETFs[Source],$B58) -> 26023.944 | T58: =SUMIFS(T_bETFs[[ 6 ]],T_bETFs[Source],$B58) -> 83783.189 | U58: =SUMIFS(T_bETFs[[ 7 ]],T_bETFs[Source],$B58) -> 46293.677 | V58: =SUMIFS(T_bETFs[[ 8 ]],T_bETFs[Source],$B58) -> 26023.944 | W58: =SUMIFS(T_bETFs[[ 9 ]],T_bETFs[Source],$B58) -> 83783.189 | X58: =SUMIFS(T_bETFs[[ 10 ]],T_bETFs[Source],$B58) -> 46293.677 | Y58: =SUMIFS(T_bETFs[[ 11 ]],T_bETFs[Source],$B58) -> 26023.944 | Z58: =SUMIFS(T_bETFs[[ 12 ]],T_bETFs[Source],$B58) -> 83783.189 | AB58: =SUM(O58:Z58) -> 682162.49
B59: Personal | C59: =SUMIFS('Bonds ETFs'!AV:AV,'Bonds ETFs'!A:A,$B59) -> 11704.378 | D59: =SUMIFS(T_bETFs[[ 2 ]],T_bETFs[Source],$B59) -> 5578.1846 | E59: =SUMIFS(T_bETFs[[ 3 ]],T_bETFs[Source],$B59) -> 5578.1846 | F59: =SUMIFS(T_bETFs[[ 4 ]],T_bETFs[Source],$B59) -> 11704.378 | G59: =SUMIFS(T_bETFs[[ 5 ]],T_bETFs[Source],$B59) -> 5578.1846 | H59: =SUMIFS(T_bETFs[[ 6 ]],T_bETFs[Source],$B59) -> 5578.1846 | I59: =SUMIFS(T_bETFs[[ 7 ]],T_bETFs[Source],$B59) -> 11704.378 | J59: =SUMIFS(T_bETFs[[ 8 ]],T_bETFs[Source],$B59) -> 5578.1846 | K59: =SUMIFS(T_bETFs[[ 9 ]],T_bETFs[Source],$B59) -> 5578.1846 | L59: =SUMIFS(T_bETFs[[ 10 ]],T_bETFs[Source],$B59) -> 11704.378 | M59: =SUMIFS(T_bETFs[[ 11 ]],T_bETFs[Source],$B59) -> 5578.1846 | N59: =SUMIFS(T_bETFs[[ 12 ]],T_bETFs[Source],$B59) -> 5578.1846 | O59: =SUMIFS('Bonds ETFs'!AV:AV,'Bonds ETFs'!A:A,$B59) -> 11704.378 | P59: =SUMIFS(T_bETFs[[ 2 ]],T_bETFs[Source],$B59) -> 5578.1846 | Q59: =SUMIFS(T_bETFs[[ 3 ]],T_bETFs[Source],$B59) -> 5578.1846 | R59: =SUMIFS(T_bETFs[[ 4 ]],T_bETFs[Source],$B59) -> 11704.378 | S59: =SUMIFS(T_bETFs[[ 5 ]],T_bETFs[Source],$B59) -> 5578.1846 | T59: =SUMIFS(T_bETFs[[ 6 ]],T_bETFs[Source],$B59) -> 5578.1846 | U59: =SUMIFS(T_bETFs[[ 7 ]],T_bETFs[Source],$B59) -> 11704.378 | V59: =SUMIFS(T_bETFs[[ 8 ]],T_bETFs[Source],$B59) -> 5578.1846 | W59: =SUMIFS(T_bETFs[[ 9 ]],T_bETFs[Source],$B59) -> 5578.1846 | X59: =SUMIFS(T_bETFs[[ 10 ]],T_bETFs[Source],$B59) -> 11704.378 | Y59: =SUMIFS(T_bETFs[[ 11 ]],T_bETFs[Source],$B59) -> 5578.1846 | Z59: =SUMIFS(T_bETFs[[ 12 ]],T_bETFs[Source],$B59) -> 5578.1846 | AB59: =SUM(O59:Z59) -> 91442.988
A62: Deposits inflows
B63: Vontobel | C63: =SUMIFS(Deposits!AJ:AJ,Deposits!$A:$A,$B56) -> 0 | D63: =SUMIFS(Deposits!AK:AK,Deposits!$A:$A,$B56) -> 0 | E63: =SUMIFS(Deposits!AL:AL,Deposits!$A:$A,$B56) -> 1581.6641 | F63: =SUMIFS(Deposits!AM:AM,Deposits!$A:$A,$B56) -> 0 | G63: =SUMIFS(Deposits!AN:AN,Deposits!$A:$A,$B56) -> 0 | H63: =SUMIFS(Deposits!AO:AO,Deposits!$A:$A,$B56) -> 0 | I63: =SUMIFS(Deposits!AP:AP,Deposits!$A:$A,$B56) -> 0 | J63: =SUMIFS(Deposits!AQ:AQ,Deposits!$A:$A,$B56) -> 0 | K63: =SUMIFS(Deposits!AR:AR,Deposits!$A:$A,$B56) -> 0 | L63: =SUMIFS(Deposits!AS:AS,Deposits!$A:$A,$B56) -> 0 | M63: =SUMIFS(Deposits!AT:AT,Deposits!$A:$A,$B56) -> 0 | N63: =SUMIFS(Deposits!AU:AU,Deposits!$A:$A,$B56) -> 0 | O63: =SUMIFS(Deposits!AV:AV,Deposits!$A:$A,$B56) -> 0 | P63: =C63 -> 0 | Q63: =D63 -> 0 | R63: =E63 -> 1581.6641 | S63: =F63 -> 0 | T63: =G63 -> 0 | U63: =H63 -> 0 | V63: =I63 -> 0 | W63: =J63 -> 0 | ... Z63: =M63 -> 0 | AB63: =SUM(O63:Z63) -> 1581.6641
B64: UBS | C64: =SUMIFS(Deposits!AJ:AJ,Deposits!$A:$A,$B57) -> 0 | D64: =SUMIFS(Deposits!AK:AK,Deposits!$A:$A,$B57) -> 0 | E64: =SUMIFS(Deposits!AL:AL,Deposits!$A:$A,$B57) -> 0 | F64: =SUMIFS(Deposits!AM:AM,Deposits!$A:$A,$B57) -> 0 | G64: =SUMIFS(Deposits!AN:AN,Deposits!$A:$A,$B57) -> 0 | H64: =SUMIFS(Deposits!AO:AO,Deposits!$A:$A,$B57) -> 0 | I64: =SUMIFS(Deposits!AP:AP,Deposits!$A:$A,$B57) -> 0 | J64: =SUMIFS(Deposits!AQ:AQ,Deposits!$A:$A,$B57) -> 0 | K64: =SUMIFS(Deposits!AR:AR,Deposits!$A:$A,$B57) -> 0 | L64: =SUMIFS(Deposits!AS:AS,Deposits!$A:$A,$B57) -> 0 | M64: =SUMIFS(Deposits!AT:AT,Deposits!$A:$A,$B57) -> 0 | N64: =SUMIFS(Deposits!AU:AU,Deposits!$A:$A,$B57) -> 0 | O64: =SUMIFS(Deposits!AV:AV,Deposits!$A:$A,$B57) -> 0 | P64: =C64 -> 0 | Q64: =D64 -> 0 | R64: =E64 -> 0 | S64: =F64 -> 0 | T64: =G64 -> 0 | U64: =H64 -> 0 | V64: =I64 -> 0 | W64: =J64 -> 0 | ... Z64: =M64 -> 0 | AB64: =SUM(O64:Z64) -> 0
B65: JPM | C65: =SUMIFS(Deposits!AJ:AJ,Deposits!$A:$A,$B58) -> 0 | D65: =SUMIFS(Deposits!AK:AK,Deposits!$A:$A,$B58) -> 0 | E65: =SUMIFS(Deposits!AL:AL,Deposits!$A:$A,$B58) -> 0 | F65: =SUMIFS(Deposits!AM:AM,Deposits!$A:$A,$B58) -> 0 | G65: =SUMIFS(Deposits!AN:AN,Deposits!$A:$A,$B58) -> 0 | H65: =SUMIFS(Deposits!AO:AO,Deposits!$A:$A,$B58) -> 0 | I65: =SUMIFS(Deposits!AP:AP,Deposits!$A:$A,$B58) -> 0 | J65: =SUMIFS(Deposits!AQ:AQ,Deposits!$A:$A,$B58) -> 0 | K65: =SUMIFS(Deposits!AR:AR,Deposits!$A:$A,$B58) -> 0 | L65: =SUMIFS(Deposits!AS:AS,Deposits!$A:$A,$B58) -> 0 | M65: =SUMIFS(Deposits!AT:AT,Deposits!$A:$A,$B58) -> 0 | N65: =SUMIFS(Deposits!AU:AU,Deposits!$A:$A,$B58) -> 0 | O65: =SUMIFS(Deposits!AV:AV,Deposits!$A:$A,$B58) -> 0 | P65: =C65 -> 0 | Q65: =D65 -> 0 | R65: =E65 -> 0 | S65: =F65 -> 0 | T65: =G65 -> 0 | U65: =H65 -> 0 | V65: =I65 -> 0 | W65: =J65 -> 0 | ... Z65: =M65 -> 0 | AB65: =SUM(O65:Z65) -> 0
B66: Personal | C66: =SUMIFS(Deposits!AJ:AJ,Deposits!$A:$A,$B59) -> 31083.333 | D66: =SUMIFS(Deposits!AK:AK,Deposits!$A:$A,$B59) -> 31083.333 | E66: =SUMIFS(Deposits!AL:AL,Deposits!$A:$A,$B59) -> 31083.333 | F66: =SUMIFS(Deposits!AM:AM,Deposits!$A:$A,$B59) -> 31083.333 | G66: =SUMIFS(Deposits!AN:AN,Deposits!$A:$A,$B59) -> 31083.333 | H66: =SUMIFS(Deposits!AO:AO,Deposits!$A:$A,$B59) -> 31083.333 | I66: =SUMIFS(Deposits!AP:AP,Deposits!$A:$A,$B59) -> 31083.333 | J66: =SUMIFS(Deposits!AQ:AQ,Deposits!$A:$A,$B59) -> 31083.333 | K66: =SUMIFS(Deposits!AR:AR,Deposits!$A:$A,$B59) -> 31083.333 | L66: =SUMIFS(Deposits!AS:AS,Deposits!$A:$A,$B59) -> 31083.333 | M66: =SUMIFS(Deposits!AT:AT,Deposits!$A:$A,$B59) -> 31083.333 | N66: =SUMIFS(Deposits!AU:AU,Deposits!$A:$A,$B59) -> 31083.333 | O66: =C66 -> 31083.333 | P66: =C66 -> 31083.333 | Q66: =D66 -> 31083.333 | R66: =E66 -> 31083.333 | S66: =F66 -> 31083.333 | T66: =G66 -> 31083.333 | U66: =H66 -> 31083.333 | V66: =I66 -> 31083.333 | W66: =J66 -> 31083.333 | ... Z66: =M66 -> 31083.333 | AB66: =SUM(O66:Z66) -> 373000
A69: Equity dividends
B70: Vontobel | C70: =SUMIFS(T_Eq[1],T_Eq[Source],'CF USD'!$B70) -> 30914.753 | D70: =SUMIFS(T_Eq[2],T_Eq[Source],'CF USD'!$B70) -> 8180.275 | E70: =SUMIFS(T_Eq[3],T_Eq[Source],'CF USD'!$B70) -> 70438.446 | F70: =SUMIFS(T_Eq[4],T_Eq[Source],'CF USD'!$B70) -> 23548.075 | G70: =SUMIFS(T_Eq[5],T_Eq[Source],'CF USD'!$B70) -> 12275.275 | H70: =SUMIFS(T_Eq[6],T_Eq[Source],'CF USD'!$B70) -> 90470.614 | I70: =SUMIFS(T_Eq[7],T_Eq[Source],'CF USD'!$B70) -> 30914.753 | J70: =SUMIFS(T_Eq[8],T_Eq[Source],'CF USD'!$B70) -> 7106.275 | K70: =SUMIFS(T_Eq[9],T_Eq[Source],'CF USD'!$B70) -> 69364.446 | L70: =SUMIFS(T_Eq[10],T_Eq[Source],'CF USD'!$B70) -> 22474.075 | M70: =SUMIFS(T_Eq[11],T_Eq[Source],'CF USD'!$B70) -> 11201.275 | N70: =SUMIFS(T_Eq[12],T_Eq[Source],'CF USD'!$B70) -> 104500.73 | O70: =SUMIFS(T_Eq[1],T_Eq[Source],'CF USD'!$B70) -> 30914.753 | P70: =SUMIFS(T_Eq[2],T_Eq[Source],'CF USD'!$B70) -> 8180.275 | Q70: =SUMIFS(T_Eq[3],T_Eq[Source],'CF USD'!$B70) -> 70438.446 | R70: =SUMIFS(T_Eq[4],T_Eq[Source],'CF USD'!$B70) -> 23548.075 | S70: =SUMIFS(T_Eq[5],T_Eq[Source],'CF USD'!$B70) -> 12275.275 | T70: =SUMIFS(T_Eq[6],T_Eq[Source],'CF USD'!$B70) -> 90470.614 | U70: =SUMIFS(T_Eq[7],T_Eq[Source],'CF USD'!$B70) -> 30914.753 | V70: =SUMIFS(T_Eq[8],T_Eq[Source],'CF USD'!$B70) -> 7106.275 | W70: =SUMIFS(T_Eq[9],T_Eq[Source],'CF USD'!$B70) -> 69364.446 | X70: =SUMIFS(T_Eq[10],T_Eq[Source],'CF USD'!$B70) -> 22474.075 | Y70: =SUMIFS(T_Eq[11],T_Eq[Source],'CF USD'!$B70) -> 11201.275 | Z70: =SUMIFS(T_Eq[12],T_Eq[Source],'CF USD'!$B70) -> 104500.73 | AB70: =SUM(O70:Z70) -> 481388.99
B71: UBS | C71: =SUMIFS(T_Eq[1],T_Eq[Source],'CF USD'!$B71) -> 0 | D71: =SUMIFS(T_Eq[2],T_Eq[Source],'CF USD'!$B71) -> 6063.3369 | E71: =SUMIFS(T_Eq[3],T_Eq[Source],'CF USD'!$B71) -> 2798.7423 | F71: =SUMIFS(T_Eq[4],T_Eq[Source],'CF USD'!$B71) -> 0 | G71: =SUMIFS(T_Eq[5],T_Eq[Source],'CF USD'!$B71) -> 0 | H71: =SUMIFS(T_Eq[6],T_Eq[Source],'CF USD'!$B71) -> 2798.7423 | I71: =SUMIFS(T_Eq[7],T_Eq[Source],'CF USD'!$B71) -> 0 | J71: =SUMIFS(T_Eq[8],T_Eq[Source],'CF USD'!$B71) -> 0 | K71: =SUMIFS(T_Eq[9],T_Eq[Source],'CF USD'!$B71) -> 2798.7423 | L71: =SUMIFS(T_Eq[10],T_Eq[Source],'CF USD'!$B71) -> 0 | M71: =SUMIFS(T_Eq[11],T_Eq[Source],'CF USD'!$B71) -> 0 | N71: =SUMIFS(T_Eq[12],T_Eq[Source],'CF USD'!$B71) -> 2798.7423 | O71: =SUMIFS(T_Eq[1],T_Eq[Source],'CF USD'!$B71) -> 0 | P71: =SUMIFS(T_Eq[2],T_Eq[Source],'CF USD'!$B71) -> 6063.3369 | Q71: =SUMIFS(T_Eq[3],T_Eq[Source],'CF USD'!$B71) -> 2798.7423 | R71: =SUMIFS(T_Eq[4],T_Eq[Source],'CF USD'!$B71) -> 0 | S71: =SUMIFS(T_Eq[5],T_Eq[Source],'CF USD'!$B71) -> 0 | T71: =SUMIFS(T_Eq[6],T_Eq[Source],'CF USD'!$B71) -> 2798.7423 | U71: =SUMIFS(T_Eq[7],T_Eq[Source],'CF USD'!$B71) -> 0 | V71: =SUMIFS(T_Eq[8],T_Eq[Source],'CF USD'!$B71) -> 0 | W71: =SUMIFS(T_Eq[9],T_Eq[Source],'CF USD'!$B71) -> 2798.7423 | X71: =SUMIFS(T_Eq[10],T_Eq[Source],'CF USD'!$B71) -> 0 | Y71: =SUMIFS(T_Eq[11],T_Eq[Source],'CF USD'!$B71) -> 0 | Z71: =SUMIFS(T_Eq[12],T_Eq[Source],'CF USD'!$B71) -> 2798.7423 | AB71: =SUM(O71:Z71) -> 17258.306
B72: JPM | C72: =SUMIFS(T_Eq[1],T_Eq[Source],'CF USD'!$B72) -> 0 | D72: =SUMIFS(T_Eq[2],T_Eq[Source],'CF USD'!$B72) -> 0 | E72: =SUMIFS(T_Eq[3],T_Eq[Source],'CF USD'!$B72) -> 2948.0869 | F72: =SUMIFS(T_Eq[4],T_Eq[Source],'CF USD'!$B72) -> 0 | G72: =SUMIFS(T_Eq[5],T_Eq[Source],'CF USD'!$B72) -> 0 | H72: =SUMIFS(T_Eq[6],T_Eq[Source],'CF USD'!$B72) -> 60.08275 | I72: =SUMIFS(T_Eq[7],T_Eq[Source],'CF USD'!$B72) -> 0 | J72: =SUMIFS(T_Eq[8],T_Eq[Source],'CF USD'!$B72) -> 0 | K72: =SUMIFS(T_Eq[9],T_Eq[Source],'CF USD'!$B72) -> 2948.0869 | L72: =SUMIFS(T_Eq[10],T_Eq[Source],'CF USD'!$B72) -> 0 | M72: =SUMIFS(T_Eq[11],T_Eq[Source],'CF USD'!$B72) -> 0 | N72: =SUMIFS(T_Eq[12],T_Eq[Source],'CF USD'!$B72) -> 60.08275 | O72: =SUMIFS(T_Eq[1],T_Eq[Source],'CF USD'!$B72) -> 0 | P72: =SUMIFS(T_Eq[2],T_Eq[Source],'CF USD'!$B72) -> 0 | Q72: =SUMIFS(T_Eq[3],T_Eq[Source],'CF USD'!$B72) -> 2948.0869 | R72: =SUMIFS(T_Eq[4],T_Eq[Source],'CF USD'!$B72) -> 0 | S72: =SUMIFS(T_Eq[5],T_Eq[Source],'CF USD'!$B72) -> 0 | T72: =SUMIFS(T_Eq[6],T_Eq[Source],'CF USD'!$B72) -> 60.08275 | U72: =SUMIFS(T_Eq[7],T_Eq[Source],'CF USD'!$B72) -> 0 | V72: =SUMIFS(T_Eq[8],T_Eq[Source],'CF USD'!$B72) -> 0 | W72: =SUMIFS(T_Eq[9],T_Eq[Source],'CF USD'!$B72) -> 2948.0869 | X72: =SUMIFS(T_Eq[10],T_Eq[Source],'CF USD'!$B72) -> 0 | Y72: =SUMIFS(T_Eq[11],T_Eq[Source],'CF USD'!$B72) -> 0 | Z72: =SUMIFS(T_Eq[12],T_Eq[Source],'CF USD'!$B72) -> 60.08275 | AB72: =SUM(O72:Z72) -> 6016.3392
B73: Personal | C73: =SUMIFS(T_Eq[1],T_Eq[Source],'CF USD'!$B73) -> 13541.868 | D73: =SUMIFS(T_Eq[2],T_Eq[Source],'CF USD'!$B73) -> 2192.0668 | E73: =SUMIFS(T_Eq[3],T_Eq[Source],'CF USD'!$B73) -> 6487.44 | F73: =SUMIFS(T_Eq[4],T_Eq[Source],'CF USD'!$B73) -> 6629.4667 | G73: =SUMIFS(T_Eq[5],T_Eq[Source],'CF USD'!$B73) -> 15760.067 | H73: =SUMIFS(T_Eq[6],T_Eq[Source],'CF USD'!$B73) -> 8166.525 | I73: =SUMIFS(T_Eq[7],T_Eq[Source],'CF USD'!$B73) -> 11435.202 | J73: =SUMIFS(T_Eq[8],T_Eq[Source],'CF USD'!$B73) -> 2192.0668 | K73: =SUMIFS(T_Eq[9],T_Eq[Source],'CF USD'!$B73) -> 8594.1067 | L73: =SUMIFS(T_Eq[10],T_Eq[Source],'CF USD'!$B73) -> 6629.4667 | M73: =SUMIFS(T_Eq[11],T_Eq[Source],'CF USD'!$B73) -> 13653.4 | N73: =SUMIFS(T_Eq[12],T_Eq[Source],'CF USD'!$B73) -> 39062.765 | O73: =SUMIFS(T_Eq[1],T_Eq[Source],'CF USD'!$B73) -> 13541.868 | P73: =SUMIFS(T_Eq[2],T_Eq[Source],'CF USD'!$B73) -> 2192.0668 | Q73: =SUMIFS(T_Eq[3],T_Eq[Source],'CF USD'!$B73) -> 6487.44 | R73: =SUMIFS(T_Eq[4],T_Eq[Source],'CF USD'!$B73) -> 6629.4667 | S73: =SUMIFS(T_Eq[5],T_Eq[Source],'CF USD'!$B73) -> 15760.067 | T73: =SUMIFS(T_Eq[6],T_Eq[Source],'CF USD'!$B73) -> 8166.525 | U73: =SUMIFS(T_Eq[7],T_Eq[Source],'CF USD'!$B73) -> 11435.202 | V73: =SUMIFS(T_Eq[8],T_Eq[Source],'CF USD'!$B73) -> 2192.0668 | W73: =SUMIFS(T_Eq[9],T_Eq[Source],'CF USD'!$B73) -> 8594.1067 | X73: =SUMIFS(T_Eq[10],T_Eq[Source],'CF USD'!$B73) -> 6629.4667 | Y73: =SUMIFS(T_Eq[11],T_Eq[Source],'CF USD'!$B73) -> 13653.4 | Z73: =SUMIFS(T_Eq[12],T_Eq[Source],'CF USD'!$B73) -> 39062.765 | AB73: =SUM(O73:Z73) -> 134344.44
A78: PE & RE cash flows, thousands USD
B79: PE & RE Cash Flow (without US) | C79: =SUM(C81:C82) -> 0 | D79: =SUM(D81:D82) -> 0 | E79: =SUM(E81:E82) -> 0 | F79: =SUM(F81:F82) -> 0 | G79: =SUM(G81:G82) -> 0 | H79: =SUM(H81:H82) -> 0 | I79: =SUM(I81:I82) -> 0 | J79: =SUM(J81:J82) -> 0 | ... Z79: =SUM(Z81:Z82) -> 73.115212 | AB79: =SUM(O79:Z79) -> 5145.0641
B80: US projects income | C80: 0 | D80: 0 | E80: 0 | F80: 0 | G80: 0 | H80: 0 | I80: 0 | J80: 0 | K80: 0 | L80: 0 | M80: 0 | N80: ='Real Estate'!#REF!/1000 -> #REF! | O80: ='Real Estate'!AX29/1000 -> 0 | P80: ='Real Estate'!AY29/1000 -> 0 | Q80: ='Real Estate'!AZ29/1000 -> 0 | R80: ='Real Estate'!BA29/1000 -> 0 | S80: ='Real Estate'!BB29/1000 -> 0 | T80: ='Real Estate'!BC29/1000 -> 8154 | U80: ='Real Estate'!BD29/1000 -> 0 | V80: ='Real Estate'!BE29/1000 -> 0 | ... Z80: ='Real Estate'!BI29/1000 -> 550 | AB80: =SUM(O80:Z80) -> 8704
B81: Private Equity Cash Flow | C81: 0 | D81: 0 | E81: 0 | F81: 0 | G81: 0 | H81: 0 | I81: 0 | J81: 0 | K81: 0 | L81: 0 | M81: 0 | N81: 0 | O81: =SUM(T_AI[1])/1000 -> 72 | P81: =SUM(T_AI[2])/1000 -> 0 | Q81: =SUM(T_AI[3])/1000 -> 0 | R81: =SUM(T_AI[4])/1000 -> 0 | S81: =SUM(T_AI[5])/1000 -> 0 | T81: =SUM(T_AI[6])/1000 -> 0 | U81: =SUM(T_AI[7])/1000 -> 0 | V81: =SUM(T_AI[8])/1000 -> 0 | W81: =SUM(T_AI[9])/1000 -> 0 | X81: =SUM(T_AI[10])/1000 -> 0 | Y81: =SUM(T_AI[11])/1000 -> 0 | Z81: =SUM(T_AI[12])/1000 -> 0 | AB81: =SUM(O81:Z81) -> 72
B82: Real Estate Cash Flow | C82: 0 | D82: 0 | E82: 0 | F82: 0 | G82: 0 | H82: 0 | I82: 0 | J82: 0 | K82: 0 | L82: 0 | M82: 0 | N82: =SUM('Real Estate'!#REF!)/1000 -> #REF! | O82: =SUM('Real Estate'!AX27:AX28)/1000 -> -449.62095 | P82: =SUM('Real Estate'!AY27:AY28)/1000 -> -327.71694 | Q82: =SUM('Real Estate'!AZ27:AZ28)/1000 -> 39.680212 | R82: =SUM('Real Estate'!BA27:BA28)/1000 -> 148.73181 | S82: =SUM('Real Estate'!BB27:BB28)/1000 -> 132.34866 | T82: =SUM('Real Estate'!BC27:BC28)/1000 -> 3831.2092 | U82: =SUM('Real Estate'!BD27:BD28)/1000 -> -287.26059 | V82: =SUM('Real Estate'!BE27:BE28)/1000 -> 167.12106 | ... Z82: =SUM('Real Estate'!BI27:BI28)/1000 -> 73.115212 | AB82: =SUM(O82:Z82) -> 5073.0641

Sheet PORTF>>

Sheet Bonds
A1: Description | B1: Source | C1: Maturity type | D1: ISIN / IBAN | E1: Risk CCY | F1: V1412 | G1: V1430 | H1: UBS | I1: Quantity | J1: Coupon | K1: Coupon in Loc.Curr | L1: Coupon in USD | M1: Maturity | N1: YTM/YTC | O1: Duration | P1: Gross P&L | Q1: Current Yield, % | R1: for WYTC | S1: V1412 CP | T1: V1430 CP | U1: Cost price | V1: Current Yield | W1: Exchange rate, C | X1: Market price | Y1: Exchange rate, N | Z1: Market value in CCY | AA1: Market value in USD | AB1: Full MV in CCY | AC1: Full MV in USD | AD1: Cost value | AE1: AI, CCY | AF1: AI, USD | AG1: G-spread, p.a. | AH1: Lending Value, % | AI1: Call date | AJ1: Call margin | AK1: Sector marker | AL1: Country | AM1: Market | AN1: Issuer | AO1: Coupons per annum | AP1: Next coupon date | AQ1: Second next coupon date | AR1: Coupon date 3 | AS1: Coupon date 4 | AT1: 1 | AU1: 2 | AV1: 3 | AW1: 4 | AX1: 5 | AY1: 6 | AZ1: 7 | BA1: 8 | BB1: 9 | BC1: 10 | BD1: 11 | BE1: 12 | BF1: Day
A2: 8.8% NITRUM FINANCE DAC 2025-30.06.2028 BONDS | B2: UBS | C2: =IF(T_Bonds[[#This Row],[Call date]]<>"","Callable","Maturity") -> Maturity | D2: XS3135134248 | E2: EUR | F2: =IFERROR(INDEX('V004'!D:E,MATCH(D2,'V004'!D:D,0),2),0) -> 0 | G2: =IFERROR(INDEX('V001'!D:E,MATCH(D2,'V001'!D:D,0),2),0) -> 0 | H2: =IFERROR(INDEX(UBS!C:D,MATCH(D2,UBS!D:D,0),1),0) -> 500000 | I2: =SUM(T_Bonds[[#This Row],[V1412]:[UBS]]) -> 500000 | J2: =LEFT(A2,FIND("%",A2,1))+1-1 -> 0.088 | K2: =J2*I2 -> 44000 | L2: =IF(Y2<>1,I2*J2*Y2,I2*J2) -> 50912.4 | M2: 46934 | N2: =IFERROR(INDEX(Cbonds!C:H,MATCH(D2,Cbonds!C:C,0),4)/100,0) -> 0 | O2: 0.03 | P2: =T_Bonds[[#This Row],[Market price]]-T_Bonds[[#This Row],[Cost price]] -> -0.2495 | Q2: =T_Bonds[[#This Row],[Coupon]]/T_Bonds[[#This Row],[Cost price]] -> 0.092050209 | R2: =N2*I2 -> 0 | S2: =IFERROR(INDEX('V004'!D:J,MATCH(D2,'V004'!D:D,0),7),0) -> 0 | T2: =IFERROR(INDEX('V001'!D:J,MATCH(D2,'V001'!D:D,0),7),0) -> 0 | U2: 0.956 | V2: =I2*J2/U2 -> 46025.105 | W2: 1.0497 | X2: 0.7065 | Y2: =INDEX('Tech list'!A:C,MATCH(T_Bonds[[#This Row],[Risk CCY]],'Tech list'!A:A,0),3) -> 1.1571 | Z2: =T_Bonds[[#This Row],[Market price]]*T_Bonds[[#This Row],[Quantity]] -> 353250 | AA2: =IF(E2<>"USD",X2*Y2*I2,X2*I2) -> 408745.58 | AB2: =T_Bonds[[#This Row],[Market value in CCY]]+T_Bonds[[#This Row],[AI, CCY]] -> 380354.97 | AC2: =T_Bonds[[#This Row],[Market value in USD]]+T_Bonds[[#This Row],[AI, USD]] -> 440108.74 | AD2: =U2*I2 -> 478000 | AE2: =(T_Bonds[[#This Row],[Coupon in Loc.Curr]]/T_Bonds[[#This Row],[Coupons per annum]])*((TODAY()-EDATE(T_Bonds[[#This Row],[Next coupon date]],-12/T_Bonds[[#This Row],[Coupons per annum]]))/IF(T_Bonds[[#This Row],[Coupons per annum]]=2,181,IF(T_Bonds[[#This Row],[Coupons per annum]]=4,91,360))) -> 27104.972 | AF2: =T_Bonds[[#This Row],[AI, CCY]]*T_Bonds[[#This Row],[Exchange rate, N]] -> 31363.164 | AG2: =IFERROR(IF(INDEX(Cbonds!C:AC,MATCH(D2,Cbonds!C:C,0),27)>5000,0,INDEX(Cbonds!C:AC,MATCH(D2,Cbonds!C:C,0),27)),0) -> 0 | AH2: 0 | AK2: Fertilizers | AL2: Hungary | AM2: Emerging Markets | AN2: Nitrogenmuvek | AO2: 2 | AP2: 46052 | AQ2: =EDATE(T_Bonds[[#This Row],[Next coupon date]],12/T_Bonds[[#This Row],[Coupons per annum]]) -> 46233 | AR2: =EDATE(T_Bonds[[#This Row],[Second next coupon date]],12/$AO2) -> 46417 | AS2: =EDATE(T_Bonds[[#This Row],[Coupon date 3]],12/$AO2) -> 46598 | AT2: =IF( OR( AT$1=MONTH($AP2), AT$1=MONTH($AQ2), AT$1=MONTH($AR2), AT$1=MONTH($AS2)), IF('CF USD'!$A$8="On",$L2,$K2)/T_Bonds[[#This Row],[Coupons per annum]],0) -> 22000 | AU2: =IF( OR( AU$1=MONTH($AP2), AU$1=MONTH($AQ2), AU$1=MONTH($AR2), AU$1=MONTH($AS2)), IF('CF USD'!$A$8="On",$L2,$K2)/T_Bonds[[#This Row],[Coupons per annum]],0) -> 0 | AV2: =IF( OR( AV$1=MONTH($AP2), AV$1=MONTH($AQ2), AV$1=MONTH($AR2), AV$1=MONTH($AS2)), IF('CF USD'!$A$8="On",$L2,$K2)/T_Bonds[[#This Row],[Coupons per annum]],0) -> 0 | AW2: =IF( OR( AW$1=MONTH($AP2), AW$1=MONTH($AQ2), AW$1=MONTH($AR2), AW$1=MONTH($AS2)), IF('CF USD'!$A$8="On",$L2,$K2)/T_Bonds[[#This Row],[Coupons per annum]],0) -> 0 | AX2: =IF( OR( AX$1=MONTH($AP2), AX$1=MONTH($AQ2), AX$1=MONTH($AR2), AX$1=MONTH($AS2)), IF('CF USD'!$A$8="On",$L2,$K2)/T_Bonds[[#This Row],[Coupons per annum]],0) -> 0 | AY2: =IF( OR( AY$1=MONTH($AP2), AY$1=MONTH($AQ2), AY$1=MONTH($AR2), AY$1=MONTH($AS2)), IF('CF USD'!$A$8="On",$L2,$K2)/T_Bonds[[#This Row],[Coupons per annum]],0) -> 0 | AZ2: =IF( OR( AZ$1=MONTH($AP2), AZ$1=MONTH($AQ2), AZ$1=MONTH($AR2), AZ$1=MONTH($AS2)), IF('CF USD'!$A$8="On",$L2,$K2)/T_Bonds[[#This Row],[Coupons per annum]],0) -> 22000 | BA2: =IF( OR( BA$1=MONTH($AP2), BA$1=MONTH($AQ2), BA$1=MONTH($AR2), BA$1=MONTH($AS2)), IF('CF USD'!$A$8="On",$L2,$K2)/T_Bonds[[#This Row],[Coupons per annum]],0) -> 0 | ... BE2: =IF( OR( BE$1=MONTH($AP2), BE$1=MONTH($AQ2), BE$1=MONTH($AR2), BE$1=MONTH($AS2)), IF('CF USD'!$A$8="On",$L2,$K2)/T_Bonds[[#This Row],[Coupons per annum]],0) -> 0 | BF2: =DAY(T_Bonds[[#This Row],[Next coupon date]]) -> 30
A3: Enel, 2040, 5.75% | B3: Personal | C3: =IF(T_Bonds[[#This Row],[Call date]]<>"","Callable","Maturity") -> Maturity | D3: XS0452187320 | E3: GBP | F3: 400000 | G3: =IFERROR(INDEX('V001'!D:E,MATCH(D3,'V001'!D:D,0),2),0) -> 0 | H3: =IFERROR(INDEX(UBS!C:D,MATCH(D3,UBS!D:D,0),1),0) -> 0 | I3: =SUM(T_Bonds[[#This Row],[V1412]:[UBS]]) -> 400000 | J3: 0.0575 | K3: =J3*I3 -> 23000 | L3: =IF(Y3<>1,I3*J3*Y3,I3*J3) -> 30760.2 | M3: 51393 | N3: 0.060511987 | O3: =IFERROR(INDEX(Cbonds!C:H,MATCH(D3,Cbonds!C:C,0),5),0) -> 10.036617 | P3: =T_Bonds[[#This Row],[Market price]]-T_Bonds[[#This Row],[Cost price]] -> 0.00861 | Q3: =T_Bonds[[#This Row],[Coupon]]/T_Bonds[[#This Row],[Cost price]] -> 0.058854236 | R3: =N3*I3 -> 24204.795 | S3: 0.97699 | T3: =IFERROR(VLOOKUP(D3,'V001'!$D:$J,7,0),0) -> 0 | U3: =IFERROR(S3*T_Bonds[[#This Row],[V1412]]/(T_Bonds[[#This Row],[V1412]]+T_Bonds[[#This Row],[V1430]])+T3*T_Bonds[[#This Row],[V1430]]/(T_Bonds[[#This Row],[V1412]]+T_Bonds[[#This Row],[V1430]]),0) -> 0.97699 | V3: =I3*J3/U3 -> 23541.694 | W3: 1.29331 | X3: =IFERROR(INDEX(Cbonds!C:AF,MATCH(D3,Cbonds!C:C,0),30)/100,0) -> 0.9856 | Y3: =INDEX('Tech list'!A:C,MATCH(T_Bonds[[#This Row],[Risk CCY]],'Tech list'!A:A,0),3) -> 1.3374 | Z3: =T_Bonds[[#This Row],[Market price]]*T_Bonds[[#This Row],[Quantity]] -> 394240 | AA3: =IF(E3<>"USD",X3*Y3*I3,X3*I3) -> 527256.58 | AB3: =T_Bonds[[#This Row],[Market value in CCY]]+T_Bonds[[#This Row],[AI, CCY]] -> 405548.33 | AC3: =T_Bonds[[#This Row],[Market value in USD]]+T_Bonds[[#This Row],[AI, USD]] -> 542380.34 | AD3: =U3*I3 -> 390796 | AE3: =(T_Bonds[[#This Row],[Coupon in Loc.Curr]]/T_Bonds[[#This Row],[Coupons per annum]])*((TODAY()-EDATE(T_Bonds[[#This Row],[Next coupon date]],-12/T_Bonds[[#This Row],[Coupons per annum]])))/(360/T_Bonds[[#This Row],[Coupons per annum]]) -> 11308.333 | AF3: =T_Bonds[[#This Row],[AI, CCY]]*T_Bonds[[#This Row],[Exchange rate, N]] -> 15123.765 | AG3: =IFERROR(IF(INDEX(Cbonds!C:AC,MATCH(D3,Cbonds!C:C,0),27)>5000,0,INDEX(Cbonds!C:AC,MATCH(D3,Cbonds!C:C,0),27)),0) -> 0 | AH3: 75 | AK3: Power | AL3: Italy | AM3: Developed | AN3: Enel | AO3: 1 | AP3: =IFERROR(INDEX(Cbonds!C:H,MATCH(D3,Cbonds!C:C,0),3),0) -> 46279 | AQ3: =EDATE(T_Bonds[[#This Row],[Next coupon date]],12/T_Bonds[[#This Row],[Coupons per annum]]) -> 46644 | AR3: =EDATE(T_Bonds[[#This Row],[Second next coupon date]],12/$AO3) -> 47010 | AS3: =EDATE(T_Bonds[[#This Row],[Coupon date 3]],12/$AO3) -> 47375 | AT3: =IF( OR( AT$1=MONTH($AP3), AT$1=MONTH($AQ3), AT$1=MONTH($AR3), AT$1=MONTH($AS3)), IF('CF USD'!$A$8="On",$L3,$K3)/T_Bonds[[#This Row],[Coupons per annum]],0) -> 0 | AU3: =IF( OR( AU$1=MONTH($AP3), AU$1=MONTH($AQ3), AU$1=MONTH($AR3), AU$1=MONTH($AS3)), IF('CF USD'!$A$8="On",$L3,$K3)/T_Bonds[[#This Row],[Coupons per annum]],0) -> 0 | AV3: =IF( OR( AV$1=MONTH($AP3), AV$1=MONTH($AQ3), AV$1=MONTH($AR3), AV$1=MONTH($AS3)), IF('CF USD'!$A$8="On",$L3,$K3)/T_Bonds[[#This Row],[Coupons per annum]],0) -> 0 | AW3: =IF( OR( AW$1=MONTH($AP3), AW$1=MONTH($AQ3), AW$1=MONTH($AR3), AW$1=MONTH($AS3)), IF('CF USD'!$A$8="On",$L3,$K3)/T_Bonds[[#This Row],[Coupons per annum]],0) -> 0 | AX3: =IF( OR( AX$1=MONTH($AP3), AX$1=MONTH($AQ3), AX$1=MONTH($AR3), AX$1=MONTH($AS3)), IF('CF USD'!$A$8="On",$L3,$K3)/T_Bonds[[#This Row],[Coupons per annum]],0) -> 0 | AY3: =IF( OR( AY$1=MONTH($AP3), AY$1=MONTH($AQ3), AY$1=MONTH($AR3), AY$1=MONTH($AS3)), IF('CF USD'!$A$8="On",$L3,$K3)/T_Bonds[[#This Row],[Coupons per annum]],0) -> 0 | AZ3: =IF( OR( AZ$1=MONTH($AP3), AZ$1=MONTH($AQ3), AZ$1=MONTH($AR3), AZ$1=MONTH($AS3)), IF('CF USD'!$A$8="On",$L3,$K3)/T_Bonds[[#This Row],[Coupons per annum]],0) -> 0 | BA3: =IF( OR( BA$1=MONTH($AP3), BA$1=MONTH($AQ3), BA$1=MONTH($AR3), BA$1=MONTH($AS3)), IF('CF USD'!$A$8="On",$L3,$K3)/T_Bonds[[#This Row],[Coupons per annum]],0) -> 0 | ... BE3: =IF( OR( BE$1=MONTH($AP3), BE$1=MONTH($AQ3), BE$1=MONTH($AR3), BE$1=MONTH($AS3)), IF('CF USD'!$A$8="On",$L3,$K3)/T_Bonds[[#This Row],[Coupons per annum]],0) -> 0 | BF3: =DAY(T_Bonds[[#This Row],[Next coupon date]]) -> 14
A4: Petrobras, 2034, 6.63% | B4: Personal | C4: =IF(T_Bonds[[#This Row],[Call date]]<>"","Callable","Maturity") -> Maturity | D4: XS0982711474 | E4: GBP | F4: 400000 | G4: =IFERROR(INDEX('V001'!D:E,MATCH(D4,'V001'!D:D,0),2),0) -> 0 | H4: =IFERROR(INDEX(UBS!C:D,MATCH(D4,UBS!D:D,0),1),0) -> 0 | I4: =SUM(T_Bonds[[#This Row],[V1412]:[UBS]]) -> 400000 | J4: 0.06625 | K4: =J4*I4 -> 26500 | L4: =IF(Y4<>1,I4*J4*Y4,I4*J4) -> 35441.1 | M4: 48960 | N4: 0.06953857 | O4: =IFERROR(INDEX(Cbonds!C:H,MATCH(D4,Cbonds!C:C,0),5),0) -> 6.4463968 | P4: =T_Bonds[[#This Row],[Market price]]-T_Bonds[[#This Row],[Cost price]] -> 0.02337 | Q4: =T_Bonds[[#This Row],[Coupon]]/T_Bonds[[#This Row],[Cost price]] -> 0.066481355 | R4: =N4*I4 -> 27815.428 | S4: 0.99652 | T4: =IFERROR(VLOOKUP(D4,'V001'!$D:$J,7,0),0) -> 0 | U4: =IFERROR(S4*T_Bonds[[#This Row],[V1412]]/(T_Bonds[[#This Row],[V1412]]+T_Bonds[[#This Row],[V1430]])+T4*T_Bonds[[#This Row],[V1430]]/(T_Bonds[[#This Row],[V1412]]+T_Bonds[[#This Row],[V1430]]),0) -> 0.99652 | V4: =I4*J4/U4 -> 26592.542 | W4: 1.29331 | X4: =IFERROR(INDEX(Cbonds!C:AF,MATCH(D4,Cbonds!C:C,0),30)/100,0) -> 1.01989 | Y4: =INDEX('Tech list'!A:C,MATCH(T_Bonds[[#This Row],[Risk CCY]],'Tech list'!A:A,0),3) -> 1.3374 | Z4: =T_Bonds[[#This Row],[Market price]]*T_Bonds[[#This Row],[Quantity]] -> 407956 | AA4: =IF(E4<>"USD",X4*Y4*I4,X4*I4) -> 545600.35 | AB4: =T_Bonds[[#This Row],[Market value in CCY]]+T_Bonds[[#This Row],[AI, CCY]] -> 411857.39 | AC4: =T_Bonds[[#This Row],[Market value in USD]]+T_Bonds[[#This Row],[AI, USD]] -> 550818.07 | AD4: =U4*I4 -> 398608 | AE4: =(T_Bonds[[#This Row],[Coupon in Loc.Curr]]/T_Bonds[[#This Row],[Coupons per annum]])*((TODAY()-EDATE(T_Bonds[[#This Row],[Next coupon date]],-12/T_Bonds[[#This Row],[Coupons per annum]])))/(360/T_Bonds[[#This Row],[Coupons per annum]]) -> 3901.3889 | AF4: =T_Bonds[[#This Row],[AI, CCY]]*T_Bonds[[#This Row],[Exchange rate, N]] -> 5217.7175 | AG4: =IFERROR(IF(INDEX(Cbonds!C:AC,MATCH(D4,Cbonds!C:C,0),27)>5000,0,INDEX(Cbonds!C:AC,MATCH(D4,Cbonds!C:C,0),27)),0) -> 0 | AH4: 30 | AK4: Oil and Gas Extraction and Refining | AL4: Brazil | AM4: Emerging Markets | AN4: Petrobras | AO4: 1 | AP4: =IFERROR(INDEX(Cbonds!C:H,MATCH(D4,Cbonds!C:C,0),3),0) -> 46403 | AQ4: =EDATE(T_Bonds[[#This Row],[Next coupon date]],12/T_Bonds[[#This Row],[Coupons per annum]]) -> 46768 | AR4: =EDATE(T_Bonds[[#This Row],[Second next coupon date]],12/$AO4) -> 47134 | AS4: =EDATE(T_Bonds[[#This Row],[Coupon date 3]],12/$AO4) -> 47499 | AT4: =IF( OR( AT$1=MONTH($AP4), AT$1=MONTH($AQ4), AT$1=MONTH($AR4), AT$1=MONTH($AS4)), IF('CF USD'!$A$8="On",$L4,$K4)/T_Bonds[[#This Row],[Coupons per annum]],0) -> 26500 | AU4: =IF( OR( AU$1=MONTH($AP4), AU$1=MONTH($AQ4), AU$1=MONTH($AR4), AU$1=MONTH($AS4)), IF('CF USD'!$A$8="On",$L4,$K4)/T_Bonds[[#This Row],[Coupons per annum]],0) -> 0 | AV4: =IF( OR( AV$1=MONTH($AP4), AV$1=MONTH($AQ4), AV$1=MONTH($AR4), AV$1=MONTH($AS4)), IF('CF USD'!$A$8="On",$L4,$K4)/T_Bonds[[#This Row],[Coupons per annum]],0) -> 0 | AW4: =IF( OR( AW$1=MONTH($AP4), AW$1=MONTH($AQ4), AW$1=MONTH($AR4), AW$1=MONTH($AS4)), IF('CF USD'!$A$8="On",$L4,$K4)/T_Bonds[[#This Row],[Coupons per annum]],0) -> 0 | AX4: =IF( OR( AX$1=MONTH($AP4), AX$1=MONTH($AQ4), AX$1=MONTH($AR4), AX$1=MONTH($AS4)), IF('CF USD'!$A$8="On",$L4,$K4)/T_Bonds[[#This Row],[Coupons per annum]],0) -> 0 | AY4: =IF( OR( AY$1=MONTH($AP4), AY$1=MONTH($AQ4), AY$1=MONTH($AR4), AY$1=MONTH($AS4)), IF('CF USD'!$A$8="On",$L4,$K4)/T_Bonds[[#This Row],[Coupons per annum]],0) -> 0 | AZ4: =IF( OR( AZ$1=MONTH($AP4), AZ$1=MONTH($AQ4), AZ$1=MONTH($AR4), AZ$1=MONTH($AS4)), IF('CF USD'!$A$8="On",$L4,$K4)/T_Bonds[[#This Row],[Coupons per annum]],0) -> 0 | BA4: =IF( OR( BA$1=MONTH($AP4), BA$1=MONTH($AQ4), BA$1=MONTH($AR4), BA$1=MONTH($AS4)), IF('CF USD'!$A$8="On",$L4,$K4)/T_Bonds[[#This Row],[Coupons per annum]],0) -> 0 | ... BE4: =IF( OR( BE$1=MONTH($AP4), BE$1=MONTH($AQ4), BE$1=MONTH($AR4), BE$1=MONTH($AS4)), IF('CF USD'!$A$8="On",$L4,$K4)/T_Bonds[[#This Row],[Coupons per annum]],0) -> 0 | BF4: =DAY(T_Bonds[[#This Row],[Next coupon date]]) -> 16
A5: Ford, 2030, 5.78% | B5: Personal | C5: =IF(T_Bonds[[#This Row],[Call date]]<>"","Callable","Maturity") -> Maturity | D5: XS2892967782 | E5: GBP | F5: 400000 | G5: =IFERROR(INDEX('V001'!D:E,MATCH(D5,'V001'!D:D,0),2),0) -> 0 | H5: =IFERROR(INDEX(UBS!C:D,MATCH(D5,UBS!D:D,0),1),0) -> 0 | I5: =SUM(T_Bonds[[#This Row],[V1412]:[UBS]]) -> 400000 | J5: 0.05757 | K5: =J5*I5 -> 23028 | L5: =IF(Y5<>1,I5*J5*Y5,I5*J5) -> 30797.647 | M5: 47603 | N5: 0.061797716 | O5: =IFERROR(INDEX(Cbonds!C:H,MATCH(D5,Cbonds!C:C,0),5),0) -> 3.7372558 | P5: =T_Bonds[[#This Row],[Market price]]-T_Bonds[[#This Row],[Cost price]] -> 0.0188 | Q5: =T_Bonds[[#This Row],[Coupon]]/T_Bonds[[#This Row],[Cost price]] -> 0.058192661 | R5: =N5*I5 -> 24719.086 | S5: 0.9893 | T5: =IFERROR(VLOOKUP(D5,'V001'!$D:$J,7,0),0) -> 0 | U5: =IFERROR(S5*T_Bonds[[#This Row],[V1412]]/(T_Bonds[[#This Row],[V1412]]+T_Bonds[[#This Row],[V1430]])+T5*T_Bonds[[#This Row],[V1430]]/(T_Bonds[[#This Row],[V1412]]+T_Bonds[[#This Row],[V1430]]),0) -> 0.9893 | V5: =I5*J5/U5 -> 23277.065 | W5: 1.29331 | X5: =IFERROR(INDEX(Cbonds!C:AF,MATCH(D5,Cbonds!C:C,0),30)/100,0) -> 1.0081 | Y5: =INDEX('Tech list'!A:C,MATCH(T_Bonds[[#This Row],[Risk CCY]],'Tech list'!A:A,0),3) -> 1.3374 | Z5: =T_Bonds[[#This Row],[Market price]]*T_Bonds[[#This Row],[Quantity]] -> 403240 | AA5: =IF(E5<>"USD",X5*Y5*I5,X5*I5) -> 539293.18 | AB5: =T_Bonds[[#This Row],[Market value in CCY]]+T_Bonds[[#This Row],[AI, CCY]] -> 423325.53 | AC5: =T_Bonds[[#This Row],[Market value in USD]]+T_Bonds[[#This Row],[AI, USD]] -> 566155.57 | AD5: =U5*I5 -> 395720 | AE5: =(T_Bonds[[#This Row],[Coupon in Loc.Curr]]/T_Bonds[[#This Row],[Coupons per annum]])*((TODAY()-EDATE(T_Bonds[[#This Row],[Next coupon date]],-12/T_Bonds[[#This Row],[Coupons per annum]])))/(360/T_Bonds[[#This Row],[Coupons per annum]]) -> 20085.533 | AF5: =T_Bonds[[#This Row],[AI, CCY]]*T_Bonds[[#This Row],[Exchange rate, N]] -> 26862.392 | AG5: =IFERROR(IF(INDEX(Cbonds!C:AC,MATCH(D5,Cbonds!C:C,0),27)>5000,0,INDEX(Cbonds!C:AC,MATCH(D5,Cbonds!C:C,0),27)),0) -> 0 | AH5: 30 | AK5: Leasing and Rental | AL5: USA | AM5: Developed | AN5: Ford Motor Credit Company | AO5: 1 | AP5: =IFERROR(INDEX(Cbonds!C:H,MATCH(D5,Cbonds!C:C,0),3),0) -> 46142 | AQ5: =EDATE(T_Bonds[[#This Row],[Next coupon date]],12/T_Bonds[[#This Row],[Coupons per annum]]) -> 46507 | AR5: =EDATE(T_Bonds[[#This Row],[Second next coupon date]],12/$AO5) -> 46873 | AS5: =EDATE(T_Bonds[[#This Row],[Coupon date 3]],12/$AO5) -> 47238 | AT5: =IF( OR( AT$1=MONTH($AP5), AT$1=MONTH($AQ5), AT$1=MONTH($AR5), AT$1=MONTH($AS5)), IF('CF USD'!$A$8="On",$L5,$K5)/T_Bonds[[#This Row],[Coupons per annum]],0) -> 0 | AU5: =IF( OR( AU$1=MONTH($AP5), AU$1=MONTH($AQ5), AU$1=MONTH($AR5), AU$1=MONTH($AS5)), IF('CF USD'!$A$8="On",$L5,$K5)/T_Bonds[[#This Row],[Coupons per annum]],0) -> 0 | AV5: =IF( OR( AV$1=MONTH($AP5), AV$1=MONTH($AQ5), AV$1=MONTH($AR5), AV$1=MONTH($AS5)), IF('CF USD'!$A$8="On",$L5,$K5)/T_Bonds[[#This Row],[Coupons per annum]],0) -> 0 | AW5: =IF( OR( AW$1=MONTH($AP5), AW$1=MONTH($AQ5), AW$1=MONTH($AR5), AW$1=MONTH($AS5)), IF('CF USD'!$A$8="On",$L5,$K5)/T_Bonds[[#This Row],[Coupons per annum]],0) -> 23028 | AX5: =IF( OR( AX$1=MONTH($AP5), AX$1=MONTH($AQ5), AX$1=MONTH($AR5), AX$1=MONTH($AS5)), IF('CF USD'!$A$8="On",$L5,$K5)/T_Bonds[[#This Row],[Coupons per annum]],0) -> 0 | AY5: =IF( OR( AY$1=MONTH($AP5), AY$1=MONTH($AQ5), AY$1=MONTH($AR5), AY$1=MONTH($AS5)), IF('CF USD'!$A$8="On",$L5,$K5)/T_Bonds[[#This Row],[Coupons per annum]],0) -> 0 | AZ5: =IF( OR( AZ$1=MONTH($AP5), AZ$1=MONTH($AQ5), AZ$1=MONTH($AR5), AZ$1=MONTH($AS5)), IF('CF USD'!$A$8="On",$L5,$K5)/T_Bonds[[#This Row],[Coupons per annum]],0) -> 0 | BA5: =IF( OR( BA$1=MONTH($AP5), BA$1=MONTH($AQ5), BA$1=MONTH($AR5), BA$1=MONTH($AS5)), IF('CF USD'!$A$8="On",$L5,$K5)/T_Bonds[[#This Row],[Coupons per annum]],0) -> 0 | ... BE5: =IF( OR( BE$1=MONTH($AP5), BE$1=MONTH($AQ5), BE$1=MONTH($AR5), BE$1=MONTH($AS5)), IF('CF USD'!$A$8="On",$L5,$K5)/T_Bonds[[#This Row],[Coupons per annum]],0) -> 0 | BF5: =DAY(T_Bonds[[#This Row],[Next coupon date]]) -> 30
A6: Ørsted, 2042, 5.38% | B6: Personal | C6: =IF(T_Bonds[[#This Row],[Call date]]<>"","Callable","Maturity") -> Maturity | D6: XS2531570112 | E6: GBP | F6: 400000 | G6: =IFERROR(INDEX('V001'!D:E,MATCH(D6,'V001'!D:D,0),2),0) -> 0 | H6: =IFERROR(INDEX(UBS!C:D,MATCH(D6,UBS!D:D,0),1),0) -> 0 | I6: =SUM(T_Bonds[[#This Row],[V1412]:[UBS]]) -> 400000 | J6: 0.05375 | K6: =J6*I6 -> 21500 | L6: =IF(Y6<>1,I6*J6*Y6,I6*J6) -> 28754.1 | M6: 52122 | N6: 0.066017947 | O6: =IFERROR(INDEX(Cbonds!C:H,MATCH(D6,Cbonds!C:C,0),5),0) -> 10.810405 | P6: =T_Bonds[[#This Row],[Market price]]-T_Bonds[[#This Row],[Cost price]] -> -0.02261 | Q6: =T_Bonds[[#This Row],[Coupon]]/T_Bonds[[#This Row],[Cost price]] -> 0.059143275 | R6: =N6*I6 -> 26407.179 | S6: 0.90881 | T6: =IFERROR(VLOOKUP(D6,'V001'!$D:$J,7,0),0) -> 0 | U6: =IFERROR(S6*T_Bonds[[#This Row],[V1412]]/(T_Bonds[[#This Row],[V1412]]+T_Bonds[[#This Row],[V1430]])+T6*T_Bonds[[#This Row],[V1430]]/(T_Bonds[[#This Row],[V1412]]+T_Bonds[[#This Row],[V1430]]),0) -> 0.90881 | V6: =I6*J6/U6 -> 23657.31 | W6: 1.29331 | X6: =IFERROR(INDEX(Cbonds!C:AF,MATCH(D6,Cbonds!C:C,0),30)/100,0) -> 0.8862 | Y6: =INDEX('Tech list'!A:C,MATCH(T_Bonds[[#This Row],[Risk CCY]],'Tech list'!A:A,0),3) -> 1.3374 | Z6: =T_Bonds[[#This Row],[Market price]]*T_Bonds[[#This Row],[Quantity]] -> 354480 | AA6: =IF(E6<>"USD",X6*Y6*I6,X6*I6) -> 474081.55 | AB6: =T_Bonds[[#This Row],[Market value in CCY]]+T_Bonds[[#This Row],[AI, CCY]] -> 365110.56 | AC6: =T_Bonds[[#This Row],[Market value in USD]]+T_Bonds[[#This Row],[AI, USD]] -> 488298.86 | AD6: =U6*I6 -> 363524 | AE6: =(T_Bonds[[#This Row],[Coupon in Loc.Curr]]/T_Bonds[[#This Row],[Coupons per annum]])*((TODAY()-EDATE(T_Bonds[[#This Row],[Next coupon date]],-12/T_Bonds[[#This Row],[Coupons per annum]])))/(360/T_Bonds[[#This Row],[Coupons per annum]]) -> 10630.556 | AF6: =T_Bonds[[#This Row],[AI, CCY]]*T_Bonds[[#This Row],[Exchange rate, N]] -> 14217.305 | AG6: =IFERROR(IF(INDEX(Cbonds!C:AC,MATCH(D6,Cbonds!C:C,0),27)>5000,0,INDEX(Cbonds!C:AC,MATCH(D6,Cbonds!C:C,0),27)),0) -> 0 | AH6: 75 | AK6: Power | AL6: Denmark | AM6: Developed | AN6: Orsted | AO6: 1 | AP6: =IFERROR(INDEX(Cbonds!C:H,MATCH(D6,Cbonds!C:C,0),3),0) -> 46278 | AQ6: =EDATE(T_Bonds[[#This Row],[Next coupon date]],12/T_Bonds[[#This Row],[Coupons per annum]]) -> 46643 | AR6: =EDATE(T_Bonds[[#This Row],[Second next coupon date]],12/$AO6) -> 47009 | AS6: =EDATE(T_Bonds[[#This Row],[Coupon date 3]],12/$AO6) -> 47374 | AT6: =IF( OR( AT$1=MONTH($AP6), AT$1=MONTH($AQ6), AT$1=MONTH($AR6), AT$1=MONTH($AS6)), IF('CF USD'!$A$8="On",$L6,$K6)/T_Bonds[[#This Row],[Coupons per annum]],0) -> 0 | AU6: =IF( OR( AU$1=MONTH($AP6), AU$1=MONTH($AQ6), AU$1=MONTH($AR6), AU$1=MONTH($AS6)), IF('CF USD'!$A$8="On",$L6,$K6)/T_Bonds[[#This Row],[Coupons per annum]],0) -> 0 | AV6: =IF( OR( AV$1=MONTH($AP6), AV$1=MONTH($AQ6), AV$1=MONTH($AR6), AV$1=MONTH($AS6)), IF('CF USD'!$A$8="On",$L6,$K6)/T_Bonds[[#This Row],[Coupons per annum]],0) -> 0 | AW6: =IF( OR( AW$1=MONTH($AP6), AW$1=MONTH($AQ6), AW$1=MONTH($AR6), AW$1=MONTH($AS6)), IF('CF USD'!$A$8="On",$L6,$K6)/T_Bonds[[#This Row],[Coupons per annum]],0) -> 0 | AX6: =IF( OR( AX$1=MONTH($AP6), AX$1=MONTH($AQ6), AX$1=MONTH($AR6), AX$1=MONTH($AS6)), IF('CF USD'!$A$8="On",$L6,$K6)/T_Bonds[[#This Row],[Coupons per annum]],0) -> 0 | AY6: =IF( OR( AY$1=MONTH($AP6), AY$1=MONTH($AQ6), AY$1=MONTH($AR6), AY$1=MONTH($AS6)), IF('CF USD'!$A$8="On",$L6,$K6)/T_Bonds[[#This Row],[Coupons per annum]],0) -> 0 | AZ6: =IF( OR( AZ$1=MONTH($AP6), AZ$1=MONTH($AQ6), AZ$1=MONTH($AR6), AZ$1=MONTH($AS6)), IF('CF USD'!$A$8="On",$L6,$K6)/T_Bonds[[#This Row],[Coupons per annum]],0) -> 0 | BA6: =IF( OR( BA$1=MONTH($AP6), BA$1=MONTH($AQ6), BA$1=MONTH($AR6), BA$1=MONTH($AS6)), IF('CF USD'!$A$8="On",$L6,$K6)/T_Bonds[[#This Row],[Coupons per annum]],0) -> 0 | ... BE6: =IF( OR( BE$1=MONTH($AP6), BE$1=MONTH($AQ6), BE$1=MONTH($AR6), BE$1=MONTH($AS6)), IF('CF USD'!$A$8="On",$L6,$K6)/T_Bonds[[#This Row],[Coupons per annum]],0) -> 0 | BF6: =DAY(T_Bonds[[#This Row],[Next coupon date]]) -> 13
A7: Lloyds 7.50% | B7: Personal | C7: Callable | D7: XS3013997666 | E7: GBP | F7: 600000 | G7: =IFERROR(INDEX('V001'!D:E,MATCH(D7,'V001'!D:D,0),2),0) -> 0 | H7: =IFERROR(INDEX(UBS!C:D,MATCH(D7,UBS!D:D,0),1),0) -> 0 | I7: =SUM(T_Bonds[[#This Row],[V1412]:[UBS]]) -> 600000 | J7: 0.075 | K7: =J7*I7 -> 45000 | L7: =IF(Y7<>1,I7*J7*Y7,I7*J7) -> 60183 | N7: 0.086238967 | O7: =IFERROR(INDEX(Cbonds!C:H,MATCH(D7,Cbonds!C:C,0),5),0) -> 3.736763 | P7: =T_Bonds[[#This Row],[Market price]]-T_Bonds[[#This Row],[Cost price]] -> 0.0583 | Q7: =T_Bonds[[#This Row],[Coupon]]/T_Bonds[[#This Row],[Cost price]] -> 0.075604839 | R7: =N7*I7 -> 51743.38 | S7: 0.992 | T7: 0 | U7: =IFERROR(S7*T_Bonds[[#This Row],[V1412]]/(T_Bonds[[#This Row],[V1412]]+T_Bonds[[#This Row],[V1430]])+T7*T_Bonds[[#This Row],[V1430]]/(T_Bonds[[#This Row],[V1412]]+T_Bonds[[#This Row],[V1430]]),0) -> 0.992 | V7: =I7*J7/U7 -> 45362.903 | W7: 1.29331 | X7: =IFERROR(INDEX(Cbonds!C:AF,MATCH(D7,Cbonds!C:C,0),29)/100,0) -> 1.0503 | Y7: =INDEX('Tech list'!A:C,MATCH(T_Bonds[[#This Row],[Risk CCY]],'Tech list'!A:A,0),3) -> 1.3374 | Z7: =T_Bonds[[#This Row],[Market price]]*T_Bonds[[#This Row],[Quantity]] -> 630180 | AA7: =IF(E7<>"USD",X7*Y7*I7,X7*I7) -> 842802.73 | AB7: =T_Bonds[[#This Row],[Market value in CCY]]+T_Bonds[[#This Row],[AI, CCY]] -> 635305 | AC7: =T_Bonds[[#This Row],[Market value in USD]]+T_Bonds[[#This Row],[AI, USD]] -> 849656.91 | AD7: =U7*I7 -> 595200 | AE7: =T_Bonds[[#This Row],[Coupon in Loc.Curr]]*(TODAY()-EDATE(T_Bonds[[#This Row],[Next coupon date]],-12/T_Bonds[[#This Row],[Coupons per annum]]))/(T_Bonds[[#This Row],[Coupons per annum]]*360) -> 5125 | AF7: =T_Bonds[[#This Row],[AI, CCY]]*T_Bonds[[#This Row],[Exchange rate, N]] -> 6854.175 | AG7: =IFERROR(IF(INDEX(Cbonds!C:AC,MATCH(D7,Cbonds!C:C,0),27)>5000,0,INDEX(Cbonds!C:AC,MATCH(D7,Cbonds!C:C,0),27)),0) -> 0 | AH7: 50 | AI7: 47661 | AJ7: 0.03436 | AK7: AT1 | AL7: United Kingdom | AM7: Developed | AN7: Lloyds Banking Group | AO7: 4 | AP7: 46018 | AQ7: =EDATE(T_Bonds[[#This Row],[Next coupon date]],12/T_Bonds[[#This Row],[Coupons per annum]]) -> 46108 | AR7: =EDATE(T_Bonds[[#This Row],[Second next coupon date]],12/$AO7) -> 46200 | AS7: =EDATE(T_Bonds[[#This Row],[Coupon date 3]],12/$AO7) -> 46292 | AT7: =IF( OR( AT$1=MONTH($AP7), AT$1=MONTH($AQ7), AT$1=MONTH($AR7), AT$1=MONTH($AS7)), IF('CF USD'!$A$8="On",$L7,$K7)/T_Bonds[[#This Row],[Coupons per annum]],0) -> 0 | AU7: =IF( OR( AU$1=MONTH($AP7), AU$1=MONTH($AQ7), AU$1=MONTH($AR7), AU$1=MONTH($AS7)), IF('CF USD'!$A$8="On",$L7,$K7)/T_Bonds[[#This Row],[Coupons per annum]],0) -> 0 | AV7: =IF( OR( AV$1=MONTH($AP7), AV$1=MONTH($AQ7), AV$1=MONTH($AR7), AV$1=MONTH($AS7)), IF('CF USD'!$A$8="On",$L7,$K7)/T_Bonds[[#This Row],[Coupons per annum]],0) -> 11250 | AW7: =IF( OR( AW$1=MONTH($AP7), AW$1=MONTH($AQ7), AW$1=MONTH($AR7), AW$1=MONTH($AS7)), IF('CF USD'!$A$8="On",$L7,$K7)/T_Bonds[[#This Row],[Coupons per annum]],0) -> 0 | AX7: =IF( OR( AX$1=MONTH($AP7), AX$1=MONTH($AQ7), AX$1=MONTH($AR7), AX$1=MONTH($AS7)), IF('CF USD'!$A$8="On",$L7,$K7)/T_Bonds[[#This Row],[Coupons per annum]],0) -> 0 | AY7: =IF( OR( AY$1=MONTH($AP7), AY$1=MONTH($AQ7), AY$1=MONTH($AR7), AY$1=MONTH($AS7)), IF('CF USD'!$A$8="On",$L7,$K7)/T_Bonds[[#This Row],[Coupons per annum]],0) -> 11250 | AZ7: =IF( OR( AZ$1=MONTH($AP7), AZ$1=MONTH($AQ7), AZ$1=MONTH($AR7), AZ$1=MONTH($AS7)), IF('CF USD'!$A$8="On",$L7,$K7)/T_Bonds[[#This Row],[Coupons per annum]],0) -> 0 | BA7: =IF( OR( BA$1=MONTH($AP7), BA$1=MONTH($AQ7), BA$1=MONTH($AR7), BA$1=MONTH($AS7)), IF('CF USD'!$A$8="On",$L7,$K7)/T_Bonds[[#This Row],[Coupons per annum]],0) -> 0 | ... BE7: =IF( OR( BE$1=MONTH($AP7), BE$1=MONTH($AQ7), BE$1=MONTH($AR7), BE$1=MONTH($AS7)), IF('CF USD'!$A$8="On",$L7,$K7)/T_Bonds[[#This Row],[Coupons per annum]],0) -> 11250 | BF7: =DAY(T_Bonds[[#This Row],[Next coupon date]]) -> 27
A8: 7.375% EDF Open End FRN Reg-S Subordinated | B8: Personal | C8: Callable | D8: FR001400SMR0 | E8: GBP | F8: 200000 | G8: =IFERROR(INDEX('V001'!D:E,MATCH(D8,'V001'!D:D,0),2),0) -> 0 | H8: =IFERROR(INDEX(UBS!C:D,MATCH(D8,UBS!D:D,0),1),0) -> 0 | I8: =SUM(T_Bonds[[#This Row],[V1412]:[UBS]]) -> 200000 | J8: =LEFT(A8,FIND("%",A8,1))+1-1 -> 0.07375 | K8: =J8*I8 -> 14750 | L8: =IF(Y8<>1,I8*J8*Y8,I8*J8) -> 19726.65 | M8: 54683 | N8: 0.073 | O8: =IFERROR(INDEX(Cbonds!C:H,MATCH(D8,Cbonds!C:C,0),5),0) -> 6.8068904 | P8: =T_Bonds[[#This Row],[Market price]]-T_Bonds[[#This Row],[Cost price]] -> 0.02545 | Q8: =T_Bonds[[#This Row],[Coupon]]/T_Bonds[[#This Row],[Cost price]] -> 0.072392638 | R8: =N8*I8 -> 14600 | S8: 1.01875 | T8: 0 | U8: =IFERROR(S8*T_Bonds[[#This Row],[V1412]]/(T_Bonds[[#This Row],[V1412]]+T_Bonds[[#This Row],[V1430]])+T8*T_Bonds[[#This Row],[V1430]]/(T_Bonds[[#This Row],[V1412]]+T_Bonds[[#This Row],[V1430]]),0) -> 1.01875 | V8: =I8*J8/U8 -> 14478.528 | W8: 1.29331 | X8: =IFERROR(INDEX(Cbonds!C:AF,MATCH(D8,Cbonds!C:C,0),29)/100,0) -> 1.0442 | Y8: =INDEX('Tech list'!A:C,MATCH(T_Bonds[[#This Row],[Risk CCY]],'Tech list'!A:A,0),3) -> 1.3374 | Z8: =T_Bonds[[#This Row],[Market price]]*T_Bonds[[#This Row],[Quantity]] -> 208840 | AA8: =IF(E8<>"USD",X8*Y8*I8,X8*I8) -> 279302.62 | AB8: =T_Bonds[[#This Row],[Market value in CCY]]+T_Bonds[[#This Row],[AI, CCY]] -> 212404.58 | AC8: =T_Bonds[[#This Row],[Market value in USD]]+T_Bonds[[#This Row],[AI, USD]] -> 284069.89 | AD8: =U8*I8 -> 203750 | AE8: =T_Bonds[[#This Row],[Coupon in Loc.Curr]]*(TODAY()-EDATE(T_Bonds[[#This Row],[Next coupon date]],-12/T_Bonds[[#This Row],[Coupons per annum]]))/(T_Bonds[[#This Row],[Coupons per annum]]*360) -> 3564.5833 | AF8: =T_Bonds[[#This Row],[AI, CCY]]*T_Bonds[[#This Row],[Exchange rate, N]] -> 4767.2737 | AG8: =IFERROR(IF(INDEX(Cbonds!C:AC,MATCH(D8,Cbonds!C:C,0),27)>5000,0,INDEX(Cbonds!C:AC,MATCH(D8,Cbonds!C:C,0),27)),0) -> 0 | AH8: 50 | AI8: 49477 | AJ8: 0.0689 | AK8: Utilities | AL8: France | AM8: Developed | AN8: Electricité de France | AO8: 2 | AP8: 46098 | AQ8: =EDATE(T_Bonds[[#This Row],[Next coupon date]],12/T_Bonds[[#This Row],[Coupons per annum]]) -> 46282 | AR8: =EDATE(T_Bonds[[#This Row],[Second next coupon date]],12/$AO8) -> 46463 | AS8: =EDATE(T_Bonds[[#This Row],[Coupon date 3]],12/$AO8) -> 46647 | AT8: =IF( OR( AT$1=MONTH($AP8), AT$1=MONTH($AQ8), AT$1=MONTH($AR8), AT$1=MONTH($AS8)), IF('CF USD'!$A$8="On",$L8,$K8)/T_Bonds[[#This Row],[Coupons per annum]],0) -> 0 | AU8: =IF( OR( AU$1=MONTH($AP8), AU$1=MONTH($AQ8), AU$1=MONTH($AR8), AU$1=MONTH($AS8)), IF('CF USD'!$A$8="On",$L8,$K8)/T_Bonds[[#This Row],[Coupons per annum]],0) -> 0 | AV8: =IF( OR( AV$1=MONTH($AP8), AV$1=MONTH($AQ8), AV$1=MONTH($AR8), AV$1=MONTH($AS8)), IF('CF USD'!$A$8="On",$L8,$K8)/T_Bonds[[#This Row],[Coupons per annum]],0) -> 7375 | AW8: =IF( OR( AW$1=MONTH($AP8), AW$1=MONTH($AQ8), AW$1=MONTH($AR8), AW$1=MONTH($AS8)), IF('CF USD'!$A$8="On",$L8,$K8)/T_Bonds[[#This Row],[Coupons per annum]],0) -> 0 | AX8: =IF( OR( AX$1=MONTH($AP8), AX$1=MONTH($AQ8), AX$1=MONTH($AR8), AX$1=MONTH($AS8)), IF('CF USD'!$A$8="On",$L8,$K8)/T_Bonds[[#This Row],[Coupons per annum]],0) -> 0 | AY8: =IF( OR( AY$1=MONTH($AP8), AY$1=MONTH($AQ8), AY$1=MONTH($AR8), AY$1=MONTH($AS8)), IF('CF USD'!$A$8="On",$L8,$K8)/T_Bonds[[#This Row],[Coupons per annum]],0) -> 0 | AZ8: =IF( OR( AZ$1=MONTH($AP8), AZ$1=MONTH($AQ8), AZ$1=MONTH($AR8), AZ$1=MONTH($AS8)), IF('CF USD'!$A$8="On",$L8,$K8)/T_Bonds[[#This Row],[Coupons per annum]],0) -> 0 | BA8: =IF( OR( BA$1=MONTH($AP8), BA$1=MONTH($AQ8), BA$1=MONTH($AR8), BA$1=MONTH($AS8)), IF('CF USD'!$A$8="On",$L8,$K8)/T_Bonds[[#This Row],[Coupons per annum]],0) -> 0 | ... BE8: =IF( OR( BE$1=MONTH($AP8), BE$1=MONTH($AQ8), BE$1=MONTH($AR8), BE$1=MONTH($AS8)), IF('CF USD'!$A$8="On",$L8,$K8)/T_Bonds[[#This Row],[Coupons per annum]],0) -> 0 | BF8: =DAY(T_Bonds[[#This Row],[Next coupon date]]) -> 17
A9: 5.391% WarnerMedia 15.03.2062 Senior | B9: Vontobel | C9: =IF(T_Bonds[[#This Row],[Call date]]<>"","Callable","Maturity") -> Maturity | D9: US55903VBF94 | E9: USD | F9: 1000000 | G9: 400000 | H9: =IFERROR(INDEX(UBS!C:D,MATCH(D9,UBS!D:D,0),1),0) -> 0 | I9: =SUM(T_Bonds[[#This Row],[V1412]:[UBS]]) -> 1400000 | J9: =LEFT(A9,FIND("%",A9,1))+1-1 -> 0.05391 | K9: =J9*I9 -> 75474 | L9: =IF(Y9<>1,I9*J9*Y9,I9*J9) -> 75474 | M9: 59245 | N9: =IFERROR(INDEX(Cbonds!C:H,MATCH(D9,Cbonds!C:C,0),4)/100,0) -> 0.096675348 | O9: =IFERROR(INDEX(Cbonds!C:H,MATCH(D9,Cbonds!C:C,0),5),0) -> 10.834692 | P9: =T_Bonds[[#This Row],[Market price]]-T_Bonds[[#This Row],[Cost price]] -> -0.19507034 | Q9: =T_Bonds[[#This Row],[Coupon]]/T_Bonds[[#This Row],[Cost price]] -> 0.069021556 | R9: =N9*I9 -> 135345.49 | S9: 0.77826652 | T9: 0.78804487 | U9: =IFERROR(S9*T_Bonds[[#This Row],[V1412]]/(T_Bonds[[#This Row],[V1412]]+T_Bonds[[#This Row],[V1430]])+T9*T_Bonds[[#This Row],[V1430]]/(T_Bonds[[#This Row],[V1412]]+T_Bonds[[#This Row],[V1430]]),0) -> 0.78106034 | V9: =I9*J9/U9 -> 96630.179 | X9: =IFERROR(INDEX(Cbonds!C:AF,MATCH(D9,Cbonds!C:C,0),30)/100,0) -> 0.58599 | Y9: =INDEX('Tech list'!A:C,MATCH(T_Bonds[[#This Row],[Risk CCY]],'Tech list'!A:A,0),3) -> 1 | Z9: =T_Bonds[[#This Row],[Market price]]*T_Bonds[[#This Row],[Quantity]] -> 820386 | AA9: =IF(E9<>"USD",X9*Y9*I9,X9*I9) -> 820386 | AB9: =T_Bonds[[#This Row],[Market value in CCY]]+T_Bonds[[#This Row],[AI, CCY]] -> 857284.4 | AC9: =T_Bonds[[#This Row],[Market value in USD]]+T_Bonds[[#This Row],[AI, USD]] -> 857284.4 | AD9: =U9*I9 -> 1093484.5 | AE9: =(T_Bonds[[#This Row],[Coupon in Loc.Curr]]/T_Bonds[[#This Row],[Coupons per annum]])*((TODAY()-EDATE(T_Bonds[[#This Row],[Next coupon date]],-12/T_Bonds[[#This Row],[Coupons per annum]])))/(360/T_Bonds[[#This Row],[Coupons per annum]]) -> 36898.4 | AF9: =T_Bonds[[#This Row],[AI, CCY]]*T_Bonds[[#This Row],[Exchange rate, N]] -> 36898.4 | AG9: =IFERROR(IF(INDEX(Cbonds!C:AC,MATCH(D9,Cbonds!C:C,0),27)>5000,0,INDEX(Cbonds!C:AC,MATCH(D9,Cbonds!C:C,0),27)),0) -> 527.12094 | AH9: 75 | AK9: Media | AL9: USA | AM9: Developed | AN9: Warnermedia Holdings | AO9: 2 | AP9: =IFERROR(INDEX(Cbonds!C:H,MATCH(D9,Cbonds!C:C,0),3),0) -> 46096 | AQ9: =EDATE(T_Bonds[[#This Row],[Next coupon date]],12/T_Bonds[[#This Row],[Coupons per annum]]) -> 46280 | AR9: =EDATE(T_Bonds[[#This Row],[Second next coupon date]],12/$AO9) -> 46461 | AS9: =EDATE(T_Bonds[[#This Row],[Coupon date 3]],12/$AO9) -> 46645 | AT9: =IF( OR( AT$1=MONTH($AP9), AT$1=MONTH($AQ9), AT$1=MONTH($AR9), AT$1=MONTH($AS9)), IF('CF USD'!$A$8="On",$L9,$K9)/T_Bonds[[#This Row],[Coupons per annum]],0) -> 0 | AU9: =IF( OR( AU$1=MONTH($AP9), AU$1=MONTH($AQ9), AU$1=MONTH($AR9), AU$1=MONTH($AS9)), IF('CF USD'!$A$8="On",$L9,$K9)/T_Bonds[[#This Row],[Coupons per annum]],0) -> 0 | AV9: =IF( OR( AV$1=MONTH($AP9), AV$1=MONTH($AQ9), AV$1=MONTH($AR9), AV$1=MONTH($AS9)), IF('CF USD'!$A$8="On",$L9,$K9)/T_Bonds[[#This Row],[Coupons per annum]],0) -> 37737 | AW9: =IF( OR( AW$1=MONTH($AP9), AW$1=MONTH($AQ9), AW$1=MONTH($AR9), AW$1=MONTH($AS9)), IF('CF USD'!$A$8="On",$L9,$K9)/T_Bonds[[#This Row],[Coupons per annum]],0) -> 0 | AX9: =IF( OR( AX$1=MONTH($AP9), AX$1=MONTH($AQ9), AX$1=MONTH($AR9), AX$1=MONTH($AS9)), IF('CF USD'!$A$8="On",$L9,$K9)/T_Bonds[[#This Row],[Coupons per annum]],0) -> 0 | AY9: =IF( OR( AY$1=MONTH($AP9), AY$1=MONTH($AQ9), AY$1=MONTH($AR9), AY$1=MONTH($AS9)), IF('CF USD'!$A$8="On",$L9,$K9)/T_Bonds[[#This Row],[Coupons per annum]],0) -> 0 | AZ9: =IF( OR( AZ$1=MONTH($AP9), AZ$1=MONTH($AQ9), AZ$1=MONTH($AR9), AZ$1=MONTH($AS9)), IF('CF USD'!$A$8="On",$L9,$K9)/T_Bonds[[#This Row],[Coupons per annum]],0) -> 0 | BA9: =IF( OR( BA$1=MONTH($AP9), BA$1=MONTH($AQ9), BA$1=MONTH($AR9), BA$1=MONTH($AS9)), IF('CF USD'!$A$8="On",$L9,$K9)/T_Bonds[[#This Row],[Coupons per annum]],0) -> 0 | ... BE9: =IF( OR( BE$1=MONTH($AP9), BE$1=MONTH($AQ9), BE$1=MONTH($AR9), BE$1=MONTH($AS9)), IF('CF USD'!$A$8="On",$L9,$K9)/T_Bonds[[#This Row],[Coupons per annum]],0) -> 0 | BF9: =DAY(T_Bonds[[#This Row],[Next coupon date]]) -> 15
A10: 4.5% Israel 03.04.2120 Senior | B10: Vontobel | C10: =IF(T_Bonds[[#This Row],[Call date]]<>"","Callable","Maturity") -> Maturity | D10: US46513JB593 | E10: USD | F10: 400000 | G10: 400000 | H10: =IFERROR(INDEX(UBS!C:D,MATCH(D10,UBS!D:D,0),1),0) -> 0 | I10: =SUM(T_Bonds[[#This Row],[V1412]:[UBS]]) -> 800000 | J10: =LEFT(A10,FIND("%",A10,1))+1-1 -> 0.045 | K10: =J10*I10 -> 36000 | L10: =IF(Y10<>1,I10*J10*Y10,I10*J10) -> 36000 | M10: 80448 | N10: =IFERROR(INDEX(Cbonds!C:H,MATCH(D10,Cbonds!C:C,0),4)/100,0) -> 0.06178131 | O10: =IFERROR(INDEX(Cbonds!C:H,MATCH(D10,Cbonds!C:C,0),5),0) -> 16.418111 | P10: =T_Bonds[[#This Row],[Market price]]-T_Bonds[[#This Row],[Cost price]] -> 0.007095675 | Q10: =T_Bonds[[#This Row],[Coupon]]/T_Bonds[[#This Row],[Cost price]] -> 0.061374433 | R10: =N10*I10 -> 49425.048 | S10: 0.73320432 | T10: 0.73320432 | U10: =IFERROR(S10*T_Bonds[[#This Row],[V1412]]/(T_Bonds[[#This Row],[V1412]]+T_Bonds[[#This Row],[V1430]])+T10*T_Bonds[[#This Row],[V1430]]/(T_Bonds[[#This Row],[V1412]]+T_Bonds[[#This Row],[V1430]]),0) -> 0.73320432 | V10: =I10*J10/U10 -> 49099.547 | X10: =IFERROR(INDEX(Cbonds!C:AF,MATCH(D10,Cbonds!C:C,0),30)/100,0) -> 0.7403 | Y10: =INDEX('Tech list'!A:C,MATCH(T_Bonds[[#This Row],[Risk CCY]],'Tech list'!A:A,0),3) -> 1 | Z10: =T_Bonds[[#This Row],[Market price]]*T_Bonds[[#This Row],[Quantity]] -> 592240 | AA10: =IF(E10<>"USD",X10*Y10*I10,X10*I10) -> 592240 | AB10: =T_Bonds[[#This Row],[Market value in CCY]]+T_Bonds[[#This Row],[AI, CCY]] -> 608040 | AC10: =T_Bonds[[#This Row],[Market value in USD]]+T_Bonds[[#This Row],[AI, USD]] -> 608040 | AD10: =U10*I10 -> 586563.46 | AE10: =(T_Bonds[[#This Row],[Coupon in Loc.Curr]]/T_Bonds[[#This Row],[Coupons per annum]])*((TODAY()-EDATE(T_Bonds[[#This Row],[Next coupon date]],-12/T_Bonds[[#This Row],[Coupons per annum]])))/(360/T_Bonds[[#This Row],[Coupons per annum]]) -> 15800 | AF10: =T_Bonds[[#This Row],[AI, CCY]]*T_Bonds[[#This Row],[Exchange rate, N]] -> 15800 | AG10: =IFERROR(IF(INDEX(Cbonds!C:AC,MATCH(D10,Cbonds!C:C,0),27)>5000,0,INDEX(Cbonds!C:AC,MATCH(D10,Cbonds!C:C,0),27)),0) -> 142.12336 | AH10: 55 | AK10: Government | AL10: Israel | AM10: Developed | AN10: Israel | AO10: 2 | AP10: =IFERROR(INDEX(Cbonds!C:H,MATCH(D10,Cbonds!C:C,0),3),0) -> 46115 | AQ10: =EDATE(T_Bonds[[#This Row],[Next coupon date]],12/T_Bonds[[#This Row],[Coupons per annum]]) -> 46298 | AR10: =EDATE(T_Bonds[[#This Row],[Second next coupon date]],12/$AO10) -> 46480 | AS10: =EDATE(T_Bonds[[#This Row],[Coupon date 3]],12/$AO10) -> 46663 | AT10: =IF( OR( AT$1=MONTH($AP10), AT$1=MONTH($AQ10), AT$1=MONTH($AR10), AT$1=MONTH($AS10)), IF('CF USD'!$A$8="On",$L10,$K10)/T_Bonds[[#This Row],[Coupons per annum]],0) -> 0 | AU10: =IF( OR( AU$1=MONTH($AP10), AU$1=MONTH($AQ10), AU$1=MONTH($AR10), AU$1=MONTH($AS10)), IF('CF USD'!$A$8="On",$L10,$K10)/T_Bonds[[#This Row],[Coupons per annum]],0) -> 0 | AV10: =IF( OR( AV$1=MONTH($AP10), AV$1=MONTH($AQ10), AV$1=MONTH($AR10), AV$1=MONTH($AS10)), IF('CF USD'!$A$8="On",$L10,$K10)/T_Bonds[[#This Row],[Coupons per annum]],0) -> 0 | AW10: =IF( OR( AW$1=MONTH($AP10), AW$1=MONTH($AQ10), AW$1=MONTH($AR10), AW$1=MONTH($AS10)), IF('CF USD'!$A$8="On",$L10,$K10)/T_Bonds[[#This Row],[Coupons per annum]],0) -> 18000 | AX10: =IF( OR( AX$1=MONTH($AP10), AX$1=MONTH($AQ10), AX$1=MONTH($AR10), AX$1=MONTH($AS10)), IF('CF USD'!$A$8="On",$L10,$K10)/T_Bonds[[#This Row],[Coupons per annum]],0) -> 0 | AY10: =IF( OR( AY$1=MONTH($AP10), AY$1=MONTH($AQ10), AY$1=MONTH($AR10), AY$1=MONTH($AS10)), IF('CF USD'!$A$8="On",$L10,$K10)/T_Bonds[[#This Row],[Coupons per annum]],0) -> 0 | AZ10: =IF( OR( AZ$1=MONTH($AP10), AZ$1=MONTH($AQ10), AZ$1=MONTH($AR10), AZ$1=MONTH($AS10)), IF('CF USD'!$A$8="On",$L10,$K10)/T_Bonds[[#This Row],[Coupons per annum]],0) -> 0 | BA10: =IF( OR( BA$1=MONTH($AP10), BA$1=MONTH($AQ10), BA$1=MONTH($AR10), BA$1=MONTH($AS10)), IF('CF USD'!$A$8="On",$L10,$K10)/T_Bonds[[#This Row],[Coupons per annum]],0) -> 0 | ... BE10: =IF( OR( BE$1=MONTH($AP10), BE$1=MONTH($AQ10), BE$1=MONTH($AR10), BE$1=MONTH($AS10)), IF('CF USD'!$A$8="On",$L10,$K10)/T_Bonds[[#This Row],[Coupons per annum]],0) -> 0 | BF10: =DAY(T_Bonds[[#This Row],[Next coupon date]]) -> 3
A11: intel 3.2 2061 | B11: Vontobel | C11: =IF(T_Bonds[[#This Row],[Call date]]<>"","Callable","Maturity") -> Maturity | D11: US458140bX76 | E11: USD | F11: 200000 | G11: 400000 | H11: =IFERROR(INDEX(UBS!C:D,MATCH(D11,UBS!D:D,0),1),0) -> 0 | I11: =SUM(T_Bonds[[#This Row],[V1412]:[UBS]]) -> 600000 | J11: 0.032 | K11: =J11*I11 -> 19200 | L11: =IF(Y11<>1,I11*J11*Y11,I11*J11) -> 19200 | M11: 59030 | N11: 0.067453316 | O11: 15.709831 | P11: =T_Bonds[[#This Row],[Market price]]-T_Bonds[[#This Row],[Cost price]] -> -0.0253 | Q11: =T_Bonds[[#This Row],[Coupon]]/T_Bonds[[#This Row],[Cost price]] -> 0.053191489 | R11: =N11*I11 -> 40471.989 | S11: 0.5658 | T11: 0.6195 | U11: =IFERROR(S11*T_Bonds[[#This Row],[V1412]]/(T_Bonds[[#This Row],[V1412]]+T_Bonds[[#This Row],[V1430]])+T11*T_Bonds[[#This Row],[V1430]]/(T_Bonds[[#This Row],[V1412]]+T_Bonds[[#This Row],[V1430]]),0) -> 0.6016 | V11: =I11*J11/U11 -> 31914.894 | X11: =IFERROR(INDEX(Cbonds!C:AF,MATCH(D11,Cbonds!C:C,0),30)/100,0) -> 0.5763 | Y11: =INDEX('Tech list'!A:C,MATCH(T_Bonds[[#This Row],[Risk CCY]],'Tech list'!A:A,0),3) -> 1 | Z11: =T_Bonds[[#This Row],[Market price]]*T_Bonds[[#This Row],[Quantity]] -> 345780 | AA11: =IF(E11<>"USD",X11*Y11*I11,X11*I11) -> 345780 | AB11: =T_Bonds[[#This Row],[Market value in CCY]]+T_Bonds[[#This Row],[AI, CCY]] -> 356980 | AC11: =T_Bonds[[#This Row],[Market value in USD]]+T_Bonds[[#This Row],[AI, USD]] -> 356980 | AD11: =U11*I11 -> 360960 | AE11: =(T_Bonds[[#This Row],[Coupon in Loc.Curr]]/T_Bonds[[#This Row],[Coupons per annum]])*((TODAY()-EDATE(T_Bonds[[#This Row],[Next coupon date]],-12/T_Bonds[[#This Row],[Coupons per annum]])))/(360/T_Bonds[[#This Row],[Coupons per annum]]) -> 11200 | AF11: =T_Bonds[[#This Row],[AI, CCY]]*T_Bonds[[#This Row],[Exchange rate, N]] -> 11200 | AG11: =IFERROR(IF(INDEX(Cbonds!C:AC,MATCH(D11,Cbonds!C:C,0),27)>5000,0,INDEX(Cbonds!C:AC,MATCH(D11,Cbonds!C:C,0),27)),0) -> 149.67608 | AH11: 65 | AK11: Semiconductors | AL11: USA | AM11: Developed | AN11: Intel | AO11: 2 | AP11: =IFERROR(INDEX(Cbonds!C:H,MATCH(D11,Cbonds!C:C,0),3),0) -> 46065 | AQ11: =EDATE(T_Bonds[[#This Row],[Next coupon date]],12/T_Bonds[[#This Row],[Coupons per annum]]) -> 46246 | AR11: =EDATE(T_Bonds[[#This Row],[Second next coupon date]],12/$AO11) -> 46430 | AS11: =EDATE(T_Bonds[[#This Row],[Coupon date 3]],12/$AO11) -> 46611 | AT11: =IF( OR( AT$1=MONTH($AP11), AT$1=MONTH($AQ11), AT$1=MONTH($AR11), AT$1=MONTH($AS11)), IF('CF USD'!$A$8="On",$L11,$K11)/T_Bonds[[#This Row],[Coupons per annum]],0) -> 0 | AU11: =IF( OR( AU$1=MONTH($AP11), AU$1=MONTH($AQ11), AU$1=MONTH($AR11), AU$1=MONTH($AS11)), IF('CF USD'!$A$8="On",$L11,$K11)/T_Bonds[[#This Row],[Coupons per annum]],0) -> 9600 | AV11: =IF( OR( AV$1=MONTH($AP11), AV$1=MONTH($AQ11), AV$1=MONTH($AR11), AV$1=MONTH($AS11)), IF('CF USD'!$A$8="On",$L11,$K11)/T_Bonds[[#This Row],[Coupons per annum]],0) -> 0 | AW11: =IF( OR( AW$1=MONTH($AP11), AW$1=MONTH($AQ11), AW$1=MONTH($AR11), AW$1=MONTH($AS11)), IF('CF USD'!$A$8="On",$L11,$K11)/T_Bonds[[#This Row],[Coupons per annum]],0) -> 0 | AX11: =IF( OR( AX$1=MONTH($AP11), AX$1=MONTH($AQ11), AX$1=MONTH($AR11), AX$1=MONTH($AS11)), IF('CF USD'!$A$8="On",$L11,$K11)/T_Bonds[[#This Row],[Coupons per annum]],0) -> 0 | AY11: =IF( OR( AY$1=MONTH($AP11), AY$1=MONTH($AQ11), AY$1=MONTH($AR11), AY$1=MONTH($AS11)), IF('CF USD'!$A$8="On",$L11,$K11)/T_Bonds[[#This Row],[Coupons per annum]],0) -> 0 | AZ11: =IF( OR( AZ$1=MONTH($AP11), AZ$1=MONTH($AQ11), AZ$1=MONTH($AR11), AZ$1=MONTH($AS11)), IF('CF USD'!$A$8="On",$L11,$K11)/T_Bonds[[#This Row],[Coupons per annum]],0) -> 0 | BA11: =IF( OR( BA$1=MONTH($AP11), BA$1=MONTH($AQ11), BA$1=MONTH($AR11), BA$1=MONTH($AS11)), IF('CF USD'!$A$8="On",$L11,$K11)/T_Bonds[[#This Row],[Coupons per annum]],0) -> 9600 | ... BE11: =IF( OR( BE$1=MONTH($AP11), BE$1=MONTH($AQ11), BE$1=MONTH($AR11), BE$1=MONTH($AS11)), IF('CF USD'!$A$8="On",$L11,$K11)/T_Bonds[[#This Row],[Coupons per annum]],0) -> 0 | BF11: =DAY(T_Bonds[[#This Row],[Next coupon date]]) -> 12
A12: Albemarle 5.65 2052 | B12: Vontobel | C12: =IF(T_Bonds[[#This Row],[Call date]]<>"","Callable","Maturity") -> Maturity | D12: US012653AF81 | E12: USD | F12: =IFERROR(INDEX('V004'!D:E,MATCH(D12,'V004'!D:D,0),2),0) -> 400000 | G12: =IFERROR(INDEX('V001'!D:E,MATCH(D12,'V001'!D:D,0),2),0) -> 0 | H12: =IFERROR(INDEX(UBS!C:D,MATCH(D12,UBS!D:D,0),1),0) -> 0 | I12: =SUM(T_Bonds[[#This Row],[V1412]:[UBS]]) -> 400000 | J12: 0.0565 | K12: =J12*I12 -> 22600 | L12: =IF(Y12<>1,I12*J12*Y12,I12*J12) -> 22600 | M12: 55671 | N12: 0.062883827 | O12: 13.8254 | P12: =T_Bonds[[#This Row],[Market price]]-T_Bonds[[#This Row],[Cost price]] -> -0.0154305 | Q12: =T_Bonds[[#This Row],[Coupon]]/T_Bonds[[#This Row],[Cost price]] -> 0.06026731 | R12: =N12*I12 -> 25153.531 | S12: 0.93749 | T12: =IFERROR(VLOOKUP(D12,'V001'!$D:$J,7,0),0) -> 0 | U12: =IFERROR(S12*T_Bonds[[#This Row],[V1412]]/(T_Bonds[[#This Row],[V1412]]+T_Bonds[[#This Row],[V1430]])+T12*T_Bonds[[#This Row],[V1430]]/(T_Bonds[[#This Row],[V1412]]+T_Bonds[[#This Row],[V1430]]),0) -> 0.93749 | V12: =I12*J12/U12 -> 24106.924 | X12: =IFERROR(INDEX(Cbonds!C:AF,MATCH(D12,Cbonds!C:C,0),30)/100,0) -> 0.9220595 | Y12: =INDEX('Tech list'!A:C,MATCH(T_Bonds[[#This Row],[Risk CCY]],'Tech list'!A:A,0),3) -> 1 | Z12: =T_Bonds[[#This Row],[Market price]]*T_Bonds[[#This Row],[Quantity]] -> 368823.8 | AA12: =IF(E12<>"USD",X12*Y12*I12,X12*I12) -> 368823.8 | AB12: =T_Bonds[[#This Row],[Market value in CCY]]+T_Bonds[[#This Row],[AI, CCY]] -> 375038.8 | AC12: =T_Bonds[[#This Row],[Market value in USD]]+T_Bonds[[#This Row],[AI, USD]] -> 375038.8 | AD12: =U12*I12 -> 374996 | AE12: =(T_Bonds[[#This Row],[Coupon in Loc.Curr]]/T_Bonds[[#This Row],[Coupons per annum]])*((TODAY()-EDATE(T_Bonds[[#This Row],[Next coupon date]],-12/T_Bonds[[#This Row],[Coupons per annum]])))/(360/T_Bonds[[#This Row],[Coupons per annum]]) -> 6215 | AF12: =T_Bonds[[#This Row],[AI, CCY]]*T_Bonds[[#This Row],[Exchange rate, N]] -> 6215 | AG12: =IFERROR(IF(INDEX(Cbonds!C:AC,MATCH(D12,Cbonds!C:C,0),27)>5000,0,INDEX(Cbonds!C:AC,MATCH(D12,Cbonds!C:C,0),27)),0) -> 178.3542 | AH12: 65 | AK12: Chemical and petrochemical industry | AL12: USA | AM12: Developed | AN12: Albemarle | AO12: 2 | AP12: =IFERROR(INDEX(Cbonds!C:H,MATCH(D12,Cbonds!C:C,0),3),0) -> 46174 | AQ12: =EDATE(T_Bonds[[#This Row],[Next coupon date]],12/T_Bonds[[#This Row],[Coupons per annum]]) -> 46357 | AR12: =EDATE(T_Bonds[[#This Row],[Second next coupon date]],12/$AO12) -> 46539 | AS12: =EDATE(T_Bonds[[#This Row],[Coupon date 3]],12/$AO12) -> 46722 | AT12: =IF( OR( AT$1=MONTH($AP12), AT$1=MONTH($AQ12), AT$1=MONTH($AR12), AT$1=MONTH($AS12)), IF('CF USD'!$A$8="On",$L12,$K12)/T_Bonds[[#This Row],[Coupons per annum]],0) -> 0 | AU12: =IF( OR( AU$1=MONTH($AP12), AU$1=MONTH($AQ12), AU$1=MONTH($AR12), AU$1=MONTH($AS12)), IF('CF USD'!$A$8="On",$L12,$K12)/T_Bonds[[#This Row],[Coupons per annum]],0) -> 0 | AV12: =IF( OR( AV$1=MONTH($AP12), AV$1=MONTH($AQ12), AV$1=MONTH($AR12), AV$1=MONTH($AS12)), IF('CF USD'!$A$8="On",$L12,$K12)/T_Bonds[[#This Row],[Coupons per annum]],0) -> 0 | AW12: =IF( OR( AW$1=MONTH($AP12), AW$1=MONTH($AQ12), AW$1=MONTH($AR12), AW$1=MONTH($AS12)), IF('CF USD'!$A$8="On",$L12,$K12)/T_Bonds[[#This Row],[Coupons per annum]],0) -> 0 | AX12: =IF( OR( AX$1=MONTH($AP12), AX$1=MONTH($AQ12), AX$1=MONTH($AR12), AX$1=MONTH($AS12)), IF('CF USD'!$A$8="On",$L12,$K12)/T_Bonds[[#This Row],[Coupons per annum]],0) -> 0 | AY12: =IF( OR( AY$1=MONTH($AP12), AY$1=MONTH($AQ12), AY$1=MONTH($AR12), AY$1=MONTH($AS12)), IF('CF USD'!$A$8="On",$L12,$K12)/T_Bonds[[#This Row],[Coupons per annum]],0) -> 11300 | AZ12: =IF( OR( AZ$1=MONTH($AP12), AZ$1=MONTH($AQ12), AZ$1=MONTH($AR12), AZ$1=MONTH($AS12)), IF('CF USD'!$A$8="On",$L12,$K12)/T_Bonds[[#This Row],[Coupons per annum]],0) -> 0 | BA12: =IF( OR( BA$1=MONTH($AP12), BA$1=MONTH($AQ12), BA$1=MONTH($AR12), BA$1=MONTH($AS12)), IF('CF USD'!$A$8="On",$L12,$K12)/T_Bonds[[#This Row],[Coupons per annum]],0) -> 0 | ... BE12: =IF( OR( BE$1=MONTH($AP12), BE$1=MONTH($AQ12), BE$1=MONTH($AR12), BE$1=MONTH($AS12)), IF('CF USD'!$A$8="On",$L12,$K12)/T_Bonds[[#This Row],[Coupons per annum]],0) -> 11300 | BF12: =DAY(T_Bonds[[#This Row],[Next coupon date]]) -> 1
